Workbook
Name L_Customers: '23_SETTINGS'!$H$9:$H$2788
Name L_Status: '23_SETTINGS'!$A$11:$A$15
Name L_RAG: '23_SETTINGS'!$B$11:$B$13
Name L_Priority: '23_SETTINGS'!$C$11:$C$14
Name L_HML: '23_SETTINGS'!$D$11:$D$13
Name L_Prob: '23_SETTINGS'!$E$11:$E$14
Name L_Impact: '23_SETTINGS'!$F$11:$F$14
Name L_RAIDType: '23_SETTINGS'!$A$18:$A$21
Name L_RAIDStatus: '23_SETTINGS'!$B$18:$B$20
Name L_RAIDCategory: '23_SETTINGS'!$C$18:$C$27
Name L_ActionStatus: '23_SETTINGS'!$D$18:$D$21
Name L_ChangeStatus: '23_SETTINGS'!$E$18:$E$20
Name L_ImplStatus: '23_SETTINGS'!$F$18:$F$21
Name L_MilestoneStatus: '23_SETTINGS'!$A$30:$A$34
Name L_TaskStatus: '23_SETTINGS'!$B$30:$B$33
Name L_Dept: '23_SETTINGS'!$C$30:$C$37
Name L_ProjType: '23_SETTINGS'!$D$30:$D$35
Name L_Owner: '23_SETTINGS'!$E$30:$E$37
Name L_Engagement: '23_SETTINGS'!$F$30:$F$34
Name L_Frequency: '23_SETTINGS'!$A$40:$A$46
Name L_YesNo: '23_SETTINGS'!$B$40:$B$41
Name L_RACI: '23_SETTINGS'!$C$40:$C$43
Name L_CostCategory: '23_SETTINGS'!$D$40:$D$47
Name L_ProcStatus: '23_SETTINGS'!$E$40:$E$45
Name L_QualityResult: '23_SETTINGS'!$F$40:$F$43
Name L_MeetingType: '23_SETTINGS'!$A$50:$A$55
Name L_DecisionStatus: '23_SETTINGS'!$B$50:$B$53
Name L_ClosureStatus: '23_SETTINGS'!$C$50:$C$53
Name L_LessonArea: '23_SETTINGS'!$D$50:$D$60
Name L_Channel: '23_SETTINGS'!$E$50:$E$55
Name L_Format: '23_SETTINGS'!$F$50:$F$54
Name L_FilterStatus: '23_SETTINGS'!$A$63:$A$68
Name L_FilterRAG: '23_SETTINGS'!$B$63:$B$66
Name L_FilterMgr: '23_SETTINGS'!$C$63:$C$71
Name L_Projects: '02_PROJECT_PORTFOLIO'!$C$5:$C$34

Sheet 00_HOME
A1: ASSISTANT PMO - MANAGEMENT SYSTEM
A2: Control centre for the portfolio: click any tile to open a sheet, then use the dashboards to brief management.
A3: Nothing here needs typing except the registers themselves - every tile, KPI, chart and count in this workbook is a formula or a hyperlink.
A4: ="PMO CONTROL CENTRE | "&TEXT(TODAY(),"dddd, dd mmmm yyyy")&" | "&COUNTIF('02_PROJECT_PORTFOLIO'!$C$5:$C$34,"?*")&" PROJECTS | "&COUNTIFS('06_RAID_LOG'!$C$5:$C$34,"Risk",'06_RAID_LOG'!$N$5:$N$34,"<>Closed")&" OPEN RISKS | "&COUNTIF('07_ACTION_TRACKER'!$K$5:$K$34,">0")&" OVERDUE ACTIONS | "&COUNTIF('17_DECISION_LOG'!$L$5:$L$34,"Pending")&" DECISIONS PENDING"
A6: NAVIGATION - CLICK ANY TILE TO OPEN THAT SHEET
A7: =HYPERLINK("#'01_EXECUTIVE_DASHBOARD'!A1","01 EXECUTIVE DASHBOARD") | C7: =HYPERLINK("#'01B_PROJECT_DASHBOARD'!A1","01B PROJECT DASHBOARD") | E7: =HYPERLINK("#'02_PROJECT_PORTFOLIO'!A1","02 PROJECT PORTFOLIO") | G7: =HYPERLINK("#'03_PROJECT_CHARTER'!A1","03 PROJECT CHARTER") | I7: =HYPERLINK("#'04_WBS_SCHEDULE'!A1","04 WBS & GANTT") | K7: QUICK STATUS
A8: =HYPERLINK("#'05_MILESTONES'!A1","05 MILESTONES") | C8: =HYPERLINK("#'06_RAID_LOG'!A1","06 RAID LOG") | E8: =HYPERLINK("#'07_ACTION_TRACKER'!A1","07 ACTION TRACKER") | G8: =HYPERLINK("#'08_RACI_MATRIX'!A1","08 RACI MATRIX") | I8: =HYPERLINK("#'09_STAKEHOLDERS'!A1","09 STAKEHOLDERS") | K8: =COUNTIF('02_PROJECT_PORTFOLIO'!$C$5:$C$34,"?*")&" projects in portfolio"
A9: =HYPERLINK("#'10_CHANGE_CONTROL'!A1","10 CHANGE CONTROL") | C9: =HYPERLINK("#'11_COST_MANAGEMENT'!A1","11 COST MANAGEMENT") | E9: =HYPERLINK("#'12_RESOURCE_MANAGEMENT'!A1","12 RESOURCE MANAGEMENT") | G9: =HYPERLINK("#'13_PROCUREMENT'!A1","13 PROCUREMENT") | I9: =HYPERLINK("#'14_QUALITY_CONTROL'!A1","14 QUALITY CONTROL") | K9: =COUNTIFS('06_RAID_LOG'!$C$5:$C$34,"Risk",'06_RAID_LOG'!$N$5:$N$34,"<>Closed")&" open risks"
A10: =HYPERLINK("#'15_WEEKLY_STATUS'!A1","15 WEEKLY STATUS") | C10: =HYPERLINK("#'16_MEETING_MINUTES'!A1","16 MEETING MINUTES") | E10: =HYPERLINK("#'17_DECISION_LOG'!A1","17 DECISION LOG") | G10: =HYPERLINK("#'18_COMMUNICATION_PLAN'!A1","18 COMMUNICATION PLAN") | I10: =HYPERLINK("#'19_PROJECT_CLOSURE'!A1","19 PROJECT CLOSURE") | K10: =COUNTIF('07_ACTION_TRACKER'!$K$5:$K$34,">0")&" overdue actions"
A11: =HYPERLINK("#'20_LESSONS_LEARNED'!A1","20 LESSONS LEARNED") | C11: =HYPERLINK("#'21_PMOSOP'!A1","21 PMO SOP") | E11: =HYPERLINK("#'22_30_60_90_PLAN'!A1","22 30 / 60 / 90 PLAN") | G11: =HYPERLINK("#'23_SETTINGS'!A1","23 SETTINGS") | I11: =HYPERLINK("#'24_DATA_DICTIONARY'!A1","24 DATA DICTIONARY") | K11: =COUNTIF('17_DECISION_LOG'!$L$5:$L$34,"Pending")&" decisions pending"
A13: HOW THIS WORKBOOK IS ORGANISED
A14: GOVERNANCE 03 Project Charter | 08 RACI Matrix | 09 Stakeholders | 10 Change Control | 17 Decision Log | 18 Communication Plan
A15: DELIVERY 02 Project Portfolio | 04 WBS & Gantt | 05 Milestones | 07 Action Tracker | 12 Resources | 13 Procurement | 14 Quality | 22 30-60-90 Plan
A16: CONTROL 06 RAID Log | 11 Cost Management | 15 Weekly Status | 16 Meeting Minutes | 19 Project Closure | 20 Lessons Learned | 21 PMO SOP
A17: REPORTING 01 Executive Dashboard | 01B Project Dashboard | 23 Settings | 24 Data Dictionary
A19: TODAY'S PRIORITIES - READ THIS BEFORE THE MANAGEMENT MEETING
A20: ="1. "&COUNTIF('07_ACTION_TRACKER'!$K$5:$K$34,">0")&" actions overdue (worst "&MAX('07_ACTION_TRACKER'!$K$5:$K$34)&" days) - open 07_ACTION_TRACKER"
A21: ="2. "&COUNTIFS('05_MILESTONES'!$F$5:$F$34,">0",'05_MILESTONES'!$F$5:$F$34,"<"&TODAY(),'05_MILESTONES'!$H$5:$H$34,"<>Complete")&" milestones overdue - open 05_MILESTONES"
A22: ="3. "&COUNTIFS('06_RAID_LOG'!$C$5:$C$34,"Risk",'06_RAID_LOG'!$I$5:$I$34,"Critical",'06_RAID_LOG'!$N$5:$N$34,"<>Closed")&" critical risks open - open 06_RAID_LOG"
A23: ="4. "&COUNTIF('10_CHANGE_CONTROL'!$N$5:$N$34,"Pending")&" change requests awaiting approval - open 10_CHANGE_CONTROL"
A24: ="5. "&COUNTIF('17_DECISION_LOG'!$L$5:$L$34,"Pending")&" decisions pending - open 17_DECISION_LOG"
A26: EVERYTHING IS AUTOMATIC: drop-downs come from 23_SETTINGS, KPIs and charts come from the registers, and the dashboards refresh the moment a register changes. Sample records are marked SAMPLE in their Notes column - delete them whenever you like.

Sheet 01_EXECUTIVE_DASHBOARD
A1: EXECUTIVE DASHBOARD | P1: AUTOMATIC CHART DATA - FORMULAS ONLY, DO NOT EDIT
A2: Live portfolio control panel: 14 KPIs, management attention panels, next milestones, a filterable portfolio view and 10 charts - every figure is a formula.
A3: All values calculate from the registers (portfolio, RAID, actions, milestones, changes, decisions). Change a register and this sheet updates automatically. | P3: BLOCK 1 - PROJECT STATUS
A4: ="PORTFOLIO: "&A6&" PROJECTS | ACTIVE: "&C6&" | ON TRACK: "&E6&" | AT RISK: "&G6&" | DELAYED: "&I6&" | OPEN RISKS: "&M6&" | OVERDUE ACTIONS: "&C10&" | DECISIONS PENDING: "&M10&" | AS AT "&TEXT(TODAY(),"DD MMM YYYY") | P4: Status | Q4: Projects
A5: TOTAL PROJECTS | C5: ACTIVE PROJECTS | E5: ON TRACK | G5: AT RISK | I5: DELAYED | K5: COMPLETED | M5: OPEN RISKS | P5: Not Started | Q5: =COUNTIF('02_PROJECT_PORTFOLIO'!$M$5:$M$34,P5)
A6: =COUNTIF('02_PROJECT_PORTFOLIO'!$C$5:$C$34,"?*") | C6: =COUNTIF('02_PROJECT_PORTFOLIO'!$M$5:$M$34,"Active") | E6: =COUNTIFS('02_PROJECT_PORTFOLIO'!$N$5:$N$34,"Green",'02_PROJECT_PORTFOLIO'!$M$5:$M$34,"<>Completed",'02_PROJECT_PORTFOLIO'!$M$5:$M$34,"<>Cancelled") | G6: =COUNTIF('02_PROJECT_PORTFOLIO'!$N$5:$N$34,"Yellow") | I6: =COUNTIF('02_PROJECT_PORTFOLIO'!$N$5:$N$34,"Red") | K6: =COUNTIF('02_PROJECT_PORTFOLIO'!$M$5:$M$34,"Completed") | M6: =COUNTIFS('06_RAID_LOG'!$C$5:$C$34,"Risk",'06_RAID_LOG'!$N$5:$N$34,"<>Closed") | P6: Active | Q6: =COUNTIF('02_PROJECT_PORTFOLIO'!$M$5:$M$34,P6)
A7: REGISTERED IN PORTFOLIO | C7: =TEXT(IFERROR(C6/A6,0),"0%")&" OF PORTFOLIO" | E7: GREEN RAG, IN FLIGHT | G7: YELLOW RAG - WATCH | I7: RED RAG - ACT NOW | K7: CLOSED / IN CLOSURE | M7: ="CRITICAL: "&COUNTIFS('06_RAID_LOG'!$C$5:$C$34,"Risk",'06_RAID_LOG'!$I$5:$I$34,"Critical",'06_RAID_LOG'!$N$5:$N$34,"<>Closed") | P7: On Hold | Q7: =COUNTIF('02_PROJECT_PORTFOLIO'!$M$5:$M$34,P7)
P8: Completed | Q8: =COUNTIF('02_PROJECT_PORTFOLIO'!$M$5:$M$34,P8)
A9: OPEN ISSUES | C9: OVERDUE ACTIONS | E9: APPROVED AMOUNT | G9: ACTUAL COST | I9: FORECAST COST | K9: MILESTONES DUE 7 DAYS | M9: PENDING DECISIONS | P9: Cancelled | Q9: =COUNTIF('02_PROJECT_PORTFOLIO'!$M$5:$M$34,P9)
A10: =COUNTIFS('06_RAID_LOG'!$C$5:$C$34,"Issue",'06_RAID_LOG'!$N$5:$N$34,"<>Closed") | C10: =COUNTIF('07_ACTION_TRACKER'!$K$5:$K$34,">0") | E10: =SUM('02_PROJECT_PORTFOLIO'!$O$5:$O$34) | G10: =SUM('02_PROJECT_PORTFOLIO'!$P$5:$P$34) | I10: =SUM('02_PROJECT_PORTFOLIO'!$Q$5:$Q$34) | K10: =COUNTIFS('05_MILESTONES'!$F$5:$F$34,">="&TODAY(),'05_MILESTONES'!$F$5:$F$34,"<="&TODAY()+7,'05_MILESTONES'!$H$5:$H$34,"<>Complete") | M10: =COUNTIF('17_DECISION_LOG'!$L$5:$L$34,"Pending")
A11: ="ESCALATED: "&COUNTIFS('06_RAID_LOG'!$C$5:$C$34,"Issue",'06_RAID_LOG'!$N$5:$N$34,"<>Closed",'06_RAID_LOG'!$O$5:$O$34,"Yes") | C11: ="WORST: "&MAX('07_ACTION_TRACKER'!$K$5:$K$34)&" DAYS LATE" | E11: TOTAL APPROVED | G11: =TEXT(IFERROR(G10/E10,0),"0%")&" OF APPROVED" | I11: =IF(I10>E10,"OVER APPROVED BY "&TEXT(I10-E10,"#,##0"),"WITHIN APPROVED") | K11: ="OVERDUE: "&COUNTIFS('05_MILESTONES'!$F$5:$F$34,">0",'05_MILESTONES'!$F$5:$F$34,"<"&TODAY(),'05_MILESTONES'!$H$5:$H$34,"<>Complete") | M11: ="CHANGES PENDING: "&COUNTIF('10_CHANGE_CONTROL'!$N$5:$N$34,"Pending") | P11: BLOCK 2 - PROJECT RAG
P12: RAG | Q12: Projects
A13: MANAGEMENT ATTENTION - WHAT NEEDS A DECISION THIS WEEK | P13: Green | Q13: =COUNTIF('02_PROJECT_PORTFOLIO'!$N$5:$N$34,P13)
A14: ="RED / DELAYED PROJECTS ("&COUNTIF('02_PROJECT_PORTFOLIO'!$N$5:$N$34,"Red")&")" | H14: ="TOP OPEN RISKS BY SCORE ("&COUNTIFS('06_RAID_LOG'!$C$5:$C$34,"Risk",'06_RAID_LOG'!$N$5:$N$34,"<>Closed")&")" | P14: Yellow | Q14: =COUNTIF('02_PROJECT_PORTFOLIO'!$N$5:$N$34,P14)
A15: ="•"&IFERROR(INDEX('02_PROJECT_PORTFOLIO'!$C$5:$C$34,MATCH(1,'02_PROJECT_PORTFOLIO'!$Z$5:$Z$34,0))&" ["&INDEX('02_PROJECT_PORTFOLIO'!$M$5:$M$34,MATCH(1,'02_PROJECT_PORTFOLIO'!$Z$5:$Z$34,0))&"] "&INDEX('02_PROJECT_PORTFOLIO'!$D$5:$D$34,MATCH(1,'02_PROJECT_PORTFOLIO'!$Z$5:$Z$34,0))&" - forecast "&TEXT(INDEX('02_PROJECT_PORTFOLIO'!$J$5:$J$34,MATCH(1,'02_PROJECT_PORTFOLIO'!$Z$5:$Z$34,0)),"dd-mmm-yy"),"") | H15: ="•"&IFERROR(INDEX('06_RAID_LOG'!$D$5:$D$34,MATCH(1,'06_RAID_LOG'!$S$5:$S$34,0))&" ("&INDEX('06_RAID_LOG'!$I$5:$I$34,MATCH(1,'06_RAID_LOG'!$S$5:$S$34,0))&" - "&INDEX('06_RAID_LOG'!$B$5:$B$34,MATCH(1,'06_RAID_LOG'!$S$5:$S$34,0))&")","") | P15: Red | Q15: =COUNTIF('02_PROJECT_PORTFOLIO'!$N$5:$N$34,P15)
A16: ="•"&IFERROR(INDEX('02_PROJECT_PORTFOLIO'!$C$5:$C$34,MATCH(2,'02_PROJECT_PORTFOLIO'!$Z$5:$Z$34,0))&" ["&INDEX('02_PROJECT_PORTFOLIO'!$M$5:$M$34,MATCH(2,'02_PROJECT_PORTFOLIO'!$Z$5:$Z$34,0))&"] "&INDEX('02_PROJECT_PORTFOLIO'!$D$5:$D$34,MATCH(2,'02_PROJECT_PORTFOLIO'!$Z$5:$Z$34,0))&" - forecast "&TEXT(INDEX('02_PROJECT_PORTFOLIO'!$J$5:$J$34,MATCH(2,'02_PROJECT_PORTFOLIO'!$Z$5:$Z$34,0)),"dd-mmm-yy"),"") | H16: ="•"&IFERROR(INDEX('06_RAID_LOG'!$D$5:$D$34,MATCH(2,'06_RAID_LOG'!$S$5:$S$34,0))&" ("&INDEX('06_RAID_LOG'!$I$5:$I$34,MATCH(2,'06_RAID_LOG'!$S$5:$S$34,0))&" - "&INDEX('06_RAID_LOG'!$B$5:$B$34,MATCH(2,'06_RAID_LOG'!$S$5:$S$34,0))&")","")
A17: ="•"&IFERROR(INDEX('02_PROJECT_PORTFOLIO'!$C$5:$C$34,MATCH(3,'02_PROJECT_PORTFOLIO'!$Z$5:$Z$34,0))&" ["&INDEX('02_PROJECT_PORTFOLIO'!$M$5:$M$34,MATCH(3,'02_PROJECT_PORTFOLIO'!$Z$5:$Z$34,0))&"] "&INDEX('02_PROJECT_PORTFOLIO'!$D$5:$D$34,MATCH(3,'02_PROJECT_PORTFOLIO'!$Z$5:$Z$34,0))&" - forecast "&TEXT(INDEX('02_PROJECT_PORTFOLIO'!$J$5:$J$34,MATCH(3,'02_PROJECT_PORTFOLIO'!$Z$5:$Z$34,0)),"dd-mmm-yy"),"") | H17: ="•"&IFERROR(INDEX('06_RAID_LOG'!$D$5:$D$34,MATCH(3,'06_RAID_LOG'!$S$5:$S$34,0))&" ("&INDEX('06_RAID_LOG'!$I$5:$I$34,MATCH(3,'06_RAID_LOG'!$S$5:$S$34,0))&" - "&INDEX('06_RAID_LOG'!$B$5:$B$34,MATCH(3,'06_RAID_LOG'!$S$5:$S$34,0))&")","") | P17: BLOCK 3 - PROJECT COMPLETION
A18: ="•"&IFERROR(INDEX('02_PROJECT_PORTFOLIO'!$C$5:$C$34,MATCH(4,'02_PROJECT_PORTFOLIO'!$Z$5:$Z$34,0))&" ["&INDEX('02_PROJECT_PORTFOLIO'!$M$5:$M$34,MATCH(4,'02_PROJECT_PORTFOLIO'!$Z$5:$Z$34,0))&"] "&INDEX('02_PROJECT_PORTFOLIO'!$D$5:$D$34,MATCH(4,'02_PROJECT_PORTFOLIO'!$Z$5:$Z$34,0))&" - forecast "&TEXT(INDEX('02_PROJECT_PORTFOLIO'!$J$5:$J$34,MATCH(4,'02_PROJECT_PORTFOLIO'!$Z$5:$Z$34,0)),"dd-mmm-yy"),"") | H18: ="•"&IFERROR(INDEX('06_RAID_LOG'!$D$5:$D$34,MATCH(4,'06_RAID_LOG'!$S$5:$S$34,0))&" ("&INDEX('06_RAID_LOG'!$I$5:$I$34,MATCH(4,'06_RAID_LOG'!$S$5:$S$34,0))&" - "&INDEX('06_RAID_LOG'!$B$5:$B$34,MATCH(4,'06_RAID_LOG'!$S$5:$S$34,0))&")","") | P18: Project | Q18: % Complete
A19: ="•"&IFERROR(INDEX('02_PROJECT_PORTFOLIO'!$C$5:$C$34,MATCH(5,'02_PROJECT_PORTFOLIO'!$Z$5:$Z$34,0))&" ["&INDEX('02_PROJECT_PORTFOLIO'!$M$5:$M$34,MATCH(5,'02_PROJECT_PORTFOLIO'!$Z$5:$Z$34,0))&"] "&INDEX('02_PROJECT_PORTFOLIO'!$D$5:$D$34,MATCH(5,'02_PROJECT_PORTFOLIO'!$Z$5:$Z$34,0))&" - forecast "&TEXT(INDEX('02_PROJECT_PORTFOLIO'!$J$5:$J$34,MATCH(5,'02_PROJECT_PORTFOLIO'!$Z$5:$Z$34,0)),"dd-mmm-yy"),"") | H19: ="•"&IFERROR(INDEX('06_RAID_LOG'!$D$5:$D$34,MATCH(5,'06_RAID_LOG'!$S$5:$S$34,0))&" ("&INDEX('06_RAID_LOG'!$I$5:$I$34,MATCH(5,'06_RAID_LOG'!$S$5:$S$34,0))&" - "&INDEX('06_RAID_LOG'!$B$5:$B$34,MATCH(5,'06_RAID_LOG'!$S$5:$S$34,0))&")","") | P19: =IFERROR(INDEX('02_PROJECT_PORTFOLIO'!$C$5:$C$34,MATCH(1,'02_PROJECT_PORTFOLIO'!$Y$5:$Y$34,0)),"") | Q19: =IF($P19="","",INDEX('02_PROJECT_PORTFOLIO'!$L$5:$L$34,MATCH($P19,'02_PROJECT_PORTFOLIO'!$C$5:$C$34,0)))
P20: =IFERROR(INDEX('02_PROJECT_PORTFOLIO'!$C$5:$C$34,MATCH(2,'02_PROJECT_PORTFOLIO'!$Y$5:$Y$34,0)),"") | Q20: =IF($P20="","",INDEX('02_PROJECT_PORTFOLIO'!$L$5:$L$34,MATCH($P20,'02_PROJECT_PORTFOLIO'!$C$5:$C$34,0)))
A21: ="OVERDUE ACTIONS ("&COUNTIF('07_ACTION_TRACKER'!$K$5:$K$34,">0")&")" | H21: ="PENDING APPROVALS & DECISIONS" | P21: =IFERROR(INDEX('02_PROJECT_PORTFOLIO'!$C$5:$C$34,MATCH(3,'02_PROJECT_PORTFOLIO'!$Y$5:$Y$34,0)),"") | Q21: =IF($P21="","",INDEX('02_PROJECT_PORTFOLIO'!$L$5:$L$34,MATCH($P21,'02_PROJECT_PORTFOLIO'!$C$5:$C$34,0)))
A22: ="•"&IFERROR(INDEX('07_ACTION_TRACKER'!$E$5:$E$34,MATCH(1,'07_ACTION_TRACKER'!$O$5:$O$34,0))&": "&LEFT(INDEX('07_ACTION_TRACKER'!$D$5:$D$34,MATCH(1,'07_ACTION_TRACKER'!$O$5:$O$34,0)),42)&" ("&INDEX('07_ACTION_TRACKER'!$K$5:$K$34,MATCH(1,'07_ACTION_TRACKER'!$O$5:$O$34,0))&"d late)","") | H22: ="•"&IFERROR(INDEX('10_CHANGE_CONTROL'!$A$5:$A$34,MATCH(1,'10_CHANGE_CONTROL'!$T$5:$T$34,0))&" "&LEFT(INDEX('10_CHANGE_CONTROL'!$E$5:$E$34,MATCH(1,'10_CHANGE_CONTROL'!$T$5:$T$34,0)),44)&" ["&TEXT(INDEX('10_CHANGE_CONTROL'!$I$5:$I$34,MATCH(1,'10_CHANGE_CONTROL'!$T$5:$T$34,0)),"#,##0")&"]","") | P22: =IFERROR(INDEX('02_PROJECT_PORTFOLIO'!$C$5:$C$34,MATCH(4,'02_PROJECT_PORTFOLIO'!$Y$5:$Y$34,0)),"") | Q22: =IF($P22="","",INDEX('02_PROJECT_PORTFOLIO'!$L$5:$L$34,MATCH($P22,'02_PROJECT_PORTFOLIO'!$C$5:$C$34,0)))
A23: ="•"&IFERROR(INDEX('07_ACTION_TRACKER'!$E$5:$E$34,MATCH(2,'07_ACTION_TRACKER'!$O$5:$O$34,0))&": "&LEFT(INDEX('07_ACTION_TRACKER'!$D$5:$D$34,MATCH(2,'07_ACTION_TRACKER'!$O$5:$O$34,0)),42)&" ("&INDEX('07_ACTION_TRACKER'!$K$5:$K$34,MATCH(2,'07_ACTION_TRACKER'!$O$5:$O$34,0))&"d late)","") | H23: ="•"&IFERROR(INDEX('10_CHANGE_CONTROL'!$A$5:$A$34,MATCH(2,'10_CHANGE_CONTROL'!$T$5:$T$34,0))&" "&LEFT(INDEX('10_CHANGE_CONTROL'!$E$5:$E$34,MATCH(2,'10_CHANGE_CONTROL'!$T$5:$T$34,0)),44)&" ["&TEXT(INDEX('10_CHANGE_CONTROL'!$I$5:$I$34,MATCH(2,'10_CHANGE_CONTROL'!$T$5:$T$34,0)),"#,##0")&"]","") | P23: =IFERROR(INDEX('02_PROJECT_PORTFOLIO'!$C$5:$C$34,MATCH(5,'02_PROJECT_PORTFOLIO'!$Y$5:$Y$34,0)),"") | Q23: =IF($P23="","",INDEX('02_PROJECT_PORTFOLIO'!$L$5:$L$34,MATCH($P23,'02_PROJECT_PORTFOLIO'!$C$5:$C$34,0)))
A24: ="•"&IFERROR(INDEX('07_ACTION_TRACKER'!$E$5:$E$34,MATCH(3,'07_ACTION_TRACKER'!$O$5:$O$34,0))&": "&LEFT(INDEX('07_ACTION_TRACKER'!$D$5:$D$34,MATCH(3,'07_ACTION_TRACKER'!$O$5:$O$34,0)),42)&" ("&INDEX('07_ACTION_TRACKER'!$K$5:$K$34,MATCH(3,'07_ACTION_TRACKER'!$O$5:$O$34,0))&"d late)","") | H24: ="•"&IFERROR(INDEX('10_CHANGE_CONTROL'!$A$5:$A$34,MATCH(3,'10_CHANGE_CONTROL'!$T$5:$T$34,0))&" "&LEFT(INDEX('10_CHANGE_CONTROL'!$E$5:$E$34,MATCH(3,'10_CHANGE_CONTROL'!$T$5:$T$34,0)),44)&" ["&TEXT(INDEX('10_CHANGE_CONTROL'!$I$5:$I$34,MATCH(3,'10_CHANGE_CONTROL'!$T$5:$T$34,0)),"#,##0")&"]","") | P24: =IFERROR(INDEX('02_PROJECT_PORTFOLIO'!$C$5:$C$34,MATCH(6,'02_PROJECT_PORTFOLIO'!$Y$5:$Y$34,0)),"") | Q24: =IF($P24="","",INDEX('02_PROJECT_PORTFOLIO'!$L$5:$L$34,MATCH($P24,'02_PROJECT_PORTFOLIO'!$C$5:$C$34,0)))
A25: ="•"&IFERROR(INDEX('07_ACTION_TRACKER'!$E$5:$E$34,MATCH(4,'07_ACTION_TRACKER'!$O$5:$O$34,0))&": "&LEFT(INDEX('07_ACTION_TRACKER'!$D$5:$D$34,MATCH(4,'07_ACTION_TRACKER'!$O$5:$O$34,0)),42)&" ("&INDEX('07_ACTION_TRACKER'!$K$5:$K$34,MATCH(4,'07_ACTION_TRACKER'!$O$5:$O$34,0))&"d late)","") | H25: ="•"&"Decisions pending: "&COUNTIF('17_DECISION_LOG'!$L$5:$L$34,"Pending")&" | decisions overdue: "&COUNTIFS('17_DECISION_LOG'!$L$5:$L$34,"Pending",'17_DECISION_LOG'!$K$5:$K$34,"<"&TODAY())&" | milestones overdue: "&COUNTIFS('05_MILESTONES'!$F$5:$F$34,">0",'05_MILESTONES'!$F$5:$F$34,"<"&TODAY(),'05_MILESTONES'!$H$5:$H$34,"<>Complete") | P25: =IFERROR(INDEX('02_PROJECT_PORTFOLIO'!$C$5:$C$34,MATCH(7,'02_PROJECT_PORTFOLIO'!$Y$5:$Y$34,0)),"") | Q25: =IF($P25="","",INDEX('02_PROJECT_PORTFOLIO'!$L$5:$L$34,MATCH($P25,'02_PROJECT_PORTFOLIO'!$C$5:$C$34,0)))
A26: ="•"&IFERROR(INDEX('07_ACTION_TRACKER'!$E$5:$E$34,MATCH(5,'07_ACTION_TRACKER'!$O$5:$O$34,0))&": "&LEFT(INDEX('07_ACTION_TRACKER'!$D$5:$D$34,MATCH(5,'07_ACTION_TRACKER'!$O$5:$O$34,0)),42)&" ("&INDEX('07_ACTION_TRACKER'!$K$5:$K$34,MATCH(5,'07_ACTION_TRACKER'!$O$5:$O$34,0))&"d late)","") | H26: ="•"&"Pending change value: "&TEXT(SUMIFS('10_CHANGE_CONTROL'!$I$5:$I$34,'10_CHANGE_CONTROL'!$N$5:$N$34,"Pending"),"#,##0")&" | quality failures: "&COUNTIF('14_QUALITY_CONTROL'!$H$5:$H$34,"Fail")&" | closure items open: "&COUNTIFS('19_PROJECT_CLOSURE'!$F$5:$F$34,"<>Complete",'19_PROJECT_CLOSURE'!$F$5:$F$34,"<>N/A",'19_PROJECT_CLOSURE'!$A$5:$A$34,"?*") | P26: =IFERROR(INDEX('02_PROJECT_PORTFOLIO'!$C$5:$C$34,MATCH(8,'02_PROJECT_PORTFOLIO'!$Y$5:$Y$34,0)),"") | Q26: =IF($P26="","",INDEX('02_PROJECT_PORTFOLIO'!$L$5:$L$34,MATCH($P26,'02_PROJECT_PORTFOLIO'!$C$5:$C$34,0)))
P27: =IFERROR(INDEX('02_PROJECT_PORTFOLIO'!$C$5:$C$34,MATCH(9,'02_PROJECT_PORTFOLIO'!$Y$5:$Y$34,0)),"") | Q27: =IF($P27="","",INDEX('02_PROJECT_PORTFOLIO'!$L$5:$L$34,MATCH($P27,'02_PROJECT_PORTFOLIO'!$C$5:$C$34,0)))
A28: NEXT 10 MILESTONES - AUTOMATIC, CLOSEST FORECAST DATE FIRST | P28: =IFERROR(INDEX('02_PROJECT_PORTFOLIO'!$C$5:$C$34,MATCH(10,'02_PROJECT_PORTFOLIO'!$Y$5:$Y$34,0)),"") | Q28: =IF($P28="","",INDEX('02_PROJECT_PORTFOLIO'!$L$5:$L$34,MATCH($P28,'02_PROJECT_PORTFOLIO'!$C$5:$C$34,0)))
A29: MILESTONE | E29: PROJECT | H29: OWNER | J29: FORECAST DATE | L29: DAYS | N29: RAG
A30: =IFERROR(INDEX('05_MILESTONES'!$C$5:$C$34,MATCH(SMALL('05_MILESTONES'!$M$5:$M$34,1),'05_MILESTONES'!$M$5:$M$34,0)),"") | E30: =IFERROR(INDEX('05_MILESTONES'!$B$5:$B$34,MATCH(SMALL('05_MILESTONES'!$M$5:$M$34,1),'05_MILESTONES'!$M$5:$M$34,0)),"") | H30: =IFERROR(INDEX('05_MILESTONES'!$D$5:$D$34,MATCH(SMALL('05_MILESTONES'!$M$5:$M$34,1),'05_MILESTONES'!$M$5:$M$34,0)),"") | J30: =IFERROR(INDEX('05_MILESTONES'!$F$5:$F$34,MATCH(SMALL('05_MILESTONES'!$M$5:$M$34,1),'05_MILESTONES'!$M$5:$M$34,0)),"") | L30: =IFERROR(INDEX('05_MILESTONES'!$I$5:$I$34,MATCH(SMALL('05_MILESTONES'!$M$5:$M$34,1),'05_MILESTONES'!$M$5:$M$34,0)),"") | N30: =IFERROR(INDEX('05_MILESTONES'!$K$5:$K$34,MATCH(SMALL('05_MILESTONES'!$M$5:$M$34,1),'05_MILESTONES'!$M$5:$M$34,0)),"") | P30: BLOCK 4 - PLANNED vs ACTUAL PROGRESS
A31: =IFERROR(INDEX('05_MILESTONES'!$C$5:$C$34,MATCH(SMALL('05_MILESTONES'!$M$5:$M$34,2),'05_MILESTONES'!$M$5:$M$34,0)),"") | E31: =IFERROR(INDEX('05_MILESTONES'!$B$5:$B$34,MATCH(SMALL('05_MILESTONES'!$M$5:$M$34,2),'05_MILESTONES'!$M$5:$M$34,0)),"") | H31: =IFERROR(INDEX('05_MILESTONES'!$D$5:$D$34,MATCH(SMALL('05_MILESTONES'!$M$5:$M$34,2),'05_MILESTONES'!$M$5:$M$34,0)),"") | J31: =IFERROR(INDEX('05_MILESTONES'!$F$5:$F$34,MATCH(SMALL('05_MILESTONES'!$M$5:$M$34,2),'05_MILESTONES'!$M$5:$M$34,0)),"") | L31: =IFERROR(INDEX('05_MILESTONES'!$I$5:$I$34,MATCH(SMALL('05_MILESTONES'!$M$5:$M$34,2),'05_MILESTONES'!$M$5:$M$34,0)),"") | N31: =IFERROR(INDEX('05_MILESTONES'!$K$5:$K$34,MATCH(SMALL('05_MILESTONES'!$M$5:$M$34,2),'05_MILESTONES'!$M$5:$M$34,0)),"") | P31: Project | Q31: Planned to date | R31: Actual
A32: =IFERROR(INDEX('05_MILESTONES'!$C$5:$C$34,MATCH(SMALL('05_MILESTONES'!$M$5:$M$34,3),'05_MILESTONES'!$M$5:$M$34,0)),"") | E32: =IFERROR(INDEX('05_MILESTONES'!$B$5:$B$34,MATCH(SMALL('05_MILESTONES'!$M$5:$M$34,3),'05_MILESTONES'!$M$5:$M$34,0)),"") | H32: =IFERROR(INDEX('05_MILESTONES'!$D$5:$D$34,MATCH(SMALL('05_MILESTONES'!$M$5:$M$34,3),'05_MILESTONES'!$M$5:$M$34,0)),"") | J32: =IFERROR(INDEX('05_MILESTONES'!$F$5:$F$34,MATCH(SMALL('05_MILESTONES'!$M$5:$M$34,3),'05_MILESTONES'!$M$5:$M$34,0)),"") | L32: =IFERROR(INDEX('05_MILESTONES'!$I$5:$I$34,MATCH(SMALL('05_MILESTONES'!$M$5:$M$34,3),'05_MILESTONES'!$M$5:$M$34,0)),"") | N32: =IFERROR(INDEX('05_MILESTONES'!$K$5:$K$34,MATCH(SMALL('05_MILESTONES'!$M$5:$M$34,3),'05_MILESTONES'!$M$5:$M$34,0)),"") | P32: =IFERROR(INDEX('02_PROJECT_PORTFOLIO'!$C$5:$C$34,MATCH(1,'02_PROJECT_PORTFOLIO'!$Y$5:$Y$34,0)),"") | Q32: =IF($P32="","",IFERROR(MAX(0,MIN(1,(TODAY()-INDEX('02_PROJECT_PORTFOLIO'!$H$5:$H$34,MATCH($P32,'02_PROJECT_PORTFOLIO'!$C$5:$C$34,0)))/(INDEX('02_PROJECT_PORTFOLIO'!$I$5:$I$34,MATCH($P32,'02_PROJECT_PORTFOLIO'!$C$5:$C$34,0))-INDEX('02_PROJECT_PORTFOLIO'!$H$5:$H$34,MATCH($P32,'02_PROJECT_PORTFOLIO'!$C$5:$C$34,0))))),"")) | R32: =IF($P32="","",INDEX('02_PROJECT_PORTFOLIO'!$L$5:$L$34,MATCH($P32,'02_PROJECT_PORTFOLIO'!$C$5:$C$34,0)))
A33: =IFERROR(INDEX('05_MILESTONES'!$C$5:$C$34,MATCH(SMALL('05_MILESTONES'!$M$5:$M$34,4),'05_MILESTONES'!$M$5:$M$34,0)),"") | E33: =IFERROR(INDEX('05_MILESTONES'!$B$5:$B$34,MATCH(SMALL('05_MILESTONES'!$M$5:$M$34,4),'05_MILESTONES'!$M$5:$M$34,0)),"") | H33: =IFERROR(INDEX('05_MILESTONES'!$D$5:$D$34,MATCH(SMALL('05_MILESTONES'!$M$5:$M$34,4),'05_MILESTONES'!$M$5:$M$34,0)),"") | J33: =IFERROR(INDEX('05_MILESTONES'!$F$5:$F$34,MATCH(SMALL('05_MILESTONES'!$M$5:$M$34,4),'05_MILESTONES'!$M$5:$M$34,0)),"") | L33: =IFERROR(INDEX('05_MILESTONES'!$I$5:$I$34,MATCH(SMALL('05_MILESTONES'!$M$5:$M$34,4),'05_MILESTONES'!$M$5:$M$34,0)),"") | N33: =IFERROR(INDEX('05_MILESTONES'!$K$5:$K$34,MATCH(SMALL('05_MILESTONES'!$M$5:$M$34,4),'05_MILESTONES'!$M$5:$M$34,0)),"") | P33: =IFERROR(INDEX('02_PROJECT_PORTFOLIO'!$C$5:$C$34,MATCH(2,'02_PROJECT_PORTFOLIO'!$Y$5:$Y$34,0)),"") | Q33: =IF($P33="","",IFERROR(MAX(0,MIN(1,(TODAY()-INDEX('02_PROJECT_PORTFOLIO'!$H$5:$H$34,MATCH($P33,'02_PROJECT_PORTFOLIO'!$C$5:$C$34,0)))/(INDEX('02_PROJECT_PORTFOLIO'!$I$5:$I$34,MATCH($P33,'02_PROJECT_PORTFOLIO'!$C$5:$C$34,0))-INDEX('02_PROJECT_PORTFOLIO'!$H$5:$H$34,MATCH($P33,'02_PROJECT_PORTFOLIO'!$C$5:$C$34,0))))),"")) | R33: =IF($P33="","",INDEX('02_PROJECT_PORTFOLIO'!$L$5:$L$34,MATCH($P33,'02_PROJECT_PORTFOLIO'!$C$5:$C$34,0)))
A34: =IFERROR(INDEX('05_MILESTONES'!$C$5:$C$34,MATCH(SMALL('05_MILESTONES'!$M$5:$M$34,5),'05_MILESTONES'!$M$5:$M$34,0)),"") | E34: =IFERROR(INDEX('05_MILESTONES'!$B$5:$B$34,MATCH(SMALL('05_MILESTONES'!$M$5:$M$34,5),'05_MILESTONES'!$M$5:$M$34,0)),"") | H34: =IFERROR(INDEX('05_MILESTONES'!$D$5:$D$34,MATCH(SMALL('05_MILESTONES'!$M$5:$M$34,5),'05_MILESTONES'!$M$5:$M$34,0)),"") | J34: =IFERROR(INDEX('05_MILESTONES'!$F$5:$F$34,MATCH(SMALL('05_MILESTONES'!$M$5:$M$34,5),'05_MILESTONES'!$M$5:$M$34,0)),"") | L34: =IFERROR(INDEX('05_MILESTONES'!$I$5:$I$34,MATCH(SMALL('05_MILESTONES'!$M$5:$M$34,5),'05_MILESTONES'!$M$5:$M$34,0)),"") | N34: =IFERROR(INDEX('05_MILESTONES'!$K$5:$K$34,MATCH(SMALL('05_MILESTONES'!$M$5:$M$34,5),'05_MILESTONES'!$M$5:$M$34,0)),"") | P34: =IFERROR(INDEX('02_PROJECT_PORTFOLIO'!$C$5:$C$34,MATCH(3,'02_PROJECT_PORTFOLIO'!$Y$5:$Y$34,0)),"") | Q34: =IF($P34="","",IFERROR(MAX(0,MIN(1,(TODAY()-INDEX('02_PROJECT_PORTFOLIO'!$H$5:$H$34,MATCH($P34,'02_PROJECT_PORTFOLIO'!$C$5:$C$34,0)))/(INDEX('02_PROJECT_PORTFOLIO'!$I$5:$I$34,MATCH($P34,'02_PROJECT_PORTFOLIO'!$C$5:$C$34,0))-INDEX('02_PROJECT_PORTFOLIO'!$H$5:$H$34,MATCH($P34,'02_PROJECT_PORTFOLIO'!$C$5:$C$34,0))))),"")) | R34: =IF($P34="","",INDEX('02_PROJECT_PORTFOLIO'!$L$5:$L$34,MATCH($P34,'02_PROJECT_PORTFOLIO'!$C$5:$C$34,0)))
A35: =IFERROR(INDEX('05_MILESTONES'!$C$5:$C$34,MATCH(SMALL('05_MILESTONES'!$M$5:$M$34,6),'05_MILESTONES'!$M$5:$M$34,0)),"") | E35: =IFERROR(INDEX('05_MILESTONES'!$B$5:$B$34,MATCH(SMALL('05_MILESTONES'!$M$5:$M$34,6),'05_MILESTONES'!$M$5:$M$34,0)),"") | H35: =IFERROR(INDEX('05_MILESTONES'!$D$5:$D$34,MATCH(SMALL('05_MILESTONES'!$M$5:$M$34,6),'05_MILESTONES'!$M$5:$M$34,0)),"") | J35: =IFERROR(INDEX('05_MILESTONES'!$F$5:$F$34,MATCH(SMALL('05_MILESTONES'!$M$5:$M$34,6),'05_MILESTONES'!$M$5:$M$34,0)),"") | L35: =IFERROR(INDEX('05_MILESTONES'!$I$5:$I$34,MATCH(SMALL('05_MILESTONES'!$M$5:$M$34,6),'05_MILESTONES'!$M$5:$M$34,0)),"") | N35: =IFERROR(INDEX('05_MILESTONES'!$K$5:$K$34,MATCH(SMALL('05_MILESTONES'!$M$5:$M$34,6),'05_MILESTONES'!$M$5:$M$34,0)),"") | P35: =IFERROR(INDEX('02_PROJECT_PORTFOLIO'!$C$5:$C$34,MATCH(4,'02_PROJECT_PORTFOLIO'!$Y$5:$Y$34,0)),"") | Q35: =IF($P35="","",IFERROR(MAX(0,MIN(1,(TODAY()-INDEX('02_PROJECT_PORTFOLIO'!$H$5:$H$34,MATCH($P35,'02_PROJECT_PORTFOLIO'!$C$5:$C$34,0)))/(INDEX('02_PROJECT_PORTFOLIO'!$I$5:$I$34,MATCH($P35,'02_PROJECT_PORTFOLIO'!$C$5:$C$34,0))-INDEX('02_PROJECT_PORTFOLIO'!$H$5:$H$34,MATCH($P35,'02_PROJECT_PORTFOLIO'!$C$5:$C$34,0))))),"")) | R35: =IF($P35="","",INDEX('02_PROJECT_PORTFOLIO'!$L$5:$L$34,MATCH($P35,'02_PROJECT_PORTFOLIO'!$C$5:$C$34,0)))
A36: =IFERROR(INDEX('05_MILESTONES'!$C$5:$C$34,MATCH(SMALL('05_MILESTONES'!$M$5:$M$34,7),'05_MILESTONES'!$M$5:$M$34,0)),"") | E36: =IFERROR(INDEX('05_MILESTONES'!$B$5:$B$34,MATCH(SMALL('05_MILESTONES'!$M$5:$M$34,7),'05_MILESTONES'!$M$5:$M$34,0)),"") | H36: =IFERROR(INDEX('05_MILESTONES'!$D$5:$D$34,MATCH(SMALL('05_MILESTONES'!$M$5:$M$34,7),'05_MILESTONES'!$M$5:$M$34,0)),"") | J36: =IFERROR(INDEX('05_MILESTONES'!$F$5:$F$34,MATCH(SMALL('05_MILESTONES'!$M$5:$M$34,7),'05_MILESTONES'!$M$5:$M$34,0)),"") | L36: =IFERROR(INDEX('05_MILESTONES'!$I$5:$I$34,MATCH(SMALL('05_MILESTONES'!$M$5:$M$34,7),'05_MILESTONES'!$M$5:$M$34,0)),"") | N36: =IFERROR(INDEX('05_MILESTONES'!$K$5:$K$34,MATCH(SMALL('05_MILESTONES'!$M$5:$M$34,7),'05_MILESTONES'!$M$5:$M$34,0)),"") | P36: =IFERROR(INDEX('02_PROJECT_PORTFOLIO'!$C$5:$C$34,MATCH(5,'02_PROJECT_PORTFOLIO'!$Y$5:$Y$34,0)),"") | Q36: =IF($P36="","",IFERROR(MAX(0,MIN(1,(TODAY()-INDEX('02_PROJECT_PORTFOLIO'!$H$5:$H$34,MATCH($P36,'02_PROJECT_PORTFOLIO'!$C$5:$C$34,0)))/(INDEX('02_PROJECT_PORTFOLIO'!$I$5:$I$34,MATCH($P36,'02_PROJECT_PORTFOLIO'!$C$5:$C$34,0))-INDEX('02_PROJECT_PORTFOLIO'!$H$5:$H$34,MATCH($P36,'02_PROJECT_PORTFOLIO'!$C$5:$C$34,0))))),"")) | R36: =IF($P36="","",INDEX('02_PROJECT_PORTFOLIO'!$L$5:$L$34,MATCH($P36,'02_PROJECT_PORTFOLIO'!$C$5:$C$34,0)))
A37: =IFERROR(INDEX('05_MILESTONES'!$C$5:$C$34,MATCH(SMALL('05_MILESTONES'!$M$5:$M$34,8),'05_MILESTONES'!$M$5:$M$34,0)),"") | E37: =IFERROR(INDEX('05_MILESTONES'!$B$5:$B$34,MATCH(SMALL('05_MILESTONES'!$M$5:$M$34,8),'05_MILESTONES'!$M$5:$M$34,0)),"") | H37: =IFERROR(INDEX('05_MILESTONES'!$D$5:$D$34,MATCH(SMALL('05_MILESTONES'!$M$5:$M$34,8),'05_MILESTONES'!$M$5:$M$34,0)),"") | J37: =IFERROR(INDEX('05_MILESTONES'!$F$5:$F$34,MATCH(SMALL('05_MILESTONES'!$M$5:$M$34,8),'05_MILESTONES'!$M$5:$M$34,0)),"") | L37: =IFERROR(INDEX('05_MILESTONES'!$I$5:$I$34,MATCH(SMALL('05_MILESTONES'!$M$5:$M$34,8),'05_MILESTONES'!$M$5:$M$34,0)),"") | N37: =IFERROR(INDEX('05_MILESTONES'!$K$5:$K$34,MATCH(SMALL('05_MILESTONES'!$M$5:$M$34,8),'05_MILESTONES'!$M$5:$M$34,0)),"") | P37: =IFERROR(INDEX('02_PROJECT_PORTFOLIO'!$C$5:$C$34,MATCH(6,'02_PROJECT_PORTFOLIO'!$Y$5:$Y$34,0)),"") | Q37: =IF($P37="","",IFERROR(MAX(0,MIN(1,(TODAY()-INDEX('02_PROJECT_PORTFOLIO'!$H$5:$H$34,MATCH($P37,'02_PROJECT_PORTFOLIO'!$C$5:$C$34,0)))/(INDEX('02_PROJECT_PORTFOLIO'!$I$5:$I$34,MATCH($P37,'02_PROJECT_PORTFOLIO'!$C$5:$C$34,0))-INDEX('02_PROJECT_PORTFOLIO'!$H$5:$H$34,MATCH($P37,'02_PROJECT_PORTFOLIO'!$C$5:$C$34,0))))),"")) | R37: =IF($P37="","",INDEX('02_PROJECT_PORTFOLIO'!$L$5:$L$34,MATCH($P37,'02_PROJECT_PORTFOLIO'!$C$5:$C$34,0)))
A38: =IFERROR(INDEX('05_MILESTONES'!$C$5:$C$34,MATCH(SMALL('05_MILESTONES'!$M$5:$M$34,9),'05_MILESTONES'!$M$5:$M$34,0)),"") | E38: =IFERROR(INDEX('05_MILESTONES'!$B$5:$B$34,MATCH(SMALL('05_MILESTONES'!$M$5:$M$34,9),'05_MILESTONES'!$M$5:$M$34,0)),"") | H38: =IFERROR(INDEX('05_MILESTONES'!$D$5:$D$34,MATCH(SMALL('05_MILESTONES'!$M$5:$M$34,9),'05_MILESTONES'!$M$5:$M$34,0)),"") | J38: =IFERROR(INDEX('05_MILESTONES'!$F$5:$F$34,MATCH(SMALL('05_MILESTONES'!$M$5:$M$34,9),'05_MILESTONES'!$M$5:$M$34,0)),"") | L38: =IFERROR(INDEX('05_MILESTONES'!$I$5:$I$34,MATCH(SMALL('05_MILESTONES'!$M$5:$M$34,9),'05_MILESTONES'!$M$5:$M$34,0)),"") | N38: =IFERROR(INDEX('05_MILESTONES'!$K$5:$K$34,MATCH(SMALL('05_MILESTONES'!$M$5:$M$34,9),'05_MILESTONES'!$M$5:$M$34,0)),"") | P38: =IFERROR(INDEX('02_PROJECT_PORTFOLIO'!$C$5:$C$34,MATCH(7,'02_PROJECT_PORTFOLIO'!$Y$5:$Y$34,0)),"") | Q38: =IF($P38="","",IFERROR(MAX(0,MIN(1,(TODAY()-INDEX('02_PROJECT_PORTFOLIO'!$H$5:$H$34,MATCH($P38,'02_PROJECT_PORTFOLIO'!$C$5:$C$34,0)))/(INDEX('02_PROJECT_PORTFOLIO'!$I$5:$I$34,MATCH($P38,'02_PROJECT_PORTFOLIO'!$C$5:$C$34,0))-INDEX('02_PROJECT_PORTFOLIO'!$H$5:$H$34,MATCH($P38,'02_PROJECT_PORTFOLIO'!$C$5:$C$34,0))))),"")) | R38: =IF($P38="","",INDEX('02_PROJECT_PORTFOLIO'!$L$5:$L$34,MATCH($P38,'02_PROJECT_PORTFOLIO'!$C$5:$C$34,0)))
A39: =IFERROR(INDEX('05_MILESTONES'!$C$5:$C$34,MATCH(SMALL('05_MILESTONES'!$M$5:$M$34,10),'05_MILESTONES'!$M$5:$M$34,0)),"") | E39: =IFERROR(INDEX('05_MILESTONES'!$B$5:$B$34,MATCH(SMALL('05_MILESTONES'!$M$5:$M$34,10),'05_MILESTONES'!$M$5:$M$34,0)),"") | H39: =IFERROR(INDEX('05_MILESTONES'!$D$5:$D$34,MATCH(SMALL('05_MILESTONES'!$M$5:$M$34,10),'05_MILESTONES'!$M$5:$M$34,0)),"") | J39: =IFERROR(INDEX('05_MILESTONES'!$F$5:$F$34,MATCH(SMALL('05_MILESTONES'!$M$5:$M$34,10),'05_MILESTONES'!$M$5:$M$34,0)),"") | L39: =IFERROR(INDEX('05_MILESTONES'!$I$5:$I$34,MATCH(SMALL('05_MILESTONES'!$M$5:$M$34,10),'05_MILESTONES'!$M$5:$M$34,0)),"") | N39: =IFERROR(INDEX('05_MILESTONES'!$K$5:$K$34,MATCH(SMALL('05_MILESTONES'!$M$5:$M$34,10),'05_MILESTONES'!$M$5:$M$34,0)),"") | P39: =IFERROR(INDEX('02_PROJECT_PORTFOLIO'!$C$5:$C$34,MATCH(8,'02_PROJECT_PORTFOLIO'!$Y$5:$Y$34,0)),"") | Q39: =IF($P39="","",IFERROR(MAX(0,MIN(1,(TODAY()-INDEX('02_PROJECT_PORTFOLIO'!$H$5:$H$34,MATCH($P39,'02_PROJECT_PORTFOLIO'!$C$5:$C$34,0)))/(INDEX('02_PROJECT_PORTFOLIO'!$I$5:$I$34,MATCH($P39,'02_PROJECT_PORTFOLIO'!$C$5:$C$34,0))-INDEX('02_PROJECT_PORTFOLIO'!$H$5:$H$34,MATCH($P39,'02_PROJECT_PORTFOLIO'!$C$5:$C$34,0))))),"")) | R39: =IF($P39="","",INDEX('02_PROJECT_PORTFOLIO'!$L$5:$L$34,MATCH($P39,'02_PROJECT_PORTFOLIO'!$C$5:$C$34,0)))
P40: =IFERROR(INDEX('02_PROJECT_PORTFOLIO'!$C$5:$C$34,MATCH(9,'02_PROJECT_PORTFOLIO'!$Y$5:$Y$34,0)),"") | Q40: =IF($P40="","",IFERROR(MAX(0,MIN(1,(TODAY()-INDEX('02_PROJECT_PORTFOLIO'!$H$5:$H$34,MATCH($P40,'02_PROJECT_PORTFOLIO'!$C$5:$C$34,0)))/(INDEX('02_PROJECT_PORTFOLIO'!$I$5:$I$34,MATCH($P40,'02_PROJECT_PORTFOLIO'!$C$5:$C$34,0))-INDEX('02_PROJECT_PORTFOLIO'!$H$5:$H$34,MATCH($P40,'02_PROJECT_PORTFOLIO'!$C$5:$C$34,0))))),"")) | R40: =IF($P40="","",INDEX('02_PROJECT_PORTFOLIO'!$L$5:$L$34,MATCH($P40,'02_PROJECT_PORTFOLIO'!$C$5:$C$34,0)))
A41: PORTFOLIO FILTER VIEW - PROJECT | STATUS | RAG | MANAGER / DEPARTMENT | TIMELINE | PROGRESS | BUDGET / ACTUAL | NEXT MILESTONE | P41: =IFERROR(INDEX('02_PROJECT_PORTFOLIO'!$C$5:$C$34,MATCH(10,'02_PROJECT_PORTFOLIO'!$Y$5:$Y$34,0)),"") | Q41: =IF($P41="","",IFERROR(MAX(0,MIN(1,(TODAY()-INDEX('02_PROJECT_PORTFOLIO'!$H$5:$H$34,MATCH($P41,'02_PROJECT_PORTFOLIO'!$C$5:$C$34,0)))/(INDEX('02_PROJECT_PORTFOLIO'!$I$5:$I$34,MATCH($P41,'02_PROJECT_PORTFOLIO'!$C$5:$C$34,0))-INDEX('02_PROJECT_PORTFOLIO'!$H$5:$H$34,MATCH($P41,'02_PROJECT_PORTFOLIO'!$C$5:$C$34,0))))),"")) | R41: =IF($P41="","",INDEX('02_PROJECT_PORTFOLIO'!$L$5:$L$34,MATCH($P41,'02_PROJECT_PORTFOLIO'!$C$5:$C$34,0)))
A42: FILTER BY: | C42: All | D42: RAG: | F42: All | G42: MANAGER: | I42: All | J42: =COUNTIF('02_PROJECT_PORTFOLIO'!$AA$5:$AA$34,">0")&" OF "&COUNTIF('02_PROJECT_PORTFOLIO'!$C$5:$C$34,"?*")&" PROJECTS SHOWN" | M42: =HYPERLINK("#'02_PROJECT_PORTFOLIO'!A1","OPEN FULL PORTFOLIO")
A43: PROJECT | C43: STATUS | D43: RAG | E43: MANAGER / DEPARTMENT | G43: TIMELINE | I43: PROGRESS | J43: BUDGET / ACTUAL | L43: NEXT MILESTONE | P43: BLOCK 5 - APPROVED / ACTUAL / FORECAST
A44: =IFERROR(INDEX('02_PROJECT_PORTFOLIO'!$A$5:$A$34,MATCH(1,'02_PROJECT_PORTFOLIO'!$AA$5:$AA$34,0))&" "&INDEX('02_PROJECT_PORTFOLIO'!$C$5:$C$34,MATCH(1,'02_PROJECT_PORTFOLIO'!$AA$5:$AA$34,0)),"") | C44: =IFERROR(INDEX('02_PROJECT_PORTFOLIO'!$M$5:$M$34,MATCH(1,'02_PROJECT_PORTFOLIO'!$AA$5:$AA$34,0)),"") | D44: =IFERROR(INDEX('02_PROJECT_PORTFOLIO'!$N$5:$N$34,MATCH(1,'02_PROJECT_PORTFOLIO'!$AA$5:$AA$34,0)),"") | E44: =IFERROR(INDEX('02_PROJECT_PORTFOLIO'!$D$5:$D$34,MATCH(1,'02_PROJECT_PORTFOLIO'!$AA$5:$AA$34,0))&" / "&INDEX('02_PROJECT_PORTFOLIO'!$E$5:$E$34,MATCH(1,'02_PROJECT_PORTFOLIO'!$AA$5:$AA$34,0)),"") | G44: =IFERROR(INDEX('02_PROJECT_PORTFOLIO'!$AB$5:$AB$34,MATCH(1,'02_PROJECT_PORTFOLIO'!$AA$5:$AA$34,0)),"") | I44: =IFERROR(INDEX('02_PROJECT_PORTFOLIO'!$L$5:$L$34,MATCH(1,'02_PROJECT_PORTFOLIO'!$AA$5:$AA$34,0)),"") | J44: =IFERROR(INDEX('02_PROJECT_PORTFOLIO'!$AC$5:$AC$34,MATCH(1,'02_PROJECT_PORTFOLIO'!$AA$5:$AA$34,0)),"") | L44: =IFERROR(INDEX('02_PROJECT_PORTFOLIO'!$T$5:$T$34,MATCH(1,'02_PROJECT_PORTFOLIO'!$AA$5:$AA$34,0))&IF(INDEX('02_PROJECT_PORTFOLIO'!$U$5:$U$34,MATCH(1,'02_PROJECT_PORTFOLIO'!$AA$5:$AA$34,0))="",""," ("&TEXT(INDEX('02_PROJECT_PORTFOLIO'!$U$5:$U$34,MATCH(1,'02_PROJECT_PORTFOLIO'!$AA$5:$AA$34,0)),"dd-mmm-yy")&")"),"") | P44: Project | Q44: Approved | R44: Actual | S44: Forecast
A45: =IFERROR(INDEX('02_PROJECT_PORTFOLIO'!$A$5:$A$34,MATCH(2,'02_PROJECT_PORTFOLIO'!$AA$5:$AA$34,0))&" "&INDEX('02_PROJECT_PORTFOLIO'!$C$5:$C$34,MATCH(2,'02_PROJECT_PORTFOLIO'!$AA$5:$AA$34,0)),"") | C45: =IFERROR(INDEX('02_PROJECT_PORTFOLIO'!$M$5:$M$34,MATCH(2,'02_PROJECT_PORTFOLIO'!$AA$5:$AA$34,0)),"") | D45: =IFERROR(INDEX('02_PROJECT_PORTFOLIO'!$N$5:$N$34,MATCH(2,'02_PROJECT_PORTFOLIO'!$AA$5:$AA$34,0)),"") | E45: =IFERROR(INDEX('02_PROJECT_PORTFOLIO'!$D$5:$D$34,MATCH(2,'02_PROJECT_PORTFOLIO'!$AA$5:$AA$34,0))&" / "&INDEX('02_PROJECT_PORTFOLIO'!$E$5:$E$34,MATCH(2,'02_PROJECT_PORTFOLIO'!$AA$5:$AA$34,0)),"") | G45: =IFERROR(INDEX('02_PROJECT_PORTFOLIO'!$AB$5:$AB$34,MATCH(2,'02_PROJECT_PORTFOLIO'!$AA$5:$AA$34,0)),"") | I45: =IFERROR(INDEX('02_PROJECT_PORTFOLIO'!$L$5:$L$34,MATCH(2,'02_PROJECT_PORTFOLIO'!$AA$5:$AA$34,0)),"") | J45: =IFERROR(INDEX('02_PROJECT_PORTFOLIO'!$AC$5:$AC$34,MATCH(2,'02_PROJECT_PORTFOLIO'!$AA$5:$AA$34,0)),"") | L45: =IFERROR(INDEX('02_PROJECT_PORTFOLIO'!$T$5:$T$34,MATCH(2,'02_PROJECT_PORTFOLIO'!$AA$5:$AA$34,0))&IF(INDEX('02_PROJECT_PORTFOLIO'!$U$5:$U$34,MATCH(2,'02_PROJECT_PORTFOLIO'!$AA$5:$AA$34,0))="",""," ("&TEXT(INDEX('02_PROJECT_PORTFOLIO'!$U$5:$U$34,MATCH(2,'02_PROJECT_PORTFOLIO'!$AA$5:$AA$34,0)),"dd-mmm-yy")&")"),"") | P45: =IFERROR(INDEX('02_PROJECT_PORTFOLIO'!$C$5:$C$34,MATCH(1,'02_PROJECT_PORTFOLIO'!$Y$5:$Y$34,0)),"") | Q45: =IF($P45="","",INDEX('02_PROJECT_PORTFOLIO'!$O$5:$O$34,MATCH($P45,'02_PROJECT_PORTFOLIO'!$C$5:$C$34,0))) | R45: =IF($P45="","",INDEX('02_PROJECT_PORTFOLIO'!$P$5:$P$34,MATCH($P45,'02_PROJECT_PORTFOLIO'!$C$5:$C$34,0))) | S45: =IF($P45="","",INDEX('02_PROJECT_PORTFOLIO'!$Q$5:$Q$34,MATCH($P45,'02_PROJECT_PORTFOLIO'!$C$5:$C$34,0)))
A46: =IFERROR(INDEX('02_PROJECT_PORTFOLIO'!$A$5:$A$34,MATCH(3,'02_PROJECT_PORTFOLIO'!$AA$5:$AA$34,0))&" "&INDEX('02_PROJECT_PORTFOLIO'!$C$5:$C$34,MATCH(3,'02_PROJECT_PORTFOLIO'!$AA$5:$AA$34,0)),"") | C46: =IFERROR(INDEX('02_PROJECT_PORTFOLIO'!$M$5:$M$34,MATCH(3,'02_PROJECT_PORTFOLIO'!$AA$5:$AA$34,0)),"") | D46: =IFERROR(INDEX('02_PROJECT_PORTFOLIO'!$N$5:$N$34,MATCH(3,'02_PROJECT_PORTFOLIO'!$AA$5:$AA$34,0)),"") | E46: =IFERROR(INDEX('02_PROJECT_PORTFOLIO'!$D$5:$D$34,MATCH(3,'02_PROJECT_PORTFOLIO'!$AA$5:$AA$34,0))&" / "&INDEX('02_PROJECT_PORTFOLIO'!$E$5:$E$34,MATCH(3,'02_PROJECT_PORTFOLIO'!$AA$5:$AA$34,0)),"") | G46: =IFERROR(INDEX('02_PROJECT_PORTFOLIO'!$AB$5:$AB$34,MATCH(3,'02_PROJECT_PORTFOLIO'!$AA$5:$AA$34,0)),"") | I46: =IFERROR(INDEX('02_PROJECT_PORTFOLIO'!$L$5:$L$34,MATCH(3,'02_PROJECT_PORTFOLIO'!$AA$5:$AA$34,0)),"") | J46: =IFERROR(INDEX('02_PROJECT_PORTFOLIO'!$AC$5:$AC$34,MATCH(3,'02_PROJECT_PORTFOLIO'!$AA$5:$AA$34,0)),"") | L46: =IFERROR(INDEX('02_PROJECT_PORTFOLIO'!$T$5:$T$34,MATCH(3,'02_PROJECT_PORTFOLIO'!$AA$5:$AA$34,0))&IF(INDEX('02_PROJECT_PORTFOLIO'!$U$5:$U$34,MATCH(3,'02_PROJECT_PORTFOLIO'!$AA$5:$AA$34,0))="",""," ("&TEXT(INDEX('02_PROJECT_PORTFOLIO'!$U$5:$U$34,MATCH(3,'02_PROJECT_PORTFOLIO'!$AA$5:$AA$34,0)),"dd-mmm-yy")&")"),"") | P46: =IFERROR(INDEX('02_PROJECT_PORTFOLIO'!$C$5:$C$34,MATCH(2,'02_PROJECT_PORTFOLIO'!$Y$5:$Y$34,0)),"") | Q46: =IF($P46="","",INDEX('02_PROJECT_PORTFOLIO'!$O$5:$O$34,MATCH($P46,'02_PROJECT_PORTFOLIO'!$C$5:$C$34,0))) | R46: =IF($P46="","",INDEX('02_PROJECT_PORTFOLIO'!$P$5:$P$34,MATCH($P46,'02_PROJECT_PORTFOLIO'!$C$5:$C$34,0))) | S46: =IF($P46="","",INDEX('02_PROJECT_PORTFOLIO'!$Q$5:$Q$34,MATCH($P46,'02_PROJECT_PORTFOLIO'!$C$5:$C$34,0)))
A47: =IFERROR(INDEX('02_PROJECT_PORTFOLIO'!$A$5:$A$34,MATCH(4,'02_PROJECT_PORTFOLIO'!$AA$5:$AA$34,0))&" "&INDEX('02_PROJECT_PORTFOLIO'!$C$5:$C$34,MATCH(4,'02_PROJECT_PORTFOLIO'!$AA$5:$AA$34,0)),"") | C47: =IFERROR(INDEX('02_PROJECT_PORTFOLIO'!$M$5:$M$34,MATCH(4,'02_PROJECT_PORTFOLIO'!$AA$5:$AA$34,0)),"") | D47: =IFERROR(INDEX('02_PROJECT_PORTFOLIO'!$N$5:$N$34,MATCH(4,'02_PROJECT_PORTFOLIO'!$AA$5:$AA$34,0)),"") | E47: =IFERROR(INDEX('02_PROJECT_PORTFOLIO'!$D$5:$D$34,MATCH(4,'02_PROJECT_PORTFOLIO'!$AA$5:$AA$34,0))&" / "&INDEX('02_PROJECT_PORTFOLIO'!$E$5:$E$34,MATCH(4,'02_PROJECT_PORTFOLIO'!$AA$5:$AA$34,0)),"") | G47: =IFERROR(INDEX('02_PROJECT_PORTFOLIO'!$AB$5:$AB$34,MATCH(4,'02_PROJECT_PORTFOLIO'!$AA$5:$AA$34,0)),"") | I47: =IFERROR(INDEX('02_PROJECT_PORTFOLIO'!$L$5:$L$34,MATCH(4,'02_PROJECT_PORTFOLIO'!$AA$5:$AA$34,0)),"") | J47: =IFERROR(INDEX('02_PROJECT_PORTFOLIO'!$AC$5:$AC$34,MATCH(4,'02_PROJECT_PORTFOLIO'!$AA$5:$AA$34,0)),"") | L47: =IFERROR(INDEX('02_PROJECT_PORTFOLIO'!$T$5:$T$34,MATCH(4,'02_PROJECT_PORTFOLIO'!$AA$5:$AA$34,0))&IF(INDEX('02_PROJECT_PORTFOLIO'!$U$5:$U$34,MATCH(4,'02_PROJECT_PORTFOLIO'!$AA$5:$AA$34,0))="",""," ("&TEXT(INDEX('02_PROJECT_PORTFOLIO'!$U$5:$U$34,MATCH(4,'02_PROJECT_PORTFOLIO'!$AA$5:$AA$34,0)),"dd-mmm-yy")&")"),"") | P47: =IFERROR(INDEX('02_PROJECT_PORTFOLIO'!$C$5:$C$34,MATCH(3,'02_PROJECT_PORTFOLIO'!$Y$5:$Y$34,0)),"") | Q47: =IF($P47="","",INDEX('02_PROJECT_PORTFOLIO'!$O$5:$O$34,MATCH($P47,'02_PROJECT_PORTFOLIO'!$C$5:$C$34,0))) | R47: =IF($P47="","",INDEX('02_PROJECT_PORTFOLIO'!$P$5:$P$34,MATCH($P47,'02_PROJECT_PORTFOLIO'!$C$5:$C$34,0))) | S47: =IF($P47="","",INDEX('02_PROJECT_PORTFOLIO'!$Q$5:$Q$34,MATCH($P47,'02_PROJECT_PORTFOLIO'!$C$5:$C$34,0)))
A48: =IFERROR(INDEX('02_PROJECT_PORTFOLIO'!$A$5:$A$34,MATCH(5,'02_PROJECT_PORTFOLIO'!$AA$5:$AA$34,0))&" "&INDEX('02_PROJECT_PORTFOLIO'!$C$5:$C$34,MATCH(5,'02_PROJECT_PORTFOLIO'!$AA$5:$AA$34,0)),"") | C48: =IFERROR(INDEX('02_PROJECT_PORTFOLIO'!$M$5:$M$34,MATCH(5,'02_PROJECT_PORTFOLIO'!$AA$5:$AA$34,0)),"") | D48: =IFERROR(INDEX('02_PROJECT_PORTFOLIO'!$N$5:$N$34,MATCH(5,'02_PROJECT_PORTFOLIO'!$AA$5:$AA$34,0)),"") | E48: =IFERROR(INDEX('02_PROJECT_PORTFOLIO'!$D$5:$D$34,MATCH(5,'02_PROJECT_PORTFOLIO'!$AA$5:$AA$34,0))&" / "&INDEX('02_PROJECT_PORTFOLIO'!$E$5:$E$34,MATCH(5,'02_PROJECT_PORTFOLIO'!$AA$5:$AA$34,0)),"") | G48: =IFERROR(INDEX('02_PROJECT_PORTFOLIO'!$AB$5:$AB$34,MATCH(5,'02_PROJECT_PORTFOLIO'!$AA$5:$AA$34,0)),"") | I48: =IFERROR(INDEX('02_PROJECT_PORTFOLIO'!$L$5:$L$34,MATCH(5,'02_PROJECT_PORTFOLIO'!$AA$5:$AA$34,0)),"") | J48: =IFERROR(INDEX('02_PROJECT_PORTFOLIO'!$AC$5:$AC$34,MATCH(5,'02_PROJECT_PORTFOLIO'!$AA$5:$AA$34,0)),"") | L48: =IFERROR(INDEX('02_PROJECT_PORTFOLIO'!$T$5:$T$34,MATCH(5,'02_PROJECT_PORTFOLIO'!$AA$5:$AA$34,0))&IF(INDEX('02_PROJECT_PORTFOLIO'!$U$5:$U$34,MATCH(5,'02_PROJECT_PORTFOLIO'!$AA$5:$AA$34,0))="",""," ("&TEXT(INDEX('02_PROJECT_PORTFOLIO'!$U$5:$U$34,MATCH(5,'02_PROJECT_PORTFOLIO'!$AA$5:$AA$34,0)),"dd-mmm-yy")&")"),"") | P48: =IFERROR(INDEX('02_PROJECT_PORTFOLIO'!$C$5:$C$34,MATCH(4,'02_PROJECT_PORTFOLIO'!$Y$5:$Y$34,0)),"") | Q48: =IF($P48="","",INDEX('02_PROJECT_PORTFOLIO'!$O$5:$O$34,MATCH($P48,'02_PROJECT_PORTFOLIO'!$C$5:$C$34,0))) | R48: =IF($P48="","",INDEX('02_PROJECT_PORTFOLIO'!$P$5:$P$34,MATCH($P48,'02_PROJECT_PORTFOLIO'!$C$5:$C$34,0))) | S48: =IF($P48="","",INDEX('02_PROJECT_PORTFOLIO'!$Q$5:$Q$34,MATCH($P48,'02_PROJECT_PORTFOLIO'!$C$5:$C$34,0)))
A49: =IFERROR(INDEX('02_PROJECT_PORTFOLIO'!$A$5:$A$34,MATCH(6,'02_PROJECT_PORTFOLIO'!$AA$5:$AA$34,0))&" "&INDEX('02_PROJECT_PORTFOLIO'!$C$5:$C$34,MATCH(6,'02_PROJECT_PORTFOLIO'!$AA$5:$AA$34,0)),"") | C49: =IFERROR(INDEX('02_PROJECT_PORTFOLIO'!$M$5:$M$34,MATCH(6,'02_PROJECT_PORTFOLIO'!$AA$5:$AA$34,0)),"") | D49: =IFERROR(INDEX('02_PROJECT_PORTFOLIO'!$N$5:$N$34,MATCH(6,'02_PROJECT_PORTFOLIO'!$AA$5:$AA$34,0)),"") | E49: =IFERROR(INDEX('02_PROJECT_PORTFOLIO'!$D$5:$D$34,MATCH(6,'02_PROJECT_PORTFOLIO'!$AA$5:$AA$34,0))&" / "&INDEX('02_PROJECT_PORTFOLIO'!$E$5:$E$34,MATCH(6,'02_PROJECT_PORTFOLIO'!$AA$5:$AA$34,0)),"") | G49: =IFERROR(INDEX('02_PROJECT_PORTFOLIO'!$AB$5:$AB$34,MATCH(6,'02_PROJECT_PORTFOLIO'!$AA$5:$AA$34,0)),"") | I49: =IFERROR(INDEX('02_PROJECT_PORTFOLIO'!$L$5:$L$34,MATCH(6,'02_PROJECT_PORTFOLIO'!$AA$5:$AA$34,0)),"") | J49: =IFERROR(INDEX('02_PROJECT_PORTFOLIO'!$AC$5:$AC$34,MATCH(6,'02_PROJECT_PORTFOLIO'!$AA$5:$AA$34,0)),"") | L49: =IFERROR(INDEX('02_PROJECT_PORTFOLIO'!$T$5:$T$34,MATCH(6,'02_PROJECT_PORTFOLIO'!$AA$5:$AA$34,0))&IF(INDEX('02_PROJECT_PORTFOLIO'!$U$5:$U$34,MATCH(6,'02_PROJECT_PORTFOLIO'!$AA$5:$AA$34,0))="",""," ("&TEXT(INDEX('02_PROJECT_PORTFOLIO'!$U$5:$U$34,MATCH(6,'02_PROJECT_PORTFOLIO'!$AA$5:$AA$34,0)),"dd-mmm-yy")&")"),"") | P49: =IFERROR(INDEX('02_PROJECT_PORTFOLIO'!$C$5:$C$34,MATCH(5,'02_PROJECT_PORTFOLIO'!$Y$5:$Y$34,0)),"") | Q49: =IF($P49="","",INDEX('02_PROJECT_PORTFOLIO'!$O$5:$O$34,MATCH($P49,'02_PROJECT_PORTFOLIO'!$C$5:$C$34,0))) | R49: =IF($P49="","",INDEX('02_PROJECT_PORTFOLIO'!$P$5:$P$34,MATCH($P49,'02_PROJECT_PORTFOLIO'!$C$5:$C$34,0))) | S49: =IF($P49="","",INDEX('02_PROJECT_PORTFOLIO'!$Q$5:$Q$34,MATCH($P49,'02_PROJECT_PORTFOLIO'!$C$5:$C$34,0)))
A50: =IFERROR(INDEX('02_PROJECT_PORTFOLIO'!$A$5:$A$34,MATCH(7,'02_PROJECT_PORTFOLIO'!$AA$5:$AA$34,0))&" "&INDEX('02_PROJECT_PORTFOLIO'!$C$5:$C$34,MATCH(7,'02_PROJECT_PORTFOLIO'!$AA$5:$AA$34,0)),"") | C50: =IFERROR(INDEX('02_PROJECT_PORTFOLIO'!$M$5:$M$34,MATCH(7,'02_PROJECT_PORTFOLIO'!$AA$5:$AA$34,0)),"") | D50: =IFERROR(INDEX('02_PROJECT_PORTFOLIO'!$N$5:$N$34,MATCH(7,'02_PROJECT_PORTFOLIO'!$AA$5:$AA$34,0)),"") | E50: =IFERROR(INDEX('02_PROJECT_PORTFOLIO'!$D$5:$D$34,MATCH(7,'02_PROJECT_PORTFOLIO'!$AA$5:$AA$34,0))&" / "&INDEX('02_PROJECT_PORTFOLIO'!$E$5:$E$34,MATCH(7,'02_PROJECT_PORTFOLIO'!$AA$5:$AA$34,0)),"") | G50: =IFERROR(INDEX('02_PROJECT_PORTFOLIO'!$AB$5:$AB$34,MATCH(7,'02_PROJECT_PORTFOLIO'!$AA$5:$AA$34,0)),"") | I50: =IFERROR(INDEX('02_PROJECT_PORTFOLIO'!$L$5:$L$34,MATCH(7,'02_PROJECT_PORTFOLIO'!$AA$5:$AA$34,0)),"") | J50: =IFERROR(INDEX('02_PROJECT_PORTFOLIO'!$AC$5:$AC$34,MATCH(7,'02_PROJECT_PORTFOLIO'!$AA$5:$AA$34,0)),"") | L50: =IFERROR(INDEX('02_PROJECT_PORTFOLIO'!$T$5:$T$34,MATCH(7,'02_PROJECT_PORTFOLIO'!$AA$5:$AA$34,0))&IF(INDEX('02_PROJECT_PORTFOLIO'!$U$5:$U$34,MATCH(7,'02_PROJECT_PORTFOLIO'!$AA$5:$AA$34,0))="",""," ("&TEXT(INDEX('02_PROJECT_PORTFOLIO'!$U$5:$U$34,MATCH(7,'02_PROJECT_PORTFOLIO'!$AA$5:$AA$34,0)),"dd-mmm-yy")&")"),"") | P50: =IFERROR(INDEX('02_PROJECT_PORTFOLIO'!$C$5:$C$34,MATCH(6,'02_PROJECT_PORTFOLIO'!$Y$5:$Y$34,0)),"") | Q50: =IF($P50="","",INDEX('02_PROJECT_PORTFOLIO'!$O$5:$O$34,MATCH($P50,'02_PROJECT_PORTFOLIO'!$C$5:$C$34,0))) | R50: =IF($P50="","",INDEX('02_PROJECT_PORTFOLIO'!$P$5:$P$34,MATCH($P50,'02_PROJECT_PORTFOLIO'!$C$5:$C$34,0))) | S50: =IF($P50="","",INDEX('02_PROJECT_PORTFOLIO'!$Q$5:$Q$34,MATCH($P50,'02_PROJECT_PORTFOLIO'!$C$5:$C$34,0)))
A51: =IFERROR(INDEX('02_PROJECT_PORTFOLIO'!$A$5:$A$34,MATCH(8,'02_PROJECT_PORTFOLIO'!$AA$5:$AA$34,0))&" "&INDEX('02_PROJECT_PORTFOLIO'!$C$5:$C$34,MATCH(8,'02_PROJECT_PORTFOLIO'!$AA$5:$AA$34,0)),"") | C51: =IFERROR(INDEX('02_PROJECT_PORTFOLIO'!$M$5:$M$34,MATCH(8,'02_PROJECT_PORTFOLIO'!$AA$5:$AA$34,0)),"") | D51: =IFERROR(INDEX('02_PROJECT_PORTFOLIO'!$N$5:$N$34,MATCH(8,'02_PROJECT_PORTFOLIO'!$AA$5:$AA$34,0)),"") | E51: =IFERROR(INDEX('02_PROJECT_PORTFOLIO'!$D$5:$D$34,MATCH(8,'02_PROJECT_PORTFOLIO'!$AA$5:$AA$34,0))&" / "&INDEX('02_PROJECT_PORTFOLIO'!$E$5:$E$34,MATCH(8,'02_PROJECT_PORTFOLIO'!$AA$5:$AA$34,0)),"") | G51: =IFERROR(INDEX('02_PROJECT_PORTFOLIO'!$AB$5:$AB$34,MATCH(8,'02_PROJECT_PORTFOLIO'!$AA$5:$AA$34,0)),"") | I51: =IFERROR(INDEX('02_PROJECT_PORTFOLIO'!$L$5:$L$34,MATCH(8,'02_PROJECT_PORTFOLIO'!$AA$5:$AA$34,0)),"") | J51: =IFERROR(INDEX('02_PROJECT_PORTFOLIO'!$AC$5:$AC$34,MATCH(8,'02_PROJECT_PORTFOLIO'!$AA$5:$AA$34,0)),"") | L51: =IFERROR(INDEX('02_PROJECT_PORTFOLIO'!$T$5:$T$34,MATCH(8,'02_PROJECT_PORTFOLIO'!$AA$5:$AA$34,0))&IF(INDEX('02_PROJECT_PORTFOLIO'!$U$5:$U$34,MATCH(8,'02_PROJECT_PORTFOLIO'!$AA$5:$AA$34,0))="",""," ("&TEXT(INDEX('02_PROJECT_PORTFOLIO'!$U$5:$U$34,MATCH(8,'02_PROJECT_PORTFOLIO'!$AA$5:$AA$34,0)),"dd-mmm-yy")&")"),"") | P51: =IFERROR(INDEX('02_PROJECT_PORTFOLIO'!$C$5:$C$34,MATCH(7,'02_PROJECT_PORTFOLIO'!$Y$5:$Y$34,0)),"") | Q51: =IF($P51="","",INDEX('02_PROJECT_PORTFOLIO'!$O$5:$O$34,MATCH($P51,'02_PROJECT_PORTFOLIO'!$C$5:$C$34,0))) | R51: =IF($P51="","",INDEX('02_PROJECT_PORTFOLIO'!$P$5:$P$34,MATCH($P51,'02_PROJECT_PORTFOLIO'!$C$5:$C$34,0))) | S51: =IF($P51="","",INDEX('02_PROJECT_PORTFOLIO'!$Q$5:$Q$34,MATCH($P51,'02_PROJECT_PORTFOLIO'!$C$5:$C$34,0)))
A52: =IFERROR(INDEX('02_PROJECT_PORTFOLIO'!$A$5:$A$34,MATCH(9,'02_PROJECT_PORTFOLIO'!$AA$5:$AA$34,0))&" "&INDEX('02_PROJECT_PORTFOLIO'!$C$5:$C$34,MATCH(9,'02_PROJECT_PORTFOLIO'!$AA$5:$AA$34,0)),"") | C52: =IFERROR(INDEX('02_PROJECT_PORTFOLIO'!$M$5:$M$34,MATCH(9,'02_PROJECT_PORTFOLIO'!$AA$5:$AA$34,0)),"") | D52: =IFERROR(INDEX('02_PROJECT_PORTFOLIO'!$N$5:$N$34,MATCH(9,'02_PROJECT_PORTFOLIO'!$AA$5:$AA$34,0)),"") | E52: =IFERROR(INDEX('02_PROJECT_PORTFOLIO'!$D$5:$D$34,MATCH(9,'02_PROJECT_PORTFOLIO'!$AA$5:$AA$34,0))&" / "&INDEX('02_PROJECT_PORTFOLIO'!$E$5:$E$34,MATCH(9,'02_PROJECT_PORTFOLIO'!$AA$5:$AA$34,0)),"") | G52: =IFERROR(INDEX('02_PROJECT_PORTFOLIO'!$AB$5:$AB$34,MATCH(9,'02_PROJECT_PORTFOLIO'!$AA$5:$AA$34,0)),"") | I52: =IFERROR(INDEX('02_PROJECT_PORTFOLIO'!$L$5:$L$34,MATCH(9,'02_PROJECT_PORTFOLIO'!$AA$5:$AA$34,0)),"") | J52: =IFERROR(INDEX('02_PROJECT_PORTFOLIO'!$AC$5:$AC$34,MATCH(9,'02_PROJECT_PORTFOLIO'!$AA$5:$AA$34,0)),"") | L52: =IFERROR(INDEX('02_PROJECT_PORTFOLIO'!$T$5:$T$34,MATCH(9,'02_PROJECT_PORTFOLIO'!$AA$5:$AA$34,0))&IF(INDEX('02_PROJECT_PORTFOLIO'!$U$5:$U$34,MATCH(9,'02_PROJECT_PORTFOLIO'!$AA$5:$AA$34,0))="",""," ("&TEXT(INDEX('02_PROJECT_PORTFOLIO'!$U$5:$U$34,MATCH(9,'02_PROJECT_PORTFOLIO'!$AA$5:$AA$34,0)),"dd-mmm-yy")&")"),"") | P52: =IFERROR(INDEX('02_PROJECT_PORTFOLIO'!$C$5:$C$34,MATCH(8,'02_PROJECT_PORTFOLIO'!$Y$5:$Y$34,0)),"") | Q52: =IF($P52="","",INDEX('02_PROJECT_PORTFOLIO'!$O$5:$O$34,MATCH($P52,'02_PROJECT_PORTFOLIO'!$C$5:$C$34,0))) | R52: =IF($P52="","",INDEX('02_PROJECT_PORTFOLIO'!$P$5:$P$34,MATCH($P52,'02_PROJECT_PORTFOLIO'!$C$5:$C$34,0))) | S52: =IF($P52="","",INDEX('02_PROJECT_PORTFOLIO'!$Q$5:$Q$34,MATCH($P52,'02_PROJECT_PORTFOLIO'!$C$5:$C$34,0)))
A53: =IFERROR(INDEX('02_PROJECT_PORTFOLIO'!$A$5:$A$34,MATCH(10,'02_PROJECT_PORTFOLIO'!$AA$5:$AA$34,0))&" "&INDEX('02_PROJECT_PORTFOLIO'!$C$5:$C$34,MATCH(10,'02_PROJECT_PORTFOLIO'!$AA$5:$AA$34,0)),"") | C53: =IFERROR(INDEX('02_PROJECT_PORTFOLIO'!$M$5:$M$34,MATCH(10,'02_PROJECT_PORTFOLIO'!$AA$5:$AA$34,0)),"") | D53: =IFERROR(INDEX('02_PROJECT_PORTFOLIO'!$N$5:$N$34,MATCH(10,'02_PROJECT_PORTFOLIO'!$AA$5:$AA$34,0)),"") | E53: =IFERROR(INDEX('02_PROJECT_PORTFOLIO'!$D$5:$D$34,MATCH(10,'02_PROJECT_PORTFOLIO'!$AA$5:$AA$34,0))&" / "&INDEX('02_PROJECT_PORTFOLIO'!$E$5:$E$34,MATCH(10,'02_PROJECT_PORTFOLIO'!$AA$5:$AA$34,0)),"") | G53: =IFERROR(INDEX('02_PROJECT_PORTFOLIO'!$AB$5:$AB$34,MATCH(10,'02_PROJECT_PORTFOLIO'!$AA$5:$AA$34,0)),"") | I53: =IFERROR(INDEX('02_PROJECT_PORTFOLIO'!$L$5:$L$34,MATCH(10,'02_PROJECT_PORTFOLIO'!$AA$5:$AA$34,0)),"") | J53: =IFERROR(INDEX('02_PROJECT_PORTFOLIO'!$AC$5:$AC$34,MATCH(10,'02_PROJECT_PORTFOLIO'!$AA$5:$AA$34,0)),"") | L53: =IFERROR(INDEX('02_PROJECT_PORTFOLIO'!$T$5:$T$34,MATCH(10,'02_PROJECT_PORTFOLIO'!$AA$5:$AA$34,0))&IF(INDEX('02_PROJECT_PORTFOLIO'!$U$5:$U$34,MATCH(10,'02_PROJECT_PORTFOLIO'!$AA$5:$AA$34,0))="",""," ("&TEXT(INDEX('02_PROJECT_PORTFOLIO'!$U$5:$U$34,MATCH(10,'02_PROJECT_PORTFOLIO'!$AA$5:$AA$34,0)),"dd-mmm-yy")&")"),"") | P53: =IFERROR(INDEX('02_PROJECT_PORTFOLIO'!$C$5:$C$34,MATCH(9,'02_PROJECT_PORTFOLIO'!$Y$5:$Y$34,0)),"") | Q53: =IF($P53="","",INDEX('02_PROJECT_PORTFOLIO'!$O$5:$O$34,MATCH($P53,'02_PROJECT_PORTFOLIO'!$C$5:$C$34,0))) | R53: =IF($P53="","",INDEX('02_PROJECT_PORTFOLIO'!$P$5:$P$34,MATCH($P53,'02_PROJECT_PORTFOLIO'!$C$5:$C$34,0))) | S53: =IF($P53="","",INDEX('02_PROJECT_PORTFOLIO'!$Q$5:$Q$34,MATCH($P53,'02_PROJECT_PORTFOLIO'!$C$5:$C$34,0)))
A54: =IFERROR(INDEX('02_PROJECT_PORTFOLIO'!$A$5:$A$34,MATCH(11,'02_PROJECT_PORTFOLIO'!$AA$5:$AA$34,0))&" "&INDEX('02_PROJECT_PORTFOLIO'!$C$5:$C$34,MATCH(11,'02_PROJECT_PORTFOLIO'!$AA$5:$AA$34,0)),"") | C54: =IFERROR(INDEX('02_PROJECT_PORTFOLIO'!$M$5:$M$34,MATCH(11,'02_PROJECT_PORTFOLIO'!$AA$5:$AA$34,0)),"") | D54: =IFERROR(INDEX('02_PROJECT_PORTFOLIO'!$N$5:$N$34,MATCH(11,'02_PROJECT_PORTFOLIO'!$AA$5:$AA$34,0)),"") | E54: =IFERROR(INDEX('02_PROJECT_PORTFOLIO'!$D$5:$D$34,MATCH(11,'02_PROJECT_PORTFOLIO'!$AA$5:$AA$34,0))&" / "&INDEX('02_PROJECT_PORTFOLIO'!$E$5:$E$34,MATCH(11,'02_PROJECT_PORTFOLIO'!$AA$5:$AA$34,0)),"") | G54: =IFERROR(INDEX('02_PROJECT_PORTFOLIO'!$AB$5:$AB$34,MATCH(11,'02_PROJECT_PORTFOLIO'!$AA$5:$AA$34,0)),"") | I54: =IFERROR(INDEX('02_PROJECT_PORTFOLIO'!$L$5:$L$34,MATCH(11,'02_PROJECT_PORTFOLIO'!$AA$5:$AA$34,0)),"") | J54: =IFERROR(INDEX('02_PROJECT_PORTFOLIO'!$AC$5:$AC$34,MATCH(11,'02_PROJECT_PORTFOLIO'!$AA$5:$AA$34,0)),"") | L54: =IFERROR(INDEX('02_PROJECT_PORTFOLIO'!$T$5:$T$34,MATCH(11,'02_PROJECT_PORTFOLIO'!$AA$5:$AA$34,0))&IF(INDEX('02_PROJECT_PORTFOLIO'!$U$5:$U$34,MATCH(11,'02_PROJECT_PORTFOLIO'!$AA$5:$AA$34,0))="",""," ("&TEXT(INDEX('02_PROJECT_PORTFOLIO'!$U$5:$U$34,MATCH(11,'02_PROJECT_PORTFOLIO'!$AA$5:$AA$34,0)),"dd-mmm-yy")&")"),"") | P54: =IFERROR(INDEX('02_PROJECT_PORTFOLIO'!$C$5:$C$34,MATCH(10,'02_PROJECT_PORTFOLIO'!$Y$5:$Y$34,0)),"") | Q54: =IF($P54="","",INDEX('02_PROJECT_PORTFOLIO'!$O$5:$O$34,MATCH($P54,'02_PROJECT_PORTFOLIO'!$C$5:$C$34,0))) | R54: =IF($P54="","",INDEX('02_PROJECT_PORTFOLIO'!$P$5:$P$34,MATCH($P54,'02_PROJECT_PORTFOLIO'!$C$5:$C$34,0))) | S54: =IF($P54="","",INDEX('02_PROJECT_PORTFOLIO'!$Q$5:$Q$34,MATCH($P54,'02_PROJECT_PORTFOLIO'!$C$5:$C$34,0)))
A55: =IFERROR(INDEX('02_PROJECT_PORTFOLIO'!$A$5:$A$34,MATCH(12,'02_PROJECT_PORTFOLIO'!$AA$5:$AA$34,0))&" "&INDEX('02_PROJECT_PORTFOLIO'!$C$5:$C$34,MATCH(12,'02_PROJECT_PORTFOLIO'!$AA$5:$AA$34,0)),"") | C55: =IFERROR(INDEX('02_PROJECT_PORTFOLIO'!$M$5:$M$34,MATCH(12,'02_PROJECT_PORTFOLIO'!$AA$5:$AA$34,0)),"") | D55: =IFERROR(INDEX('02_PROJECT_PORTFOLIO'!$N$5:$N$34,MATCH(12,'02_PROJECT_PORTFOLIO'!$AA$5:$AA$34,0)),"") | E55: =IFERROR(INDEX('02_PROJECT_PORTFOLIO'!$D$5:$D$34,MATCH(12,'02_PROJECT_PORTFOLIO'!$AA$5:$AA$34,0))&" / "&INDEX('02_PROJECT_PORTFOLIO'!$E$5:$E$34,MATCH(12,'02_PROJECT_PORTFOLIO'!$AA$5:$AA$34,0)),"") | G55: =IFERROR(INDEX('02_PROJECT_PORTFOLIO'!$AB$5:$AB$34,MATCH(12,'02_PROJECT_PORTFOLIO'!$AA$5:$AA$34,0)),"") | I55: =IFERROR(INDEX('02_PROJECT_PORTFOLIO'!$L$5:$L$34,MATCH(12,'02_PROJECT_PORTFOLIO'!$AA$5:$AA$34,0)),"") | J55: =IFERROR(INDEX('02_PROJECT_PORTFOLIO'!$AC$5:$AC$34,MATCH(12,'02_PROJECT_PORTFOLIO'!$AA$5:$AA$34,0)),"") | L55: =IFERROR(INDEX('02_PROJECT_PORTFOLIO'!$T$5:$T$34,MATCH(12,'02_PROJECT_PORTFOLIO'!$AA$5:$AA$34,0))&IF(INDEX('02_PROJECT_PORTFOLIO'!$U$5:$U$34,MATCH(12,'02_PROJECT_PORTFOLIO'!$AA$5:$AA$34,0))="",""," ("&TEXT(INDEX('02_PROJECT_PORTFOLIO'!$U$5:$U$34,MATCH(12,'02_PROJECT_PORTFOLIO'!$AA$5:$AA$34,0)),"dd-mmm-yy")&")"),"")
A56: =IFERROR(INDEX('02_PROJECT_PORTFOLIO'!$A$5:$A$34,MATCH(13,'02_PROJECT_PORTFOLIO'!$AA$5:$AA$34,0))&" "&INDEX('02_PROJECT_PORTFOLIO'!$C$5:$C$34,MATCH(13,'02_PROJECT_PORTFOLIO'!$AA$5:$AA$34,0)),"") | C56: =IFERROR(INDEX('02_PROJECT_PORTFOLIO'!$M$5:$M$34,MATCH(13,'02_PROJECT_PORTFOLIO'!$AA$5:$AA$34,0)),"") | D56: =IFERROR(INDEX('02_PROJECT_PORTFOLIO'!$N$5:$N$34,MATCH(13,'02_PROJECT_PORTFOLIO'!$AA$5:$AA$34,0)),"") | E56: =IFERROR(INDEX('02_PROJECT_PORTFOLIO'!$D$5:$D$34,MATCH(13,'02_PROJECT_PORTFOLIO'!$AA$5:$AA$34,0))&" / "&INDEX('02_PROJECT_PORTFOLIO'!$E$5:$E$34,MATCH(13,'02_PROJECT_PORTFOLIO'!$AA$5:$AA$34,0)),"") | G56: =IFERROR(INDEX('02_PROJECT_PORTFOLIO'!$AB$5:$AB$34,MATCH(13,'02_PROJECT_PORTFOLIO'!$AA$5:$AA$34,0)),"") | I56: =IFERROR(INDEX('02_PROJECT_PORTFOLIO'!$L$5:$L$34,MATCH(13,'02_PROJECT_PORTFOLIO'!$AA$5:$AA$34,0)),"") | J56: =IFERROR(INDEX('02_PROJECT_PORTFOLIO'!$AC$5:$AC$34,MATCH(13,'02_PROJECT_PORTFOLIO'!$AA$5:$AA$34,0)),"") | L56: =IFERROR(INDEX('02_PROJECT_PORTFOLIO'!$T$5:$T$34,MATCH(13,'02_PROJECT_PORTFOLIO'!$AA$5:$AA$34,0))&IF(INDEX('02_PROJECT_PORTFOLIO'!$U$5:$U$34,MATCH(13,'02_PROJECT_PORTFOLIO'!$AA$5:$AA$34,0))="",""," ("&TEXT(INDEX('02_PROJECT_PORTFOLIO'!$U$5:$U$34,MATCH(13,'02_PROJECT_PORTFOLIO'!$AA$5:$AA$34,0)),"dd-mmm-yy")&")"),"") | P56: BLOCK 6 - MONTHLY MILESTONE DELIVERY (BASELINE vs ACTUAL)
A57: =IFERROR(INDEX('02_PROJECT_PORTFOLIO'!$A$5:$A$34,MATCH(14,'02_PROJECT_PORTFOLIO'!$AA$5:$AA$34,0))&" "&INDEX('02_PROJECT_PORTFOLIO'!$C$5:$C$34,MATCH(14,'02_PROJECT_PORTFOLIO'!$AA$5:$AA$34,0)),"") | C57: =IFERROR(INDEX('02_PROJECT_PORTFOLIO'!$M$5:$M$34,MATCH(14,'02_PROJECT_PORTFOLIO'!$AA$5:$AA$34,0)),"") | D57: =IFERROR(INDEX('02_PROJECT_PORTFOLIO'!$N$5:$N$34,MATCH(14,'02_PROJECT_PORTFOLIO'!$AA$5:$AA$34,0)),"") | E57: =IFERROR(INDEX('02_PROJECT_PORTFOLIO'!$D$5:$D$34,MATCH(14,'02_PROJECT_PORTFOLIO'!$AA$5:$AA$34,0))&" / "&INDEX('02_PROJECT_PORTFOLIO'!$E$5:$E$34,MATCH(14,'02_PROJECT_PORTFOLIO'!$AA$5:$AA$34,0)),"") | G57: =IFERROR(INDEX('02_PROJECT_PORTFOLIO'!$AB$5:$AB$34,MATCH(14,'02_PROJECT_PORTFOLIO'!$AA$5:$AA$34,0)),"") | I57: =IFERROR(INDEX('02_PROJECT_PORTFOLIO'!$L$5:$L$34,MATCH(14,'02_PROJECT_PORTFOLIO'!$AA$5:$AA$34,0)),"") | J57: =IFERROR(INDEX('02_PROJECT_PORTFOLIO'!$AC$5:$AC$34,MATCH(14,'02_PROJECT_PORTFOLIO'!$AA$5:$AA$34,0)),"") | L57: =IFERROR(INDEX('02_PROJECT_PORTFOLIO'!$T$5:$T$34,MATCH(14,'02_PROJECT_PORTFOLIO'!$AA$5:$AA$34,0))&IF(INDEX('02_PROJECT_PORTFOLIO'!$U$5:$U$34,MATCH(14,'02_PROJECT_PORTFOLIO'!$AA$5:$AA$34,0))="",""," ("&TEXT(INDEX('02_PROJECT_PORTFOLIO'!$U$5:$U$34,MATCH(14,'02_PROJECT_PORTFOLIO'!$AA$5:$AA$34,0)),"dd-mmm-yy")&")"),"") | P57: Month | Q57: Month start | R57: Baseline | S57: Actual
A58: =IFERROR(INDEX('02_PROJECT_PORTFOLIO'!$A$5:$A$34,MATCH(15,'02_PROJECT_PORTFOLIO'!$AA$5:$AA$34,0))&" "&INDEX('02_PROJECT_PORTFOLIO'!$C$5:$C$34,MATCH(15,'02_PROJECT_PORTFOLIO'!$AA$5:$AA$34,0)),"") | C58: =IFERROR(INDEX('02_PROJECT_PORTFOLIO'!$M$5:$M$34,MATCH(15,'02_PROJECT_PORTFOLIO'!$AA$5:$AA$34,0)),"") | D58: =IFERROR(INDEX('02_PROJECT_PORTFOLIO'!$N$5:$N$34,MATCH(15,'02_PROJECT_PORTFOLIO'!$AA$5:$AA$34,0)),"") | E58: =IFERROR(INDEX('02_PROJECT_PORTFOLIO'!$D$5:$D$34,MATCH(15,'02_PROJECT_PORTFOLIO'!$AA$5:$AA$34,0))&" / "&INDEX('02_PROJECT_PORTFOLIO'!$E$5:$E$34,MATCH(15,'02_PROJECT_PORTFOLIO'!$AA$5:$AA$34,0)),"") | G58: =IFERROR(INDEX('02_PROJECT_PORTFOLIO'!$AB$5:$AB$34,MATCH(15,'02_PROJECT_PORTFOLIO'!$AA$5:$AA$34,0)),"") | I58: =IFERROR(INDEX('02_PROJECT_PORTFOLIO'!$L$5:$L$34,MATCH(15,'02_PROJECT_PORTFOLIO'!$AA$5:$AA$34,0)),"") | J58: =IFERROR(INDEX('02_PROJECT_PORTFOLIO'!$AC$5:$AC$34,MATCH(15,'02_PROJECT_PORTFOLIO'!$AA$5:$AA$34,0)),"") | L58: =IFERROR(INDEX('02_PROJECT_PORTFOLIO'!$T$5:$T$34,MATCH(15,'02_PROJECT_PORTFOLIO'!$AA$5:$AA$34,0))&IF(INDEX('02_PROJECT_PORTFOLIO'!$U$5:$U$34,MATCH(15,'02_PROJECT_PORTFOLIO'!$AA$5:$AA$34,0))="",""," ("&TEXT(INDEX('02_PROJECT_PORTFOLIO'!$U$5:$U$34,MATCH(15,'02_PROJECT_PORTFOLIO'!$AA$5:$AA$34,0)),"dd-mmm-yy")&")"),"") | P58: =TEXT($Q58,"mmm-yy") | Q58: =EOMONTH(TODAY(),-1)+1 | R58: =COUNTIFS('05_MILESTONES'!$E$5:$E$34,">="&$Q58,'05_MILESTONES'!$E$5:$E$34,"<"&EDATE($Q58,1)) | S58: =COUNTIFS('05_MILESTONES'!$G$5:$G$34,">="&$Q58,'05_MILESTONES'!$G$5:$G$34,"<"&EDATE($Q58,1))
P59: =TEXT($Q59,"mmm-yy") | Q59: =EDATE(Q58,1) | R59: =COUNTIFS('05_MILESTONES'!$E$5:$E$34,">="&$Q59,'05_MILESTONES'!$E$5:$E$34,"<"&EDATE($Q59,1)) | S59: =COUNTIFS('05_MILESTONES'!$G$5:$G$34,">="&$Q59,'05_MILESTONES'!$G$5:$G$34,"<"&EDATE($Q59,1))
A60: PORTFOLIO CHARTS - ALL FORMULA DRIVEN, NO MANUAL UPDATING | P60: =TEXT($Q60,"mmm-yy") | Q60: =EDATE(Q59,1) | R60: =COUNTIFS('05_MILESTONES'!$E$5:$E$34,">="&$Q60,'05_MILESTONES'!$E$5:$E$34,"<"&EDATE($Q60,1)) | S60: =COUNTIFS('05_MILESTONES'!$G$5:$G$34,">="&$Q60,'05_MILESTONES'!$G$5:$G$34,"<"&EDATE($Q60,1))
P61: =TEXT($Q61,"mmm-yy") | Q61: =EDATE(Q60,1) | R61: =COUNTIFS('05_MILESTONES'!$E$5:$E$34,">="&$Q61,'05_MILESTONES'!$E$5:$E$34,"<"&EDATE($Q61,1)) | S61: =COUNTIFS('05_MILESTONES'!$G$5:$G$34,">="&$Q61,'05_MILESTONES'!$G$5:$G$34,"<"&EDATE($Q61,1))
P62: =TEXT($Q62,"mmm-yy") | Q62: =EDATE(Q61,1) | R62: =COUNTIFS('05_MILESTONES'!$E$5:$E$34,">="&$Q62,'05_MILESTONES'!$E$5:$E$34,"<"&EDATE($Q62,1)) | S62: =COUNTIFS('05_MILESTONES'!$G$5:$G$34,">="&$Q62,'05_MILESTONES'!$G$5:$G$34,"<"&EDATE($Q62,1))
P63: =TEXT($Q63,"mmm-yy") | Q63: =EDATE(Q62,1) | R63: =COUNTIFS('05_MILESTONES'!$E$5:$E$34,">="&$Q63,'05_MILESTONES'!$E$5:$E$34,"<"&EDATE($Q63,1)) | S63: =COUNTIFS('05_MILESTONES'!$G$5:$G$34,">="&$Q63,'05_MILESTONES'!$G$5:$G$34,"<"&EDATE($Q63,1))
P65: BLOCK 7 - OPEN RISKS BY SEVERITY
P66: Priority | Q66: Open risks
P67: Low | Q67: =COUNTIFS('06_RAID_LOG'!$C$5:$C$34,"Risk",'06_RAID_LOG'!$I$5:$I$34,P67,'06_RAID_LOG'!$N$5:$N$34,"<>Closed")
P68: Medium | Q68: =COUNTIFS('06_RAID_LOG'!$C$5:$C$34,"Risk",'06_RAID_LOG'!$I$5:$I$34,P68,'06_RAID_LOG'!$N$5:$N$34,"<>Closed")
P69: High | Q69: =COUNTIFS('06_RAID_LOG'!$C$5:$C$34,"Risk",'06_RAID_LOG'!$I$5:$I$34,P69,'06_RAID_LOG'!$N$5:$N$34,"<>Closed")
P70: Critical | Q70: =COUNTIFS('06_RAID_LOG'!$C$5:$C$34,"Risk",'06_RAID_LOG'!$I$5:$I$34,P70,'06_RAID_LOG'!$N$5:$N$34,"<>Closed")
P72: BLOCK 8 - ISSUES BY STATUS
P73: Status | Q73: Issues
P74: Open | Q74: =COUNTIFS('06_RAID_LOG'!$C$5:$C$34,"Issue",'06_RAID_LOG'!$N$5:$N$34,P74)
P75: In Progress | Q75: =COUNTIFS('06_RAID_LOG'!$C$5:$C$34,"Issue",'06_RAID_LOG'!$N$5:$N$34,P75)
P76: Closed | Q76: =COUNTIFS('06_RAID_LOG'!$C$5:$C$34,"Issue",'06_RAID_LOG'!$N$5:$N$34,P76)
P78: BLOCK 9 - OVERDUE ACTIONS BY OWNER
P79: Owner | Q79: Overdue actions
P80: Ahmed Khan | Q80: =COUNTIFS('07_ACTION_TRACKER'!$E$5:$E$34,P80,'07_ACTION_TRACKER'!$K$5:$K$34,">0")
P81: Lisa Chen | Q81: =COUNTIFS('07_ACTION_TRACKER'!$E$5:$E$34,P81,'07_ACTION_TRACKER'!$K$5:$K$34,">0")
P82: David Okoro | Q82: =COUNTIFS('07_ACTION_TRACKER'!$E$5:$E$34,P82,'07_ACTION_TRACKER'!$K$5:$K$34,">0")
P83: Maria Silva | Q83: =COUNTIFS('07_ACTION_TRACKER'!$E$5:$E$34,P83,'07_ACTION_TRACKER'!$K$5:$K$34,">0")
P84: Priya Raman | Q84: =COUNTIFS('07_ACTION_TRACKER'!$E$5:$E$34,P84,'07_ACTION_TRACKER'!$K$5:$K$34,">0")
P85: Tom Becker | Q85: =COUNTIFS('07_ACTION_TRACKER'!$E$5:$E$34,P85,'07_ACTION_TRACKER'!$K$5:$K$34,">0")
P86: Grace Alemu | Q86: =COUNTIFS('07_ACTION_TRACKER'!$E$5:$E$34,P86,'07_ACTION_TRACKER'!$K$5:$K$34,">0")
P87: Sarah Mitchell | Q87: =COUNTIFS('07_ACTION_TRACKER'!$E$5:$E$34,P87,'07_ACTION_TRACKER'!$K$5:$K$34,">0")
P89: BLOCK 10 - UPCOMING MILESTONES (NEXT 30 DAYS)
P90: Window | Q90: Milestones
P91: Next 7 days | Q91: =COUNTIFS('05_MILESTONES'!$F$5:$F$34,">="&TODAY(),'05_MILESTONES'!$F$5:$F$34,"<="&TODAY()+7,'05_MILESTONES'!$H$5:$H$34,"<>Complete")
P92: 8 - 14 days | Q92: =COUNTIFS('05_MILESTONES'!$F$5:$F$34,">"&TODAY()+7,'05_MILESTONES'!$F$5:$F$34,"<="&TODAY()+14,'05_MILESTONES'!$H$5:$H$34,"<>Complete")
P93: 15 - 30 days | Q93: =COUNTIFS('05_MILESTONES'!$F$5:$F$34,">"&TODAY()+14,'05_MILESTONES'!$F$5:$F$34,"<="&TODAY()+30,'05_MILESTONES'!$H$5:$H$34,"<>Complete")

Sheet 01B_PROJECT_DASHBOARD
A1: PROJECT DASHBOARD | P1: AUTOMATIC CHART DATA - FORMULAS ONLY, DO NOT EDIT
A2: ="SINGLE PROJECT VIEW - "&IF($D$3="","SELECT A PROJECT IN ROW 3",$D$3)
A3: SELECT PROJECT: | D3: ERP Implementation | I3: ="AS AT "&TEXT(TODAY(),"dd mmm yyyy")&" | LAST UPDATED: "&IFERROR(TEXT(INDEX('02_PROJECT_PORTFOLIO'!$W$5:$W$34,MATCH($D$3,'02_PROJECT_PORTFOLIO'!$C$5:$C$34,0)),"dd mmm yyyy"),"-") | P3: BLOCK 1 - TASK STATUS
A4: PROJECT SNAPSHOT - EVERY FIGURE FOLLOWS THE PROJECT SELECTED ABOVE | P4: Status | Q4: Tasks
A5: STATUS | C5: RAG | E5: % COMPLETE | G5: SCHEDULE VARIANCE | I5: APPROVED AMOUNT | K5: ACTUAL COST | M5: FORECAST COST | P5: Not Started | Q5: =COUNTIFS('04_WBS_SCHEDULE'!$B$5:$B$34,$D$3,'04_WBS_SCHEDULE'!$N$5:$N$34,P5)
A6: =IFERROR(INDEX('02_PROJECT_PORTFOLIO'!$M$5:$M$34,MATCH($D$3,'02_PROJECT_PORTFOLIO'!$C$5:$C$34,0)),"-") | C6: =IFERROR(INDEX('02_PROJECT_PORTFOLIO'!$N$5:$N$34,MATCH($D$3,'02_PROJECT_PORTFOLIO'!$C$5:$C$34,0)),"-") | E6: =IFERROR(INDEX('02_PROJECT_PORTFOLIO'!$L$5:$L$34,MATCH($D$3,'02_PROJECT_PORTFOLIO'!$C$5:$C$34,0)),"-") | G6: =IFERROR(INDEX('02_PROJECT_PORTFOLIO'!$R$5:$R$34,MATCH($D$3,'02_PROJECT_PORTFOLIO'!$C$5:$C$34,0)),"-") | I6: =IFERROR(INDEX('02_PROJECT_PORTFOLIO'!$O$5:$O$34,MATCH($D$3,'02_PROJECT_PORTFOLIO'!$C$5:$C$34,0)),"-") | K6: =IFERROR(INDEX('02_PROJECT_PORTFOLIO'!$P$5:$P$34,MATCH($D$3,'02_PROJECT_PORTFOLIO'!$C$5:$C$34,0)),"-") | M6: =IFERROR(INDEX('02_PROJECT_PORTFOLIO'!$Q$5:$Q$34,MATCH($D$3,'02_PROJECT_PORTFOLIO'!$C$5:$C$34,0)),"-") | P6: In Progress | Q6: =COUNTIFS('04_WBS_SCHEDULE'!$B$5:$B$34,$D$3,'04_WBS_SCHEDULE'!$N$5:$N$34,P6)
A7: LIFECYCLE STATUS | C7: OVERALL HEALTH | E7: REPORTED BY THE PM | G7: FORECAST vs BASELINE (DAYS) | I7: TOTAL APPROVED | K7: SPENT TO DATE | M7: EXPECTED AT COMPLETION | P7: Complete | Q7: =COUNTIFS('04_WBS_SCHEDULE'!$B$5:$B$34,$D$3,'04_WBS_SCHEDULE'!$N$5:$N$34,P7)
P8: Blocked | Q8: =COUNTIFS('04_WBS_SCHEDULE'!$B$5:$B$34,$D$3,'04_WBS_SCHEDULE'!$N$5:$N$34,P8)
A9: PROJECT HEALTH | C9: CUSTOMER | E9: PROJECT MANAGER | G9: DEPARTMENT | I9: PRIORITY | K9: START DATE | M9: BASELINE END
A10: =IFERROR(INDEX('02_PROJECT_PORTFOLIO'!$V$5:$V$34,MATCH($D$3,'02_PROJECT_PORTFOLIO'!$C$5:$C$34,0)),"-") | C10: =IFERROR(INDEX('02_PROJECT_PORTFOLIO'!$B$5:$B$34,MATCH($D$3,'02_PROJECT_PORTFOLIO'!$C$5:$C$34,0)),"-") | E10: =IFERROR(INDEX('02_PROJECT_PORTFOLIO'!$D$5:$D$34,MATCH($D$3,'02_PROJECT_PORTFOLIO'!$C$5:$C$34,0)),"-") | G10: =IFERROR(INDEX('02_PROJECT_PORTFOLIO'!$E$5:$E$34,MATCH($D$3,'02_PROJECT_PORTFOLIO'!$C$5:$C$34,0)),"-") | I10: =IFERROR(INDEX('02_PROJECT_PORTFOLIO'!$G$5:$G$34,MATCH($D$3,'02_PROJECT_PORTFOLIO'!$C$5:$C$34,0)),"-") | K10: =IFERROR(INDEX('02_PROJECT_PORTFOLIO'!$H$5:$H$34,MATCH($D$3,'02_PROJECT_PORTFOLIO'!$C$5:$C$34,0)),"-") | M10: =IFERROR(INDEX('02_PROJECT_PORTFOLIO'!$I$5:$I$34,MATCH($D$3,'02_PROJECT_PORTFOLIO'!$C$5:$C$34,0)),"-") | P10: BLOCK 2 - TASKS BY OWNER
A11: AUTOMATIC FLAG | C11: CLIENT / INTERNAL | E11: ACCOUNTABLE OWNER | G11: OWNING DEPARTMENT | I11: BUSINESS PRIORITY | K11: PLANNED START | M11: CONTRACTUAL FINISH | P11: Owner | Q11: Tasks
P12: Ahmed Khan | Q12: =COUNTIFS('04_WBS_SCHEDULE'!$B$5:$B$34,$D$3,'04_WBS_SCHEDULE'!$F$5:$F$34,P12)
A13: PROJECT DETAIL (AUTOMATIC) | P13: Lisa Chen | Q13: =COUNTIFS('04_WBS_SCHEDULE'!$B$5:$B$34,$D$3,'04_WBS_SCHEDULE'!$F$5:$F$34,P13)
A14: SCHEDULE VARIANCE (DAYS) | C14: =IFERROR(INDEX('02_PROJECT_PORTFOLIO'!$R$5:$R$34,MATCH($D$3,'02_PROJECT_PORTFOLIO'!$C$5:$C$34,0)),"-") | F14: FORECAST vs APPROVED | H14: =IFERROR(INDEX('02_PROJECT_PORTFOLIO'!$O$5:$O$34,MATCH($D$3,'02_PROJECT_PORTFOLIO'!$C$5:$C$34,0))-INDEX('02_PROJECT_PORTFOLIO'!$Q$5:$Q$34,MATCH($D$3,'02_PROJECT_PORTFOLIO'!$C$5:$C$34,0)),"-") | K14: COST UTILISATION | M14: =IFERROR(INDEX('02_PROJECT_PORTFOLIO'!$P$5:$P$34,MATCH($D$3,'02_PROJECT_PORTFOLIO'!$C$5:$C$34,0))/INDEX('02_PROJECT_PORTFOLIO'!$O$5:$O$34,MATCH($D$3,'02_PROJECT_PORTFOLIO'!$C$5:$C$34,0)),"-") | P14: David Okoro | Q14: =COUNTIFS('04_WBS_SCHEDULE'!$B$5:$B$34,$D$3,'04_WBS_SCHEDULE'!$F$5:$F$34,P14)
A15: BASELINE END | C15: =IFERROR(INDEX('02_PROJECT_PORTFOLIO'!$I$5:$I$34,MATCH($D$3,'02_PROJECT_PORTFOLIO'!$C$5:$C$34,0)),"-") | F15: FORECAST END | H15: =IFERROR(INDEX('02_PROJECT_PORTFOLIO'!$J$5:$J$34,MATCH($D$3,'02_PROJECT_PORTFOLIO'!$C$5:$C$34,0)),"-") | K15: ACTUAL END | M15: =IFERROR(INDEX('02_PROJECT_PORTFOLIO'!$K$5:$K$34,MATCH($D$3,'02_PROJECT_PORTFOLIO'!$C$5:$C$34,0)),"-") | P15: Maria Silva | Q15: =COUNTIFS('04_WBS_SCHEDULE'!$B$5:$B$34,$D$3,'04_WBS_SCHEDULE'!$F$5:$F$34,P15)
A16: OPEN RISKS | C16: =COUNTIFS('06_RAID_LOG'!$B$5:$B$34,$D$3,'06_RAID_LOG'!$C$5:$C$34,"Risk",'06_RAID_LOG'!$N$5:$N$34,"<>Closed") | F16: OPEN ISSUES | H16: =COUNTIFS('06_RAID_LOG'!$B$5:$B$34,$D$3,'06_RAID_LOG'!$C$5:$C$34,"Issue",'06_RAID_LOG'!$N$5:$N$34,"<>Closed") | K16: OVERDUE ACTIONS | M16: =COUNTIFS('07_ACTION_TRACKER'!$B$5:$B$34,$D$3,'07_ACTION_TRACKER'!$K$5:$K$34,">0") | P16: Priya Raman | Q16: =COUNTIFS('04_WBS_SCHEDULE'!$B$5:$B$34,$D$3,'04_WBS_SCHEDULE'!$F$5:$F$34,P16)
A17: NEXT MILESTONE | C17: =IFERROR(INDEX('05_MILESTONES'!$C$5:$C$34,MATCH($D$3&"|1",'05_MILESTONES'!$N$5:$N$34,0)),"-") | F17: MILESTONE DATE | H17: =IFERROR(INDEX('05_MILESTONES'!$F$5:$F$34,MATCH($D$3&"|1",'05_MILESTONES'!$N$5:$N$34,0)),"-") | K17: TASKS COMPLETE | M17: =IF(COUNTIF('04_WBS_SCHEDULE'!$B$5:$B$34,$D$3)=0,"-",COUNTIFS('04_WBS_SCHEDULE'!$B$5:$B$34,$D$3,'04_WBS_SCHEDULE'!$N$5:$N$34,"Complete")&" of "&COUNTIF('04_WBS_SCHEDULE'!$B$5:$B$34,$D$3)) | P17: Tom Becker | Q17: =COUNTIFS('04_WBS_SCHEDULE'!$B$5:$B$34,$D$3,'04_WBS_SCHEDULE'!$F$5:$F$34,P17)
P18: Grace Alemu | Q18: =COUNTIFS('04_WBS_SCHEDULE'!$B$5:$B$34,$D$3,'04_WBS_SCHEDULE'!$F$5:$F$34,P18)
A19: ="TOP OPEN RISKS ("&COUNTIFS('06_RAID_LOG'!$B$5:$B$34,$D$3,'06_RAID_LOG'!$C$5:$C$34,"Risk",'06_RAID_LOG'!$N$5:$N$34,"<>Closed")&")" | H19: ="TOP ISSUES ("&COUNTIFS('06_RAID_LOG'!$B$5:$B$34,$D$3,'06_RAID_LOG'!$C$5:$C$34,"Issue",'06_RAID_LOG'!$N$5:$N$34,"<>Closed")&")" | P19: Sarah Mitchell | Q19: =COUNTIFS('04_WBS_SCHEDULE'!$B$5:$B$34,$D$3,'04_WBS_SCHEDULE'!$F$5:$F$34,P19)
A20: ="•"&IFERROR(INDEX('06_RAID_LOG'!$D$5:$D$34,MATCH("Risk|"&$D$3&"|1",'06_RAID_LOG'!$T$5:$T$34,0))&" ("&INDEX('06_RAID_LOG'!$I$5:$I$34,MATCH("Risk|"&$D$3&"|1",'06_RAID_LOG'!$T$5:$T$34,0))&" - "&INDEX('06_RAID_LOG'!$J$5:$J$34,MATCH("Risk|"&$D$3&"|1",'06_RAID_LOG'!$T$5:$T$34,0))&")","") | H20: ="•"&IFERROR(INDEX('06_RAID_LOG'!$D$5:$D$34,MATCH("Issue|"&$D$3&"|1",'06_RAID_LOG'!$T$5:$T$34,0))&" ("&INDEX('06_RAID_LOG'!$I$5:$I$34,MATCH("Issue|"&$D$3&"|1",'06_RAID_LOG'!$T$5:$T$34,0))&" - "&INDEX('06_RAID_LOG'!$J$5:$J$34,MATCH("Issue|"&$D$3&"|1",'06_RAID_LOG'!$T$5:$T$34,0))&")","")
A21: ="•"&IFERROR(INDEX('06_RAID_LOG'!$D$5:$D$34,MATCH("Risk|"&$D$3&"|2",'06_RAID_LOG'!$T$5:$T$34,0))&" ("&INDEX('06_RAID_LOG'!$I$5:$I$34,MATCH("Risk|"&$D$3&"|2",'06_RAID_LOG'!$T$5:$T$34,0))&" - "&INDEX('06_RAID_LOG'!$J$5:$J$34,MATCH("Risk|"&$D$3&"|2",'06_RAID_LOG'!$T$5:$T$34,0))&")","") | H21: ="•"&IFERROR(INDEX('06_RAID_LOG'!$D$5:$D$34,MATCH("Issue|"&$D$3&"|2",'06_RAID_LOG'!$T$5:$T$34,0))&" ("&INDEX('06_RAID_LOG'!$I$5:$I$34,MATCH("Issue|"&$D$3&"|2",'06_RAID_LOG'!$T$5:$T$34,0))&" - "&INDEX('06_RAID_LOG'!$J$5:$J$34,MATCH("Issue|"&$D$3&"|2",'06_RAID_LOG'!$T$5:$T$34,0))&")","") | P21: BLOCK 3 - OPEN RAID BY TYPE
A22: ="•"&IFERROR(INDEX('06_RAID_LOG'!$D$5:$D$34,MATCH("Risk|"&$D$3&"|3",'06_RAID_LOG'!$T$5:$T$34,0))&" ("&INDEX('06_RAID_LOG'!$I$5:$I$34,MATCH("Risk|"&$D$3&"|3",'06_RAID_LOG'!$T$5:$T$34,0))&" - "&INDEX('06_RAID_LOG'!$J$5:$J$34,MATCH("Risk|"&$D$3&"|3",'06_RAID_LOG'!$T$5:$T$34,0))&")","") | H22: ="•"&IFERROR(INDEX('06_RAID_LOG'!$D$5:$D$34,MATCH("Issue|"&$D$3&"|3",'06_RAID_LOG'!$T$5:$T$34,0))&" ("&INDEX('06_RAID_LOG'!$I$5:$I$34,MATCH("Issue|"&$D$3&"|3",'06_RAID_LOG'!$T$5:$T$34,0))&" - "&INDEX('06_RAID_LOG'!$J$5:$J$34,MATCH("Issue|"&$D$3&"|3",'06_RAID_LOG'!$T$5:$T$34,0))&")","") | P22: Type | Q22: Open items
A23: ="•"&IFERROR(INDEX('06_RAID_LOG'!$D$5:$D$34,MATCH("Risk|"&$D$3&"|4",'06_RAID_LOG'!$T$5:$T$34,0))&" ("&INDEX('06_RAID_LOG'!$I$5:$I$34,MATCH("Risk|"&$D$3&"|4",'06_RAID_LOG'!$T$5:$T$34,0))&" - "&INDEX('06_RAID_LOG'!$J$5:$J$34,MATCH("Risk|"&$D$3&"|4",'06_RAID_LOG'!$T$5:$T$34,0))&")","") | H23: ="•"&IFERROR(INDEX('06_RAID_LOG'!$D$5:$D$34,MATCH("Issue|"&$D$3&"|4",'06_RAID_LOG'!$T$5:$T$34,0))&" ("&INDEX('06_RAID_LOG'!$I$5:$I$34,MATCH("Issue|"&$D$3&"|4",'06_RAID_LOG'!$T$5:$T$34,0))&" - "&INDEX('06_RAID_LOG'!$J$5:$J$34,MATCH("Issue|"&$D$3&"|4",'06_RAID_LOG'!$T$5:$T$34,0))&")","") | P23: Risk | Q23: =COUNTIFS('06_RAID_LOG'!$B$5:$B$34,$D$3,'06_RAID_LOG'!$C$5:$C$34,P23,'06_RAID_LOG'!$N$5:$N$34,"<>Closed")
A24: ="•"&IFERROR(INDEX('06_RAID_LOG'!$D$5:$D$34,MATCH("Risk|"&$D$3&"|5",'06_RAID_LOG'!$T$5:$T$34,0))&" ("&INDEX('06_RAID_LOG'!$I$5:$I$34,MATCH("Risk|"&$D$3&"|5",'06_RAID_LOG'!$T$5:$T$34,0))&" - "&INDEX('06_RAID_LOG'!$J$5:$J$34,MATCH("Risk|"&$D$3&"|5",'06_RAID_LOG'!$T$5:$T$34,0))&")","") | H24: ="•"&IFERROR(INDEX('06_RAID_LOG'!$D$5:$D$34,MATCH("Issue|"&$D$3&"|5",'06_RAID_LOG'!$T$5:$T$34,0))&" ("&INDEX('06_RAID_LOG'!$I$5:$I$34,MATCH("Issue|"&$D$3&"|5",'06_RAID_LOG'!$T$5:$T$34,0))&" - "&INDEX('06_RAID_LOG'!$J$5:$J$34,MATCH("Issue|"&$D$3&"|5",'06_RAID_LOG'!$T$5:$T$34,0))&")","") | P24: Assumption | Q24: =COUNTIFS('06_RAID_LOG'!$B$5:$B$34,$D$3,'06_RAID_LOG'!$C$5:$C$34,P24,'06_RAID_LOG'!$N$5:$N$34,"<>Closed")
P25: Issue | Q25: =COUNTIFS('06_RAID_LOG'!$B$5:$B$34,$D$3,'06_RAID_LOG'!$C$5:$C$34,P25,'06_RAID_LOG'!$N$5:$N$34,"<>Closed")
A26: ="OPEN ACTIONS ("&COUNTIFS('07_ACTION_TRACKER'!$B$5:$B$34,$D$3,'07_ACTION_TRACKER'!$I$5:$I$34,"<>Complete")&")" | H26: ="UPCOMING MILESTONES ("&COUNTIFS('05_MILESTONES'!$B$5:$B$34,$D$3,'05_MILESTONES'!$H$5:$H$34,"<>Complete")&")" | P26: Dependency | Q26: =COUNTIFS('06_RAID_LOG'!$B$5:$B$34,$D$3,'06_RAID_LOG'!$C$5:$C$34,P26,'06_RAID_LOG'!$N$5:$N$34,"<>Closed")
A27: ="•"&IFERROR(INDEX('07_ACTION_TRACKER'!$E$5:$E$34,MATCH($D$3&"|1",'07_ACTION_TRACKER'!$P$5:$P$34,0))&": "&LEFT(INDEX('07_ACTION_TRACKER'!$D$5:$D$34,MATCH($D$3&"|1",'07_ACTION_TRACKER'!$P$5:$P$34,0)),40)&" due "&TEXT(INDEX('07_ACTION_TRACKER'!$H$5:$H$34,MATCH($D$3&"|1",'07_ACTION_TRACKER'!$P$5:$P$34,0)),"dd-mmm"),"") | H27: ="•"&IFERROR(INDEX('05_MILESTONES'!$C$5:$C$34,MATCH($D$3&"|1",'05_MILESTONES'!$N$5:$N$34,0))&" ("&TEXT(INDEX('05_MILESTONES'!$F$5:$F$34,MATCH($D$3&"|1",'05_MILESTONES'!$N$5:$N$34,0)),"dd-mmm-yy")&", "&INDEX('05_MILESTONES'!$D$5:$D$34,MATCH($D$3&"|1",'05_MILESTONES'!$N$5:$N$34,0))&")","")
A28: ="•"&IFERROR(INDEX('07_ACTION_TRACKER'!$E$5:$E$34,MATCH($D$3&"|2",'07_ACTION_TRACKER'!$P$5:$P$34,0))&": "&LEFT(INDEX('07_ACTION_TRACKER'!$D$5:$D$34,MATCH($D$3&"|2",'07_ACTION_TRACKER'!$P$5:$P$34,0)),40)&" due "&TEXT(INDEX('07_ACTION_TRACKER'!$H$5:$H$34,MATCH($D$3&"|2",'07_ACTION_TRACKER'!$P$5:$P$34,0)),"dd-mmm"),"") | H28: ="•"&IFERROR(INDEX('05_MILESTONES'!$C$5:$C$34,MATCH($D$3&"|2",'05_MILESTONES'!$N$5:$N$34,0))&" ("&TEXT(INDEX('05_MILESTONES'!$F$5:$F$34,MATCH($D$3&"|2",'05_MILESTONES'!$N$5:$N$34,0)),"dd-mmm-yy")&", "&INDEX('05_MILESTONES'!$D$5:$D$34,MATCH($D$3&"|2",'05_MILESTONES'!$N$5:$N$34,0))&")","") | P28: BLOCK 4 - COST BY CATEGORY
A29: ="•"&IFERROR(INDEX('07_ACTION_TRACKER'!$E$5:$E$34,MATCH($D$3&"|3",'07_ACTION_TRACKER'!$P$5:$P$34,0))&": "&LEFT(INDEX('07_ACTION_TRACKER'!$D$5:$D$34,MATCH($D$3&"|3",'07_ACTION_TRACKER'!$P$5:$P$34,0)),40)&" due "&TEXT(INDEX('07_ACTION_TRACKER'!$H$5:$H$34,MATCH($D$3&"|3",'07_ACTION_TRACKER'!$P$5:$P$34,0)),"dd-mmm"),"") | H29: ="•"&IFERROR(INDEX('05_MILESTONES'!$C$5:$C$34,MATCH($D$3&"|3",'05_MILESTONES'!$N$5:$N$34,0))&" ("&TEXT(INDEX('05_MILESTONES'!$F$5:$F$34,MATCH($D$3&"|3",'05_MILESTONES'!$N$5:$N$34,0)),"dd-mmm-yy")&", "&INDEX('05_MILESTONES'!$D$5:$D$34,MATCH($D$3&"|3",'05_MILESTONES'!$N$5:$N$34,0))&")","") | P29: Category | Q29: Approved | R29: Actual | S29: Forecast
A30: ="•"&IFERROR(INDEX('07_ACTION_TRACKER'!$E$5:$E$34,MATCH($D$3&"|4",'07_ACTION_TRACKER'!$P$5:$P$34,0))&": "&LEFT(INDEX('07_ACTION_TRACKER'!$D$5:$D$34,MATCH($D$3&"|4",'07_ACTION_TRACKER'!$P$5:$P$34,0)),40)&" due "&TEXT(INDEX('07_ACTION_TRACKER'!$H$5:$H$34,MATCH($D$3&"|4",'07_ACTION_TRACKER'!$P$5:$P$34,0)),"dd-mmm"),"") | H30: ="•"&IFERROR(INDEX('05_MILESTONES'!$C$5:$C$34,MATCH($D$3&"|4",'05_MILESTONES'!$N$5:$N$34,0))&" ("&TEXT(INDEX('05_MILESTONES'!$F$5:$F$34,MATCH($D$3&"|4",'05_MILESTONES'!$N$5:$N$34,0)),"dd-mmm-yy")&", "&INDEX('05_MILESTONES'!$D$5:$D$34,MATCH($D$3&"|4",'05_MILESTONES'!$N$5:$N$34,0))&")","") | P30: Personnel | Q30: =SUMIFS('11_COST_MANAGEMENT'!$E$5:$E$34,'11_COST_MANAGEMENT'!$B$5:$B$34,$D$3,'11_COST_MANAGEMENT'!$C$5:$C$34,$P30) | R30: =SUMIFS('11_COST_MANAGEMENT'!$G$5:$G$34,'11_COST_MANAGEMENT'!$B$5:$B$34,$D$3,'11_COST_MANAGEMENT'!$C$5:$C$34,$P30) | S30: =SUMIFS('11_COST_MANAGEMENT'!$H$5:$H$34,'11_COST_MANAGEMENT'!$B$5:$B$34,$D$3,'11_COST_MANAGEMENT'!$C$5:$C$34,$P30)
A31: ="•"&IFERROR(INDEX('07_ACTION_TRACKER'!$E$5:$E$34,MATCH($D$3&"|5",'07_ACTION_TRACKER'!$P$5:$P$34,0))&": "&LEFT(INDEX('07_ACTION_TRACKER'!$D$5:$D$34,MATCH($D$3&"|5",'07_ACTION_TRACKER'!$P$5:$P$34,0)),40)&" due "&TEXT(INDEX('07_ACTION_TRACKER'!$H$5:$H$34,MATCH($D$3&"|5",'07_ACTION_TRACKER'!$P$5:$P$34,0)),"dd-mmm"),"") | H31: ="•"&IFERROR(INDEX('05_MILESTONES'!$C$5:$C$34,MATCH($D$3&"|5",'05_MILESTONES'!$N$5:$N$34,0))&" ("&TEXT(INDEX('05_MILESTONES'!$F$5:$F$34,MATCH($D$3&"|5",'05_MILESTONES'!$N$5:$N$34,0)),"dd-mmm-yy")&", "&INDEX('05_MILESTONES'!$D$5:$D$34,MATCH($D$3&"|5",'05_MILESTONES'!$N$5:$N$34,0))&")","") | P31: Software | Q31: =SUMIFS('11_COST_MANAGEMENT'!$E$5:$E$34,'11_COST_MANAGEMENT'!$B$5:$B$34,$D$3,'11_COST_MANAGEMENT'!$C$5:$C$34,$P31) | R31: =SUMIFS('11_COST_MANAGEMENT'!$G$5:$G$34,'11_COST_MANAGEMENT'!$B$5:$B$34,$D$3,'11_COST_MANAGEMENT'!$C$5:$C$34,$P31) | S31: =SUMIFS('11_COST_MANAGEMENT'!$H$5:$H$34,'11_COST_MANAGEMENT'!$B$5:$B$34,$D$3,'11_COST_MANAGEMENT'!$C$5:$C$34,$P31)
P32: Hardware | Q32: =SUMIFS('11_COST_MANAGEMENT'!$E$5:$E$34,'11_COST_MANAGEMENT'!$B$5:$B$34,$D$3,'11_COST_MANAGEMENT'!$C$5:$C$34,$P32) | R32: =SUMIFS('11_COST_MANAGEMENT'!$G$5:$G$34,'11_COST_MANAGEMENT'!$B$5:$B$34,$D$3,'11_COST_MANAGEMENT'!$C$5:$C$34,$P32) | S32: =SUMIFS('11_COST_MANAGEMENT'!$H$5:$H$34,'11_COST_MANAGEMENT'!$B$5:$B$34,$D$3,'11_COST_MANAGEMENT'!$C$5:$C$34,$P32)
A33: PROJECT CHARTS - RECALCULATE WHEN YOU CHANGE THE PROJECT SELECTED ABOVE | P33: Procurement | Q33: =SUMIFS('11_COST_MANAGEMENT'!$E$5:$E$34,'11_COST_MANAGEMENT'!$B$5:$B$34,$D$3,'11_COST_MANAGEMENT'!$C$5:$C$34,$P33) | R33: =SUMIFS('11_COST_MANAGEMENT'!$G$5:$G$34,'11_COST_MANAGEMENT'!$B$5:$B$34,$D$3,'11_COST_MANAGEMENT'!$C$5:$C$34,$P33) | S33: =SUMIFS('11_COST_MANAGEMENT'!$H$5:$H$34,'11_COST_MANAGEMENT'!$B$5:$B$34,$D$3,'11_COST_MANAGEMENT'!$C$5:$C$34,$P33)
P34: Consulting | Q34: =SUMIFS('11_COST_MANAGEMENT'!$E$5:$E$34,'11_COST_MANAGEMENT'!$B$5:$B$34,$D$3,'11_COST_MANAGEMENT'!$C$5:$C$34,$P34) | R34: =SUMIFS('11_COST_MANAGEMENT'!$G$5:$G$34,'11_COST_MANAGEMENT'!$B$5:$B$34,$D$3,'11_COST_MANAGEMENT'!$C$5:$C$34,$P34) | S34: =SUMIFS('11_COST_MANAGEMENT'!$H$5:$H$34,'11_COST_MANAGEMENT'!$B$5:$B$34,$D$3,'11_COST_MANAGEMENT'!$C$5:$C$34,$P34)
P35: Training | Q35: =SUMIFS('11_COST_MANAGEMENT'!$E$5:$E$34,'11_COST_MANAGEMENT'!$B$5:$B$34,$D$3,'11_COST_MANAGEMENT'!$C$5:$C$34,$P35) | R35: =SUMIFS('11_COST_MANAGEMENT'!$G$5:$G$34,'11_COST_MANAGEMENT'!$B$5:$B$34,$D$3,'11_COST_MANAGEMENT'!$C$5:$C$34,$P35) | S35: =SUMIFS('11_COST_MANAGEMENT'!$H$5:$H$34,'11_COST_MANAGEMENT'!$B$5:$B$34,$D$3,'11_COST_MANAGEMENT'!$C$5:$C$34,$P35)
P36: Travel | Q36: =SUMIFS('11_COST_MANAGEMENT'!$E$5:$E$34,'11_COST_MANAGEMENT'!$B$5:$B$34,$D$3,'11_COST_MANAGEMENT'!$C$5:$C$34,$P36) | R36: =SUMIFS('11_COST_MANAGEMENT'!$G$5:$G$34,'11_COST_MANAGEMENT'!$B$5:$B$34,$D$3,'11_COST_MANAGEMENT'!$C$5:$C$34,$P36) | S36: =SUMIFS('11_COST_MANAGEMENT'!$H$5:$H$34,'11_COST_MANAGEMENT'!$B$5:$B$34,$D$3,'11_COST_MANAGEMENT'!$C$5:$C$34,$P36)
P37: Other | Q37: =SUMIFS('11_COST_MANAGEMENT'!$E$5:$E$34,'11_COST_MANAGEMENT'!$B$5:$B$34,$D$3,'11_COST_MANAGEMENT'!$C$5:$C$34,$P37) | R37: =SUMIFS('11_COST_MANAGEMENT'!$G$5:$G$34,'11_COST_MANAGEMENT'!$B$5:$B$34,$D$3,'11_COST_MANAGEMENT'!$C$5:$C$34,$P37) | S37: =SUMIFS('11_COST_MANAGEMENT'!$H$5:$H$34,'11_COST_MANAGEMENT'!$B$5:$B$34,$D$3,'11_COST_MANAGEMENT'!$C$5:$C$34,$P37)
P39: BLOCK 5 - MILESTONE STATUS
P40: Status | Q40: Milestones
P41: Not Started | Q41: =COUNTIFS('05_MILESTONES'!$B$5:$B$34,$D$3,'05_MILESTONES'!$H$5:$H$34,P41)
P42: In Progress | Q42: =COUNTIFS('05_MILESTONES'!$B$5:$B$34,$D$3,'05_MILESTONES'!$H$5:$H$34,P42)
P43: Complete | Q43: =COUNTIFS('05_MILESTONES'!$B$5:$B$34,$D$3,'05_MILESTONES'!$H$5:$H$34,P43)
P44: Delayed | Q44: =COUNTIFS('05_MILESTONES'!$B$5:$B$34,$D$3,'05_MILESTONES'!$H$5:$H$34,P44)
P45: Cancelled | Q45: =COUNTIFS('05_MILESTONES'!$B$5:$B$34,$D$3,'05_MILESTONES'!$H$5:$H$34,P45)
P47: BLOCK 6 - ACTION STATUS
P48: Status | Q48: Actions
P49: Open | Q49: =COUNTIFS('07_ACTION_TRACKER'!$B$5:$B$34,$D$3,'07_ACTION_TRACKER'!$I$5:$I$34,P49)
P50: In Progress | Q50: =COUNTIFS('07_ACTION_TRACKER'!$B$5:$B$34,$D$3,'07_ACTION_TRACKER'!$I$5:$I$34,P50)
P51: Complete | Q51: =COUNTIFS('07_ACTION_TRACKER'!$B$5:$B$34,$D$3,'07_ACTION_TRACKER'!$I$5:$I$34,P51)
P52: Cancelled | Q52: =COUNTIFS('07_ACTION_TRACKER'!$B$5:$B$34,$D$3,'07_ACTION_TRACKER'!$I$5:$I$34,P52)

Sheet 02_PROJECT_PORTFOLIO
A1: PROJECT PORTFOLIO REGISTER
A2: Single source of truth for every project: customer, schedule, RAG, approved amount, actual and forecast cost. Dashboard KPIs and charts read from this table.
A3: SAMPLE DATA - every sample record is marked SAMPLE in the Notes column. Delete or overwrite them freely: all formulas, KPIs, charts and drop-downs keep working.
A4: Project ID | B4: Customer | C4: Project Name | D4: Project Manager | E4: Department | F4: Project Type | G4: Priority | H4: Start Date | I4: Baseline End Date | J4: Forecast End Date | K4: Actual End Date | L4: % Complete | M4: Status | N4: RAG | O4: Total Approved Amount | P4: Actual Cost | Q4: Forecast Cost | R4: Schedule Variance | S4: Cost Variance | T4: Next Milestone | U4: Milestone Date | V4: Project Health | W4: Last Updated | X4: Notes | Y4: ChartIdx | Z4: RedRank | AA4: ViewRank | AB4: Timeline | AC4: Budget/Actual
A5: PRJ-001 | B5: HEINEKEN | C5: ERP Implementation | D5: Ahmed Khan | E5: IT | F5: System Implementation | G5: Critical | H5: 46204 | I5: 46374 | J5: 46402 | L5: 0.62 | M5: Active | N5: Yellow | O5: 850000 | P5: 520000 | Q5: 910000 | R5: =IF(OR(I5="",J5=""),"",J5-I5) | S5: =IF(OR(O5="",P5=""),"",O5-P5) | T5: =IFERROR(INDEX('05_MILESTONES'!$C$5:$C$34,MATCH(AGGREGATE(15,6,'05_MILESTONES'!$M$5:$M$34/('05_MILESTONES'!$B$5:$B$34=$C5),1),'05_MILESTONES'!$M$5:$M$34,0)),"") | U5: =IFERROR(INT(AGGREGATE(15,6,'05_MILESTONES'!$M$5:$M$34/('05_MILESTONES'!$B$5:$B$34=$C5),1)),"") | V5: =IF(C5="","",IF(M5="Completed","Closed",IF(M5="Cancelled","N/A",IF(N5="Red","Critical",IF(OR(N5="Yellow",AND(Q5<>"",O5<>"",Q5>O5),AND(R5<>"",R5>7)),"Needs Attention","Healthy"))))) | W5: 46302 | X5: SAMPLE - ERP rollout, one month late on baseline. | Y5: =IF(C5="","",COUNTIF($C$5:$C5,"?*")) | Z5: =IF(OR(C5="",N5<>"Red"),"",COUNTIF($N$5:$N$34,"Red")-COUNTIF($N$5:$N5,"Red")+1) | AA5: =IF(C5="","",IF(AND(OR('01_EXECUTIVE_DASHBOARD'!$C$42="All",'01_EXECUTIVE_DASHBOARD'!$C$42=$M5),OR('01_EXECUTIVE_DASHBOARD'!$F$42="All",'01_EXECUTIVE_DASHBOARD'!$F$42=$N5),OR('01_EXECUTIVE_DASHBOARD'!$I$42="All",'01_EXECUTIVE_DASHBOARD'!$I$42=$D5)),SUMPRODUCT(($C$5:$C5<>"")*((('01_EXECUTIVE_DASHBOARD'!$C$42="All")+($M$5:$M5='01_EXECUTIVE_DASHBOARD'!$C$42))>0)*((('01_EXECUTIVE_DASHBOARD'!$F$42="All")+($N$5:$N5='01_EXECUTIVE_DASHBOARD'!$F$42))>0)*((('01_EXECUTIVE_DASHBOARD'!$I$42="All")+($D$5:$D5='01_EXECUTIVE_DASHBOARD'!$I$42))>0)),"")) | AB5: =IF(C5="","",TEXT(H5,"dd-mmm-yy")&" - "&TEXT(IF(K5<>"",K5,J5),"dd-mmm-yy")) | AC5: =IF(C5="","",TEXT(O5,"#,##0")&" / "&TEXT(P5,"#,##0"))
A6: PRJ-002 | B6: Internal | C6: Network Infrastructure Upgrade | D6: Lisa Chen | E6: IT | F6: Infrastructure | G6: High | H6: 46249 | I6: 46356 | J6: 46351 | L6: 0.45 | M6: Active | N6: Green | O6: 320000 | P6: 140000 | Q6: 305000 | R6: =IF(OR(I6="",J6=""),"",J6-I6) | S6: =IF(OR(O6="",P6=""),"",O6-P6) | T6: =IFERROR(INDEX('05_MILESTONES'!$C$5:$C$34,MATCH(AGGREGATE(15,6,'05_MILESTONES'!$M$5:$M$34/('05_MILESTONES'!$B$5:$B$34=$C6),1),'05_MILESTONES'!$M$5:$M$34,0)),"") | U6: =IFERROR(INT(AGGREGATE(15,6,'05_MILESTONES'!$M$5:$M$34/('05_MILESTONES'!$B$5:$B$34=$C6),1)),"") | V6: =IF(C6="","",IF(M6="Completed","Closed",IF(M6="Cancelled","N/A",IF(N6="Red","Critical",IF(OR(N6="Yellow",AND(Q6<>"",O6<>"",Q6>O6),AND(R6<>"",R6>7)),"Needs Attention","Healthy"))))) | W6: 46302 | X6: SAMPLE - ahead of plan, vendor on track. | Y6: =IF(C6="","",COUNTIF($C$5:$C6,"?*")) | Z6: =IF(OR(C6="",N6<>"Red"),"",COUNTIF($N$5:$N$34,"Red")-COUNTIF($N$5:$N6,"Red")+1) | AA6: =IF(C6="","",IF(AND(OR('01_EXECUTIVE_DASHBOARD'!$C$42="All",'01_EXECUTIVE_DASHBOARD'!$C$42=$M6),OR('01_EXECUTIVE_DASHBOARD'!$F$42="All",'01_EXECUTIVE_DASHBOARD'!$F$42=$N6),OR('01_EXECUTIVE_DASHBOARD'!$I$42="All",'01_EXECUTIVE_DASHBOARD'!$I$42=$D6)),SUMPRODUCT(($C$5:$C6<>"")*((('01_EXECUTIVE_DASHBOARD'!$C$42="All")+($M$5:$M6='01_EXECUTIVE_DASHBOARD'!$C$42))>0)*((('01_EXECUTIVE_DASHBOARD'!$F$42="All")+($N$5:$N6='01_EXECUTIVE_DASHBOARD'!$F$42))>0)*((('01_EXECUTIVE_DASHBOARD'!$I$42="All")+($D$5:$D6='01_EXECUTIVE_DASHBOARD'!$I$42))>0)),"")) | AB6: =IF(C6="","",TEXT(H6,"dd-mmm-yy")&" - "&TEXT(IF(K6<>"",K6,J6),"dd-mmm-yy")) | AC6: =IF(C6="","",TEXT(O6,"#,##0")&" / "&TEXT(P6,"#,##0"))
A7: PRJ-003 | B7: H A K F TRADING PLC | C7: HR Management System | D7: David Okoro | E7: HR | F7: System Implementation | G7: High | H7: 46266 | I7: 46477 | J7: 46522 | L7: 0.22 | M7: Active | N7: Red | O7: 480000 | P7: 150000 | Q7: 560000 | R7: =IF(OR(I7="",J7=""),"",J7-I7) | S7: =IF(OR(O7="",P7=""),"",O7-P7) | T7: =IFERROR(INDEX('05_MILESTONES'!$C$5:$C$34,MATCH(AGGREGATE(15,6,'05_MILESTONES'!$M$5:$M$34/('05_MILESTONES'!$B$5:$B$34=$C7),1),'05_MILESTONES'!$M$5:$M$34,0)),"") | U7: =IFERROR(INT(AGGREGATE(15,6,'05_MILESTONES'!$M$5:$M$34/('05_MILESTONES'!$B$5:$B$34=$C7),1)),"") | V7: =IF(C7="","",IF(M7="Completed","Closed",IF(M7="Cancelled","N/A",IF(N7="Red","Critical",IF(OR(N7="Yellow",AND(Q7<>"",O7<>"",Q7>O7),AND(R7<>"",R7>7)),"Needs Attention","Healthy"))))) | W7: 46301 | X7: SAMPLE - vendor delay and forecast overrun. | Y7: =IF(C7="","",COUNTIF($C$5:$C7,"?*")) | Z7: =IF(OR(C7="",N7<>"Red"),"",COUNTIF($N$5:$N$34,"Red")-COUNTIF($N$5:$N7,"Red")+1) | AA7: =IF(C7="","",IF(AND(OR('01_EXECUTIVE_DASHBOARD'!$C$42="All",'01_EXECUTIVE_DASHBOARD'!$C$42=$M7),OR('01_EXECUTIVE_DASHBOARD'!$F$42="All",'01_EXECUTIVE_DASHBOARD'!$F$42=$N7),OR('01_EXECUTIVE_DASHBOARD'!$I$42="All",'01_EXECUTIVE_DASHBOARD'!$I$42=$D7)),SUMPRODUCT(($C$5:$C7<>"")*((('01_EXECUTIVE_DASHBOARD'!$C$42="All")+($M$5:$M7='01_EXECUTIVE_DASHBOARD'!$C$42))>0)*((('01_EXECUTIVE_DASHBOARD'!$F$42="All")+($N$5:$N7='01_EXECUTIVE_DASHBOARD'!$F$42))>0)*((('01_EXECUTIVE_DASHBOARD'!$I$42="All")+($D$5:$D7='01_EXECUTIVE_DASHBOARD'!$I$42))>0)),"")) | AB7: =IF(C7="","",TEXT(H7,"dd-mmm-yy")&" - "&TEXT(IF(K7<>"",K7,J7),"dd-mmm-yy")) | AC7: =IF(C7="","",TEXT(O7,"#,##0")&" / "&TEXT(P7,"#,##0"))
A8: PRJ-004 | B8: MEGERSA MERGA MEGENTA | C8: Website Development | D8: Maria Silva | E8: Marketing | F8: Development | G8: Medium | H8: 46280 | I8: 46341 | J8: 46361 | L8: 0.4 | M8: On Hold | N8: Yellow | O8: 120000 | P8: 62000 | Q8: 138000 | R8: =IF(OR(I8="",J8=""),"",J8-I8) | S8: =IF(OR(O8="",P8=""),"",O8-P8) | T8: =IFERROR(INDEX('05_MILESTONES'!$C$5:$C$34,MATCH(AGGREGATE(15,6,'05_MILESTONES'!$M$5:$M$34/('05_MILESTONES'!$B$5:$B$34=$C8),1),'05_MILESTONES'!$M$5:$M$34,0)),"") | U8: =IFERROR(INT(AGGREGATE(15,6,'05_MILESTONES'!$M$5:$M$34/('05_MILESTONES'!$B$5:$B$34=$C8),1)),"") | V8: =IF(C8="","",IF(M8="Completed","Closed",IF(M8="Cancelled","N/A",IF(N8="Red","Critical",IF(OR(N8="Yellow",AND(Q8<>"",O8<>"",Q8>O8),AND(R8<>"",R8>7)),"Needs Attention","Healthy"))))) | W8: 46300 | X8: SAMPLE - paused pending content approval. | Y8: =IF(C8="","",COUNTIF($C$5:$C8,"?*")) | Z8: =IF(OR(C8="",N8<>"Red"),"",COUNTIF($N$5:$N$34,"Red")-COUNTIF($N$5:$N8,"Red")+1) | AA8: =IF(C8="","",IF(AND(OR('01_EXECUTIVE_DASHBOARD'!$C$42="All",'01_EXECUTIVE_DASHBOARD'!$C$42=$M8),OR('01_EXECUTIVE_DASHBOARD'!$F$42="All",'01_EXECUTIVE_DASHBOARD'!$F$42=$N8),OR('01_EXECUTIVE_DASHBOARD'!$I$42="All",'01_EXECUTIVE_DASHBOARD'!$I$42=$D8)),SUMPRODUCT(($C$5:$C8<>"")*((('01_EXECUTIVE_DASHBOARD'!$C$42="All")+($M$5:$M8='01_EXECUTIVE_DASHBOARD'!$C$42))>0)*((('01_EXECUTIVE_DASHBOARD'!$F$42="All")+($N$5:$N8='01_EXECUTIVE_DASHBOARD'!$F$42))>0)*((('01_EXECUTIVE_DASHBOARD'!$I$42="All")+($D$5:$D8='01_EXECUTIVE_DASHBOARD'!$I$42))>0)),"")) | AB8: =IF(C8="","",TEXT(H8,"dd-mmm-yy")&" - "&TEXT(IF(K8<>"",K8,J8),"dd-mmm-yy")) | AC8: =IF(C8="","",TEXT(O8,"#,##0")&" / "&TEXT(P8,"#,##0"))
A9: PRJ-005 | B9: Internal | C9: Office Security Upgrade | D9: Tom Becker | E9: Operations | F9: Infrastructure | G9: Medium | H9: 46280 | I9: 46371 | J9: 46371 | L9: 0.15 | M9: Active | N9: Green | O9: 60000 | P9: 9000 | Q9: 60000 | R9: =IF(OR(I9="",J9=""),"",J9-I9) | S9: =IF(OR(O9="",P9=""),"",O9-P9) | T9: =IFERROR(INDEX('05_MILESTONES'!$C$5:$C$34,MATCH(AGGREGATE(15,6,'05_MILESTONES'!$M$5:$M$34/('05_MILESTONES'!$B$5:$B$34=$C9),1),'05_MILESTONES'!$M$5:$M$34,0)),"") | U9: =IFERROR(INT(AGGREGATE(15,6,'05_MILESTONES'!$M$5:$M$34/('05_MILESTONES'!$B$5:$B$34=$C9),1)),"") | V9: =IF(C9="","",IF(M9="Completed","Closed",IF(M9="Cancelled","N/A",IF(N9="Red","Critical",IF(OR(N9="Yellow",AND(Q9<>"",O9<>"",Q9>O9),AND(R9<>"",R9>7)),"Needs Attention","Healthy"))))) | W9: 46301 | X9: SAMPLE - small works package. | Y9: =IF(C9="","",COUNTIF($C$5:$C9,"?*")) | Z9: =IF(OR(C9="",N9<>"Red"),"",COUNTIF($N$5:$N$34,"Red")-COUNTIF($N$5:$N9,"Red")+1) | AA9: =IF(C9="","",IF(AND(OR('01_EXECUTIVE_DASHBOARD'!$C$42="All",'01_EXECUTIVE_DASHBOARD'!$C$42=$M9),OR('01_EXECUTIVE_DASHBOARD'!$F$42="All",'01_EXECUTIVE_DASHBOARD'!$F$42=$N9),OR('01_EXECUTIVE_DASHBOARD'!$I$42="All",'01_EXECUTIVE_DASHBOARD'!$I$42=$D9)),SUMPRODUCT(($C$5:$C9<>"")*((('01_EXECUTIVE_DASHBOARD'!$C$42="All")+($M$5:$M9='01_EXECUTIVE_DASHBOARD'!$C$42))>0)*((('01_EXECUTIVE_DASHBOARD'!$F$42="All")+($N$5:$N9='01_EXECUTIVE_DASHBOARD'!$F$42))>0)*((('01_EXECUTIVE_DASHBOARD'!$I$42="All")+($D$5:$D9='01_EXECUTIVE_DASHBOARD'!$I$42))>0)),"")) | AB9: =IF(C9="","",TEXT(H9,"dd-mmm-yy")&" - "&TEXT(IF(K9<>"",K9,J9),"dd-mmm-yy")) | AC9: =IF(C9="","",TEXT(O9,"#,##0")&" / "&TEXT(P9,"#,##0"))
A10: PRJ-006 | B10: SELAMU SEGARO | C10: Payroll Reporting Portal | D10: Priya Raman | E10: Finance | F10: Development | G10: Medium | H10: 46113 | I10: 46295 | J10: 46295 | K10: 46293 | L10: 1 | M10: Completed | N10: Green | O10: 95000 | P10: 92000 | Q10: 92000 | R10: =IF(OR(I10="",J10=""),"",J10-I10) | S10: =IF(OR(O10="",P10=""),"",O10-P10) | T10: =IFERROR(INDEX('05_MILESTONES'!$C$5:$C$34,MATCH(AGGREGATE(15,6,'05_MILESTONES'!$M$5:$M$34/('05_MILESTONES'!$B$5:$B$34=$C10),1),'05_MILESTONES'!$M$5:$M$34,0)),"") | U10: =IFERROR(INT(AGGREGATE(15,6,'05_MILESTONES'!$M$5:$M$34/('05_MILESTONES'!$B$5:$B$34=$C10),1)),"") | V10: =IF(C10="","",IF(M10="Completed","Closed",IF(M10="Cancelled","N/A",IF(N10="Red","Critical",IF(OR(N10="Yellow",AND(Q10<>"",O10<>"",Q10>O10),AND(R10<>"",R10>7)),"Needs Attention","Healthy"))))) | W10: 46296 | X10: SAMPLE - closed, ready for closure checklist. | Y10: =IF(C10="","",COUNTIF($C$5:$C10,"?*")) | Z10: =IF(OR(C10="",N10<>"Red"),"",COUNTIF($N$5:$N$34,"Red")-COUNTIF($N$5:$N10,"Red")+1) | AA10: =IF(C10="","",IF(AND(OR('01_EXECUTIVE_DASHBOARD'!$C$42="All",'01_EXECUTIVE_DASHBOARD'!$C$42=$M10),OR('01_EXECUTIVE_DASHBOARD'!$F$42="All",'01_EXECUTIVE_DASHBOARD'!$F$42=$N10),OR('01_EXECUTIVE_DASHBOARD'!$I$42="All",'01_EXECUTIVE_DASHBOARD'!$I$42=$D10)),SUMPRODUCT(($C$5:$C10<>"")*((('01_EXECUTIVE_DASHBOARD'!$C$42="All")+($M$5:$M10='01_EXECUTIVE_DASHBOARD'!$C$42))>0)*((('01_EXECUTIVE_DASHBOARD'!$F$42="All")+($N$5:$N10='01_EXECUTIVE_DASHBOARD'!$F$42))>0)*((('01_EXECUTIVE_DASHBOARD'!$I$42="All")+($D$5:$D10='01_EXECUTIVE_DASHBOARD'!$I$42))>0)),"")) | AB10: =IF(C10="","",TEXT(H10,"dd-mmm-yy")&" - "&TEXT(IF(K10<>"",K10,J10),"dd-mmm-yy")) | AC10: =IF(C10="","",TEXT(O10,"#,##0")&" / "&TEXT(P10,"#,##0"))
A11: PRJ-007 | B11: Internal | C11: Legacy Fax System Decommission | D11: Tom Becker | E11: IT | F11: Maintenance | G11: Low | H11: 46174 | I11: 46265 | J11: 46265 | L11: 0.1 | M11: Cancelled | N11: Red | O11: 25000 | P11: 4000 | Q11: 4000 | R11: =IF(OR(I11="",J11=""),"",J11-I11) | S11: =IF(OR(O11="",P11=""),"",O11-P11) | T11: =IFERROR(INDEX('05_MILESTONES'!$C$5:$C$34,MATCH(AGGREGATE(15,6,'05_MILESTONES'!$M$5:$M$34/('05_MILESTONES'!$B$5:$B$34=$C11),1),'05_MILESTONES'!$M$5:$M$34,0)),"") | U11: =IFERROR(INT(AGGREGATE(15,6,'05_MILESTONES'!$M$5:$M$34/('05_MILESTONES'!$B$5:$B$34=$C11),1)),"") | V11: =IF(C11="","",IF(M11="Completed","Closed",IF(M11="Cancelled","N/A",IF(N11="Red","Critical",IF(OR(N11="Yellow",AND(Q11<>"",O11<>"",Q11>O11),AND(R11<>"",R11>7)),"Needs Attention","Healthy"))))) | W11: 46254 | X11: SAMPLE - cancelled, superseded by network upgrade. | Y11: =IF(C11="","",COUNTIF($C$5:$C11,"?*")) | Z11: =IF(OR(C11="",N11<>"Red"),"",COUNTIF($N$5:$N$34,"Red")-COUNTIF($N$5:$N11,"Red")+1) | AA11: =IF(C11="","",IF(AND(OR('01_EXECUTIVE_DASHBOARD'!$C$42="All",'01_EXECUTIVE_DASHBOARD'!$C$42=$M11),OR('01_EXECUTIVE_DASHBOARD'!$F$42="All",'01_EXECUTIVE_DASHBOARD'!$F$42=$N11),OR('01_EXECUTIVE_DASHBOARD'!$I$42="All",'01_EXECUTIVE_DASHBOARD'!$I$42=$D11)),SUMPRODUCT(($C$5:$C11<>"")*((('01_EXECUTIVE_DASHBOARD'!$C$42="All")+($M$5:$M11='01_EXECUTIVE_DASHBOARD'!$C$42))>0)*((('01_EXECUTIVE_DASHBOARD'!$F$42="All")+($N$5:$N11='01_EXECUTIVE_DASHBOARD'!$F$42))>0)*((('01_EXECUTIVE_DASHBOARD'!$I$42="All")+($D$5:$D11='01_EXECUTIVE_DASHBOARD'!$I$42))>0)),"")) | AB11: =IF(C11="","",TEXT(H11,"dd-mmm-yy")&" - "&TEXT(IF(K11<>"",K11,J11),"dd-mmm-yy")) | AC11: =IF(C11="","",TEXT(O11,"#,##0")&" / "&TEXT(P11,"#,##0"))
R12: =IF(OR(I12="",J12=""),"",J12-I12) | S12: =IF(OR(O12="",P12=""),"",O12-P12) | T12: =IFERROR(INDEX('05_MILESTONES'!$C$5:$C$34,MATCH(AGGREGATE(15,6,'05_MILESTONES'!$M$5:$M$34/('05_MILESTONES'!$B$5:$B$34=$C12),1),'05_MILESTONES'!$M$5:$M$34,0)),"") | U12: =IFERROR(INT(AGGREGATE(15,6,'05_MILESTONES'!$M$5:$M$34/('05_MILESTONES'!$B$5:$B$34=$C12),1)),"") | V12: =IF(C12="","",IF(M12="Completed","Closed",IF(M12="Cancelled","N/A",IF(N12="Red","Critical",IF(OR(N12="Yellow",AND(Q12<>"",O12<>"",Q12>O12),AND(R12<>"",R12>7)),"Needs Attention","Healthy"))))) | Y12: =IF(C12="","",COUNTIF($C$5:$C12,"?*")) | Z12: =IF(OR(C12="",N12<>"Red"),"",COUNTIF($N$5:$N$34,"Red")-COUNTIF($N$5:$N12,"Red")+1) | AA12: =IF(C12="","",IF(AND(OR('01_EXECUTIVE_DASHBOARD'!$C$42="All",'01_EXECUTIVE_DASHBOARD'!$C$42=$M12),OR('01_EXECUTIVE_DASHBOARD'!$F$42="All",'01_EXECUTIVE_DASHBOARD'!$F$42=$N12),OR('01_EXECUTIVE_DASHBOARD'!$I$42="All",'01_EXECUTIVE_DASHBOARD'!$I$42=$D12)),SUMPRODUCT(($C$5:$C12<>"")*((('01_EXECUTIVE_DASHBOARD'!$C$42="All")+($M$5:$M12='01_EXECUTIVE_DASHBOARD'!$C$42))>0)*((('01_EXECUTIVE_DASHBOARD'!$F$42="All")+($N$5:$N12='01_EXECUTIVE_DASHBOARD'!$F$42))>0)*((('01_EXECUTIVE_DASHBOARD'!$I$42="All")+($D$5:$D12='01_EXECUTIVE_DASHBOARD'!$I$42))>0)),"")) | AB12: =IF(C12="","",TEXT(H12,"dd-mmm-yy")&" - "&TEXT(IF(K12<>"",K12,J12),"dd-mmm-yy")) | AC12: =IF(C12="","",TEXT(O12,"#,##0")&" / "&TEXT(P12,"#,##0"))
R13: =IF(OR(I13="",J13=""),"",J13-I13) | S13: =IF(OR(O13="",P13=""),"",O13-P13) | T13: =IFERROR(INDEX('05_MILESTONES'!$C$5:$C$34,MATCH(AGGREGATE(15,6,'05_MILESTONES'!$M$5:$M$34/('05_MILESTONES'!$B$5:$B$34=$C13),1),'05_MILESTONES'!$M$5:$M$34,0)),"") | U13: =IFERROR(INT(AGGREGATE(15,6,'05_MILESTONES'!$M$5:$M$34/('05_MILESTONES'!$B$5:$B$34=$C13),1)),"") | V13: =IF(C13="","",IF(M13="Completed","Closed",IF(M13="Cancelled","N/A",IF(N13="Red","Critical",IF(OR(N13="Yellow",AND(Q13<>"",O13<>"",Q13>O13),AND(R13<>"",R13>7)),"Needs Attention","Healthy"))))) | Y13: =IF(C13="","",COUNTIF($C$5:$C13,"?*")) | Z13: =IF(OR(C13="",N13<>"Red"),"",COUNTIF($N$5:$N$34,"Red")-COUNTIF($N$5:$N13,"Red")+1) | AA13: =IF(C13="","",IF(AND(OR('01_EXECUTIVE_DASHBOARD'!$C$42="All",'01_EXECUTIVE_DASHBOARD'!$C$42=$M13),OR('01_EXECUTIVE_DASHBOARD'!$F$42="All",'01_EXECUTIVE_DASHBOARD'!$F$42=$N13),OR('01_EXECUTIVE_DASHBOARD'!$I$42="All",'01_EXECUTIVE_DASHBOARD'!$I$42=$D13)),SUMPRODUCT(($C$5:$C13<>"")*((('01_EXECUTIVE_DASHBOARD'!$C$42="All")+($M$5:$M13='01_EXECUTIVE_DASHBOARD'!$C$42))>0)*((('01_EXECUTIVE_DASHBOARD'!$F$42="All")+($N$5:$N13='01_EXECUTIVE_DASHBOARD'!$F$42))>0)*((('01_EXECUTIVE_DASHBOARD'!$I$42="All")+($D$5:$D13='01_EXECUTIVE_DASHBOARD'!$I$42))>0)),"")) | AB13: =IF(C13="","",TEXT(H13,"dd-mmm-yy")&" - "&TEXT(IF(K13<>"",K13,J13),"dd-mmm-yy")) | AC13: =IF(C13="","",TEXT(O13,"#,##0")&" / "&TEXT(P13,"#,##0"))
R14: =IF(OR(I14="",J14=""),"",J14-I14) | S14: =IF(OR(O14="",P14=""),"",O14-P14) | T14: =IFERROR(INDEX('05_MILESTONES'!$C$5:$C$34,MATCH(AGGREGATE(15,6,'05_MILESTONES'!$M$5:$M$34/('05_MILESTONES'!$B$5:$B$34=$C14),1),'05_MILESTONES'!$M$5:$M$34,0)),"") | U14: =IFERROR(INT(AGGREGATE(15,6,'05_MILESTONES'!$M$5:$M$34/('05_MILESTONES'!$B$5:$B$34=$C14),1)),"") | V14: =IF(C14="","",IF(M14="Completed","Closed",IF(M14="Cancelled","N/A",IF(N14="Red","Critical",IF(OR(N14="Yellow",AND(Q14<>"",O14<>"",Q14>O14),AND(R14<>"",R14>7)),"Needs Attention","Healthy"))))) | Y14: =IF(C14="","",COUNTIF($C$5:$C14,"?*")) | Z14: =IF(OR(C14="",N14<>"Red"),"",COUNTIF($N$5:$N$34,"Red")-COUNTIF($N$5:$N14,"Red")+1) | AA14: =IF(C14="","",IF(AND(OR('01_EXECUTIVE_DASHBOARD'!$C$42="All",'01_EXECUTIVE_DASHBOARD'!$C$42=$M14),OR('01_EXECUTIVE_DASHBOARD'!$F$42="All",'01_EXECUTIVE_DASHBOARD'!$F$42=$N14),OR('01_EXECUTIVE_DASHBOARD'!$I$42="All",'01_EXECUTIVE_DASHBOARD'!$I$42=$D14)),SUMPRODUCT(($C$5:$C14<>"")*((('01_EXECUTIVE_DASHBOARD'!$C$42="All")+($M$5:$M14='01_EXECUTIVE_DASHBOARD'!$C$42))>0)*((('01_EXECUTIVE_DASHBOARD'!$F$42="All")+($N$5:$N14='01_EXECUTIVE_DASHBOARD'!$F$42))>0)*((('01_EXECUTIVE_DASHBOARD'!$I$42="All")+($D$5:$D14='01_EXECUTIVE_DASHBOARD'!$I$42))>0)),"")) | AB14: =IF(C14="","",TEXT(H14,"dd-mmm-yy")&" - "&TEXT(IF(K14<>"",K14,J14),"dd-mmm-yy")) | AC14: =IF(C14="","",TEXT(O14,"#,##0")&" / "&TEXT(P14,"#,##0"))
R15: =IF(OR(I15="",J15=""),"",J15-I15) | S15: =IF(OR(O15="",P15=""),"",O15-P15) | T15: =IFERROR(INDEX('05_MILESTONES'!$C$5:$C$34,MATCH(AGGREGATE(15,6,'05_MILESTONES'!$M$5:$M$34/('05_MILESTONES'!$B$5:$B$34=$C15),1),'05_MILESTONES'!$M$5:$M$34,0)),"") | U15: =IFERROR(INT(AGGREGATE(15,6,'05_MILESTONES'!$M$5:$M$34/('05_MILESTONES'!$B$5:$B$34=$C15),1)),"") | V15: =IF(C15="","",IF(M15="Completed","Closed",IF(M15="Cancelled","N/A",IF(N15="Red","Critical",IF(OR(N15="Yellow",AND(Q15<>"",O15<>"",Q15>O15),AND(R15<>"",R15>7)),"Needs Attention","Healthy"))))) | Y15: =IF(C15="","",COUNTIF($C$5:$C15,"?*")) | Z15: =IF(OR(C15="",N15<>"Red"),"",COUNTIF($N$5:$N$34,"Red")-COUNTIF($N$5:$N15,"Red")+1) | AA15: =IF(C15="","",IF(AND(OR('01_EXECUTIVE_DASHBOARD'!$C$42="All",'01_EXECUTIVE_DASHBOARD'!$C$42=$M15),OR('01_EXECUTIVE_DASHBOARD'!$F$42="All",'01_EXECUTIVE_DASHBOARD'!$F$42=$N15),OR('01_EXECUTIVE_DASHBOARD'!$I$42="All",'01_EXECUTIVE_DASHBOARD'!$I$42=$D15)),SUMPRODUCT(($C$5:$C15<>"")*((('01_EXECUTIVE_DASHBOARD'!$C$42="All")+($M$5:$M15='01_EXECUTIVE_DASHBOARD'!$C$42))>0)*((('01_EXECUTIVE_DASHBOARD'!$F$42="All")+($N$5:$N15='01_EXECUTIVE_DASHBOARD'!$F$42))>0)*((('01_EXECUTIVE_DASHBOARD'!$I$42="All")+($D$5:$D15='01_EXECUTIVE_DASHBOARD'!$I$42))>0)),"")) | AB15: =IF(C15="","",TEXT(H15,"dd-mmm-yy")&" - "&TEXT(IF(K15<>"",K15,J15),"dd-mmm-yy")) | AC15: =IF(C15="","",TEXT(O15,"#,##0")&" / "&TEXT(P15,"#,##0"))
R16: =IF(OR(I16="",J16=""),"",J16-I16) | S16: =IF(OR(O16="",P16=""),"",O16-P16) | T16: =IFERROR(INDEX('05_MILESTONES'!$C$5:$C$34,MATCH(AGGREGATE(15,6,'05_MILESTONES'!$M$5:$M$34/('05_MILESTONES'!$B$5:$B$34=$C16),1),'05_MILESTONES'!$M$5:$M$34,0)),"") | U16: =IFERROR(INT(AGGREGATE(15,6,'05_MILESTONES'!$M$5:$M$34/('05_MILESTONES'!$B$5:$B$34=$C16),1)),"") | V16: =IF(C16="","",IF(M16="Completed","Closed",IF(M16="Cancelled","N/A",IF(N16="Red","Critical",IF(OR(N16="Yellow",AND(Q16<>"",O16<>"",Q16>O16),AND(R16<>"",R16>7)),"Needs Attention","Healthy"))))) | Y16: =IF(C16="","",COUNTIF($C$5:$C16,"?*")) | Z16: =IF(OR(C16="",N16<>"Red"),"",COUNTIF($N$5:$N$34,"Red")-COUNTIF($N$5:$N16,"Red")+1) | AA16: =IF(C16="","",IF(AND(OR('01_EXECUTIVE_DASHBOARD'!$C$42="All",'01_EXECUTIVE_DASHBOARD'!$C$42=$M16),OR('01_EXECUTIVE_DASHBOARD'!$F$42="All",'01_EXECUTIVE_DASHBOARD'!$F$42=$N16),OR('01_EXECUTIVE_DASHBOARD'!$I$42="All",'01_EXECUTIVE_DASHBOARD'!$I$42=$D16)),SUMPRODUCT(($C$5:$C16<>"")*((('01_EXECUTIVE_DASHBOARD'!$C$42="All")+($M$5:$M16='01_EXECUTIVE_DASHBOARD'!$C$42))>0)*((('01_EXECUTIVE_DASHBOARD'!$F$42="All")+($N$5:$N16='01_EXECUTIVE_DASHBOARD'!$F$42))>0)*((('01_EXECUTIVE_DASHBOARD'!$I$42="All")+($D$5:$D16='01_EXECUTIVE_DASHBOARD'!$I$42))>0)),"")) | AB16: =IF(C16="","",TEXT(H16,"dd-mmm-yy")&" - "&TEXT(IF(K16<>"",K16,J16),"dd-mmm-yy")) | AC16: =IF(C16="","",TEXT(O16,"#,##0")&" / "&TEXT(P16,"#,##0"))
R17: =IF(OR(I17="",J17=""),"",J17-I17) | S17: =IF(OR(O17="",P17=""),"",O17-P17) | T17: =IFERROR(INDEX('05_MILESTONES'!$C$5:$C$34,MATCH(AGGREGATE(15,6,'05_MILESTONES'!$M$5:$M$34/('05_MILESTONES'!$B$5:$B$34=$C17),1),'05_MILESTONES'!$M$5:$M$34,0)),"") | U17: =IFERROR(INT(AGGREGATE(15,6,'05_MILESTONES'!$M$5:$M$34/('05_MILESTONES'!$B$5:$B$34=$C17),1)),"") | V17: =IF(C17="","",IF(M17="Completed","Closed",IF(M17="Cancelled","N/A",IF(N17="Red","Critical",IF(OR(N17="Yellow",AND(Q17<>"",O17<>"",Q17>O17),AND(R17<>"",R17>7)),"Needs Attention","Healthy"))))) | Y17: =IF(C17="","",COUNTIF($C$5:$C17,"?*")) | Z17: =IF(OR(C17="",N17<>"Red"),"",COUNTIF($N$5:$N$34,"Red")-COUNTIF($N$5:$N17,"Red")+1) | AA17: =IF(C17="","",IF(AND(OR('01_EXECUTIVE_DASHBOARD'!$C$42="All",'01_EXECUTIVE_DASHBOARD'!$C$42=$M17),OR('01_EXECUTIVE_DASHBOARD'!$F$42="All",'01_EXECUTIVE_DASHBOARD'!$F$42=$N17),OR('01_EXECUTIVE_DASHBOARD'!$I$42="All",'01_EXECUTIVE_DASHBOARD'!$I$42=$D17)),SUMPRODUCT(($C$5:$C17<>"")*((('01_EXECUTIVE_DASHBOARD'!$C$42="All")+($M$5:$M17='01_EXECUTIVE_DASHBOARD'!$C$42))>0)*((('01_EXECUTIVE_DASHBOARD'!$F$42="All")+($N$5:$N17='01_EXECUTIVE_DASHBOARD'!$F$42))>0)*((('01_EXECUTIVE_DASHBOARD'!$I$42="All")+($D$5:$D17='01_EXECUTIVE_DASHBOARD'!$I$42))>0)),"")) | AB17: =IF(C17="","",TEXT(H17,"dd-mmm-yy")&" - "&TEXT(IF(K17<>"",K17,J17),"dd-mmm-yy")) | AC17: =IF(C17="","",TEXT(O17,"#,##0")&" / "&TEXT(P17,"#,##0"))
R18: =IF(OR(I18="",J18=""),"",J18-I18) | S18: =IF(OR(O18="",P18=""),"",O18-P18) | T18: =IFERROR(INDEX('05_MILESTONES'!$C$5:$C$34,MATCH(AGGREGATE(15,6,'05_MILESTONES'!$M$5:$M$34/('05_MILESTONES'!$B$5:$B$34=$C18),1),'05_MILESTONES'!$M$5:$M$34,0)),"") | U18: =IFERROR(INT(AGGREGATE(15,6,'05_MILESTONES'!$M$5:$M$34/('05_MILESTONES'!$B$5:$B$34=$C18),1)),"") | V18: =IF(C18="","",IF(M18="Completed","Closed",IF(M18="Cancelled","N/A",IF(N18="Red","Critical",IF(OR(N18="Yellow",AND(Q18<>"",O18<>"",Q18>O18),AND(R18<>"",R18>7)),"Needs Attention","Healthy"))))) | Y18: =IF(C18="","",COUNTIF($C$5:$C18,"?*")) | Z18: =IF(OR(C18="",N18<>"Red"),"",COUNTIF($N$5:$N$34,"Red")-COUNTIF($N$5:$N18,"Red")+1) | AA18: =IF(C18="","",IF(AND(OR('01_EXECUTIVE_DASHBOARD'!$C$42="All",'01_EXECUTIVE_DASHBOARD'!$C$42=$M18),OR('01_EXECUTIVE_DASHBOARD'!$F$42="All",'01_EXECUTIVE_DASHBOARD'!$F$42=$N18),OR('01_EXECUTIVE_DASHBOARD'!$I$42="All",'01_EXECUTIVE_DASHBOARD'!$I$42=$D18)),SUMPRODUCT(($C$5:$C18<>"")*((('01_EXECUTIVE_DASHBOARD'!$C$42="All")+($M$5:$M18='01_EXECUTIVE_DASHBOARD'!$C$42))>0)*((('01_EXECUTIVE_DASHBOARD'!$F$42="All")+($N$5:$N18='01_EXECUTIVE_DASHBOARD'!$F$42))>0)*((('01_EXECUTIVE_DASHBOARD'!$I$42="All")+($D$5:$D18='01_EXECUTIVE_DASHBOARD'!$I$42))>0)),"")) | AB18: =IF(C18="","",TEXT(H18,"dd-mmm-yy")&" - "&TEXT(IF(K18<>"",K18,J18),"dd-mmm-yy")) | AC18: =IF(C18="","",TEXT(O18,"#,##0")&" / "&TEXT(P18,"#,##0"))
R19: =IF(OR(I19="",J19=""),"",J19-I19) | S19: =IF(OR(O19="",P19=""),"",O19-P19) | T19: =IFERROR(INDEX('05_MILESTONES'!$C$5:$C$34,MATCH(AGGREGATE(15,6,'05_MILESTONES'!$M$5:$M$34/('05_MILESTONES'!$B$5:$B$34=$C19),1),'05_MILESTONES'!$M$5:$M$34,0)),"") | U19: =IFERROR(INT(AGGREGATE(15,6,'05_MILESTONES'!$M$5:$M$34/('05_MILESTONES'!$B$5:$B$34=$C19),1)),"") | V19: =IF(C19="","",IF(M19="Completed","Closed",IF(M19="Cancelled","N/A",IF(N19="Red","Critical",IF(OR(N19="Yellow",AND(Q19<>"",O19<>"",Q19>O19),AND(R19<>"",R19>7)),"Needs Attention","Healthy"))))) | Y19: =IF(C19="","",COUNTIF($C$5:$C19,"?*")) | Z19: =IF(OR(C19="",N19<>"Red"),"",COUNTIF($N$5:$N$34,"Red")-COUNTIF($N$5:$N19,"Red")+1) | AA19: =IF(C19="","",IF(AND(OR('01_EXECUTIVE_DASHBOARD'!$C$42="All",'01_EXECUTIVE_DASHBOARD'!$C$42=$M19),OR('01_EXECUTIVE_DASHBOARD'!$F$42="All",'01_EXECUTIVE_DASHBOARD'!$F$42=$N19),OR('01_EXECUTIVE_DASHBOARD'!$I$42="All",'01_EXECUTIVE_DASHBOARD'!$I$42=$D19)),SUMPRODUCT(($C$5:$C19<>"")*((('01_EXECUTIVE_DASHBOARD'!$C$42="All")+($M$5:$M19='01_EXECUTIVE_DASHBOARD'!$C$42))>0)*((('01_EXECUTIVE_DASHBOARD'!$F$42="All")+($N$5:$N19='01_EXECUTIVE_DASHBOARD'!$F$42))>0)*((('01_EXECUTIVE_DASHBOARD'!$I$42="All")+($D$5:$D19='01_EXECUTIVE_DASHBOARD'!$I$42))>0)),"")) | AB19: =IF(C19="","",TEXT(H19,"dd-mmm-yy")&" - "&TEXT(IF(K19<>"",K19,J19),"dd-mmm-yy")) | AC19: =IF(C19="","",TEXT(O19,"#,##0")&" / "&TEXT(P19,"#,##0"))
R20: =IF(OR(I20="",J20=""),"",J20-I20) | S20: =IF(OR(O20="",P20=""),"",O20-P20) | T20: =IFERROR(INDEX('05_MILESTONES'!$C$5:$C$34,MATCH(AGGREGATE(15,6,'05_MILESTONES'!$M$5:$M$34/('05_MILESTONES'!$B$5:$B$34=$C20),1),'05_MILESTONES'!$M$5:$M$34,0)),"") | U20: =IFERROR(INT(AGGREGATE(15,6,'05_MILESTONES'!$M$5:$M$34/('05_MILESTONES'!$B$5:$B$34=$C20),1)),"") | V20: =IF(C20="","",IF(M20="Completed","Closed",IF(M20="Cancelled","N/A",IF(N20="Red","Critical",IF(OR(N20="Yellow",AND(Q20<>"",O20<>"",Q20>O20),AND(R20<>"",R20>7)),"Needs Attention","Healthy"))))) | Y20: =IF(C20="","",COUNTIF($C$5:$C20,"?*")) | Z20: =IF(OR(C20="",N20<>"Red"),"",COUNTIF($N$5:$N$34,"Red")-COUNTIF($N$5:$N20,"Red")+1) | AA20: =IF(C20="","",IF(AND(OR('01_EXECUTIVE_DASHBOARD'!$C$42="All",'01_EXECUTIVE_DASHBOARD'!$C$42=$M20),OR('01_EXECUTIVE_DASHBOARD'!$F$42="All",'01_EXECUTIVE_DASHBOARD'!$F$42=$N20),OR('01_EXECUTIVE_DASHBOARD'!$I$42="All",'01_EXECUTIVE_DASHBOARD'!$I$42=$D20)),SUMPRODUCT(($C$5:$C20<>"")*((('01_EXECUTIVE_DASHBOARD'!$C$42="All")+($M$5:$M20='01_EXECUTIVE_DASHBOARD'!$C$42))>0)*((('01_EXECUTIVE_DASHBOARD'!$F$42="All")+($N$5:$N20='01_EXECUTIVE_DASHBOARD'!$F$42))>0)*((('01_EXECUTIVE_DASHBOARD'!$I$42="All")+($D$5:$D20='01_EXECUTIVE_DASHBOARD'!$I$42))>0)),"")) | AB20: =IF(C20="","",TEXT(H20,"dd-mmm-yy")&" - "&TEXT(IF(K20<>"",K20,J20),"dd-mmm-yy")) | AC20: =IF(C20="","",TEXT(O20,"#,##0")&" / "&TEXT(P20,"#,##0"))
R21: =IF(OR(I21="",J21=""),"",J21-I21) | S21: =IF(OR(O21="",P21=""),"",O21-P21) | T21: =IFERROR(INDEX('05_MILESTONES'!$C$5:$C$34,MATCH(AGGREGATE(15,6,'05_MILESTONES'!$M$5:$M$34/('05_MILESTONES'!$B$5:$B$34=$C21),1),'05_MILESTONES'!$M$5:$M$34,0)),"") | U21: =IFERROR(INT(AGGREGATE(15,6,'05_MILESTONES'!$M$5:$M$34/('05_MILESTONES'!$B$5:$B$34=$C21),1)),"") | V21: =IF(C21="","",IF(M21="Completed","Closed",IF(M21="Cancelled","N/A",IF(N21="Red","Critical",IF(OR(N21="Yellow",AND(Q21<>"",O21<>"",Q21>O21),AND(R21<>"",R21>7)),"Needs Attention","Healthy"))))) | Y21: =IF(C21="","",COUNTIF($C$5:$C21,"?*")) | Z21: =IF(OR(C21="",N21<>"Red"),"",COUNTIF($N$5:$N$34,"Red")-COUNTIF($N$5:$N21,"Red")+1) | AA21: =IF(C21="","",IF(AND(OR('01_EXECUTIVE_DASHBOARD'!$C$42="All",'01_EXECUTIVE_DASHBOARD'!$C$42=$M21),OR('01_EXECUTIVE_DASHBOARD'!$F$42="All",'01_EXECUTIVE_DASHBOARD'!$F$42=$N21),OR('01_EXECUTIVE_DASHBOARD'!$I$42="All",'01_EXECUTIVE_DASHBOARD'!$I$42=$D21)),SUMPRODUCT(($C$5:$C21<>"")*((('01_EXECUTIVE_DASHBOARD'!$C$42="All")+($M$5:$M21='01_EXECUTIVE_DASHBOARD'!$C$42))>0)*((('01_EXECUTIVE_DASHBOARD'!$F$42="All")+($N$5:$N21='01_EXECUTIVE_DASHBOARD'!$F$42))>0)*((('01_EXECUTIVE_DASHBOARD'!$I$42="All")+($D$5:$D21='01_EXECUTIVE_DASHBOARD'!$I$42))>0)),"")) | AB21: =IF(C21="","",TEXT(H21,"dd-mmm-yy")&" - "&TEXT(IF(K21<>"",K21,J21),"dd-mmm-yy")) | AC21: =IF(C21="","",TEXT(O21,"#,##0")&" / "&TEXT(P21,"#,##0"))
R22: =IF(OR(I22="",J22=""),"",J22-I22) | S22: =IF(OR(O22="",P22=""),"",O22-P22) | T22: =IFERROR(INDEX('05_MILESTONES'!$C$5:$C$34,MATCH(AGGREGATE(15,6,'05_MILESTONES'!$M$5:$M$34/('05_MILESTONES'!$B$5:$B$34=$C22),1),'05_MILESTONES'!$M$5:$M$34,0)),"") | U22: =IFERROR(INT(AGGREGATE(15,6,'05_MILESTONES'!$M$5:$M$34/('05_MILESTONES'!$B$5:$B$34=$C22),1)),"") | V22: =IF(C22="","",IF(M22="Completed","Closed",IF(M22="Cancelled","N/A",IF(N22="Red","Critical",IF(OR(N22="Yellow",AND(Q22<>"",O22<>"",Q22>O22),AND(R22<>"",R22>7)),"Needs Attention","Healthy"))))) | Y22: =IF(C22="","",COUNTIF($C$5:$C22,"?*")) | Z22: =IF(OR(C22="",N22<>"Red"),"",COUNTIF($N$5:$N$34,"Red")-COUNTIF($N$5:$N22,"Red")+1) | AA22: =IF(C22="","",IF(AND(OR('01_EXECUTIVE_DASHBOARD'!$C$42="All",'01_EXECUTIVE_DASHBOARD'!$C$42=$M22),OR('01_EXECUTIVE_DASHBOARD'!$F$42="All",'01_EXECUTIVE_DASHBOARD'!$F$42=$N22),OR('01_EXECUTIVE_DASHBOARD'!$I$42="All",'01_EXECUTIVE_DASHBOARD'!$I$42=$D22)),SUMPRODUCT(($C$5:$C22<>"")*((('01_EXECUTIVE_DASHBOARD'!$C$42="All")+($M$5:$M22='01_EXECUTIVE_DASHBOARD'!$C$42))>0)*((('01_EXECUTIVE_DASHBOARD'!$F$42="All")+($N$5:$N22='01_EXECUTIVE_DASHBOARD'!$F$42))>0)*((('01_EXECUTIVE_DASHBOARD'!$I$42="All")+($D$5:$D22='01_EXECUTIVE_DASHBOARD'!$I$42))>0)),"")) | AB22: =IF(C22="","",TEXT(H22,"dd-mmm-yy")&" - "&TEXT(IF(K22<>"",K22,J22),"dd-mmm-yy")) | AC22: =IF(C22="","",TEXT(O22,"#,##0")&" / "&TEXT(P22,"#,##0"))
R23: =IF(OR(I23="",J23=""),"",J23-I23) | S23: =IF(OR(O23="",P23=""),"",O23-P23) | T23: =IFERROR(INDEX('05_MILESTONES'!$C$5:$C$34,MATCH(AGGREGATE(15,6,'05_MILESTONES'!$M$5:$M$34/('05_MILESTONES'!$B$5:$B$34=$C23),1),'05_MILESTONES'!$M$5:$M$34,0)),"") | U23: =IFERROR(INT(AGGREGATE(15,6,'05_MILESTONES'!$M$5:$M$34/('05_MILESTONES'!$B$5:$B$34=$C23),1)),"") | V23: =IF(C23="","",IF(M23="Completed","Closed",IF(M23="Cancelled","N/A",IF(N23="Red","Critical",IF(OR(N23="Yellow",AND(Q23<>"",O23<>"",Q23>O23),AND(R23<>"",R23>7)),"Needs Attention","Healthy"))))) | Y23: =IF(C23="","",COUNTIF($C$5:$C23,"?*")) | Z23: =IF(OR(C23="",N23<>"Red"),"",COUNTIF($N$5:$N$34,"Red")-COUNTIF($N$5:$N23,"Red")+1) | AA23: =IF(C23="","",IF(AND(OR('01_EXECUTIVE_DASHBOARD'!$C$42="All",'01_EXECUTIVE_DASHBOARD'!$C$42=$M23),OR('01_EXECUTIVE_DASHBOARD'!$F$42="All",'01_EXECUTIVE_DASHBOARD'!$F$42=$N23),OR('01_EXECUTIVE_DASHBOARD'!$I$42="All",'01_EXECUTIVE_DASHBOARD'!$I$42=$D23)),SUMPRODUCT(($C$5:$C23<>"")*((('01_EXECUTIVE_DASHBOARD'!$C$42="All")+($M$5:$M23='01_EXECUTIVE_DASHBOARD'!$C$42))>0)*((('01_EXECUTIVE_DASHBOARD'!$F$42="All")+($N$5:$N23='01_EXECUTIVE_DASHBOARD'!$F$42))>0)*((('01_EXECUTIVE_DASHBOARD'!$I$42="All")+($D$5:$D23='01_EXECUTIVE_DASHBOARD'!$I$42))>0)),"")) | AB23: =IF(C23="","",TEXT(H23,"dd-mmm-yy")&" - "&TEXT(IF(K23<>"",K23,J23),"dd-mmm-yy")) | AC23: =IF(C23="","",TEXT(O23,"#,##0")&" / "&TEXT(P23,"#,##0"))
... R34: =IF(OR(I34="",J34=""),"",J34-I34) | S34: =IF(OR(O34="",P34=""),"",O34-P34) | T34: =IFERROR(INDEX('05_MILESTONES'!$C$5:$C$34,MATCH(AGGREGATE(15,6,'05_MILESTONES'!$M$5:$M$34/('05_MILESTONES'!$B$5:$B$34=$C34),1),'05_MILESTONES'!$M$5:$M$34,0)),"") | U34: =IFERROR(INT(AGGREGATE(15,6,'05_MILESTONES'!$M$5:$M$34/('05_MILESTONES'!$B$5:$B$34=$C34),1)),"") | V34: =IF(C34="","",IF(M34="Completed","Closed",IF(M34="Cancelled","N/A",IF(N34="Red","Critical",IF(OR(N34="Yellow",AND(Q34<>"",O34<>"",Q34>O34),AND(R34<>"",R34>7)),"Needs Attention","Healthy"))))) | Y34: =IF(C34="","",COUNTIF($C$5:$C34,"?*")) | Z34: =IF(OR(C34="",N34<>"Red"),"",COUNTIF($N$5:$N$34,"Red")-COUNTIF($N$5:$N34,"Red")+1) | AA34: =IF(C34="","",IF(AND(OR('01_EXECUTIVE_DASHBOARD'!$C$42="All",'01_EXECUTIVE_DASHBOARD'!$C$42=$M34),OR('01_EXECUTIVE_DASHBOARD'!$F$42="All",'01_EXECUTIVE_DASHBOARD'!$F$42=$N34),OR('01_EXECUTIVE_DASHBOARD'!$I$42="All",'01_EXECUTIVE_DASHBOARD'!$I$42=$D34)),SUMPRODUCT(($C$5:$C34<>"")*((('01_EXECUTIVE_DASHBOARD'!$C$42="All")+($M$5:$M34='01_EXECUTIVE_DASHBOARD'!$C$42))>0)*((('01_EXECUTIVE_DASHBOARD'!$F$42="All")+($N$5:$N34='01_EXECUTIVE_DASHBOARD'!$F$42))>0)*((('01_EXECUTIVE_DASHBOARD'!$I$42="All")+($D$5:$D34='01_EXECUTIVE_DASHBOARD'!$I$42))>0)),"")) | AB34: =IF(C34="","",TEXT(H34,"dd-mmm-yy")&" - "&TEXT(IF(K34<>"",K34,J34),"dd-mmm-yy")) | AC34: =IF(C34="","",TEXT(O34,"#,##0")&" / "&TEXT(P34,"#,##0"))

Sheet 03_PROJECT_CHARTER
A1: PROJECT CHARTER
A2: One-page authorisation document for a single project. Choose the project and the identification block fills itself; the business case, scope and approvals are yours to write.
A3: Grey cells are automatic (from 02_PROJECT_PORTFOLIO and 06_RAID_LOG). White cells are for you. Print landscape, one page.
A4: SELECT A PROJECT - THE IDENTIFICATION BLOCK BELOW FILLS ITSELF
A5: PROJECT | B5: ERP Implementation
A6: LEGEND: grey cells = automatic from the registers | white cells = type here
A7: 1. PROJECT IDENTIFICATION (AUTOMATIC)
A8: Project ID | B8: =IFERROR(INDEX('02_PROJECT_PORTFOLIO'!$A$5:$A$34,MATCH($B$5,'02_PROJECT_PORTFOLIO'!$C$5:$C$34,0)),"-")
A9: Customer | B9: =IFERROR(INDEX('02_PROJECT_PORTFOLIO'!$B$5:$B$34,MATCH($B$5,'02_PROJECT_PORTFOLIO'!$C$5:$C$34,0)),"-")
A10: Project Manager | B10: =IFERROR(INDEX('02_PROJECT_PORTFOLIO'!$D$5:$D$34,MATCH($B$5,'02_PROJECT_PORTFOLIO'!$C$5:$C$34,0)),"-")
A11: Department | B11: =IFERROR(INDEX('02_PROJECT_PORTFOLIO'!$E$5:$E$34,MATCH($B$5,'02_PROJECT_PORTFOLIO'!$C$5:$C$34,0)),"-")
A12: Project Type | B12: =IFERROR(INDEX('02_PROJECT_PORTFOLIO'!$F$5:$F$34,MATCH($B$5,'02_PROJECT_PORTFOLIO'!$C$5:$C$34,0)),"-")
A13: Priority | B13: =IFERROR(INDEX('02_PROJECT_PORTFOLIO'!$G$5:$G$34,MATCH($B$5,'02_PROJECT_PORTFOLIO'!$C$5:$C$34,0)),"-")
A14: Start Date | B14: =IFERROR(INDEX('02_PROJECT_PORTFOLIO'!$H$5:$H$34,MATCH($B$5,'02_PROJECT_PORTFOLIO'!$C$5:$C$34,0)),"-")
A15: Baseline End Date | B15: =IFERROR(INDEX('02_PROJECT_PORTFOLIO'!$I$5:$I$34,MATCH($B$5,'02_PROJECT_PORTFOLIO'!$C$5:$C$34,0)),"-")
A16: Forecast End Date | B16: =IFERROR(INDEX('02_PROJECT_PORTFOLIO'!$J$5:$J$34,MATCH($B$5,'02_PROJECT_PORTFOLIO'!$C$5:$C$34,0)),"-")
A17: Total Approved Amount | B17: =IFERROR(INDEX('02_PROJECT_PORTFOLIO'!$O$5:$O$34,MATCH($B$5,'02_PROJECT_PORTFOLIO'!$C$5:$C$34,0)),"-")
A18: Actual Cost | B18: =IFERROR(INDEX('02_PROJECT_PORTFOLIO'!$P$5:$P$34,MATCH($B$5,'02_PROJECT_PORTFOLIO'!$C$5:$C$34,0)),"-")
A19: Status | B19: =IFERROR(INDEX('02_PROJECT_PORTFOLIO'!$M$5:$M$34,MATCH($B$5,'02_PROJECT_PORTFOLIO'!$C$5:$C$34,0)),"-")
A20: RAG | B20: =IFERROR(INDEX('02_PROJECT_PORTFOLIO'!$N$5:$N$34,MATCH($B$5,'02_PROJECT_PORTFOLIO'!$C$5:$C$34,0)),"-")
A21: 2. BUSINESS CASE (TYPE HERE)
A22: Problem / Opportunity
A23: Business Objective
A24: Expected Benefits
A25: Success Criteria
A26: 3. SCOPE (TYPE HERE)
A27: In Scope
A28: Out of Scope
A29: Key Deliverables
A30: 4. APPROACH & GOVERNANCE
A31: Delivery Approach
A32: Key Assumptions
A33: Top Open Risk (automatic) | B33: =IFERROR(INDEX('06_RAID_LOG'!$D$5:$D$34,MATCH("Risk|"&$B$5&"|1",'06_RAID_LOG'!$T$5:$T$34,0)),"No open risk recorded")
A34: Reporting & Governance
A35: 5. APPROVALS (TYPE HERE)
A36: Prepared By
A37: Reviewed By
A38: Approved By
A39: Approval Date
A40: Signature

Sheet 04_WBS_SCHEDULE
A1: WBS, SCHEDULE & GANTT
A2: Task-level plan with baseline, variance and an automatic weekly Gantt timeline (columns R onward). Green = on schedule, amber = minor delay, red = major delay.
A3: GANTT - ONE COLUMN PER WEEK | start date of the timeline comes from 23_SETTINGS!B5 | the highlighted week is this week
A4: WBS ID | B4: Project | C4: Phase | D4: Task | E4: Deliverable | F4: Owner | G4: Dependency | H4: Start Date | I4: Finish Date | J4: Baseline Start | K4: Baseline Finish | L4: Duration | M4: % Complete | N4: Status | O4: Variance | P4: Milestone | Q4: Notes | R4: ='23_SETTINGS'!$B$5 | S4: =R4+7 | T4: =S4+7 | U4: =T4+7 | V4: =U4+7 | W4: =V4+7 | X4: =W4+7 | Y4: =X4+7 | Z4: =Y4+7 | ... AO4: =AN4+7
A5: 1.0 | B5: ERP Implementation | C5: Initiation | D5: Project charter approval | E5: Signed charter | F5: Ahmed Khan | H5: 46204 | I5: 46213 | J5: 46204 | K5: 46213 | L5: =IF(OR(H5="",I5=""),"",I5-H5+1) | M5: 1 | N5: Complete | O5: =IF(OR(I5="",K5=""),"",I5-K5) | P5: Yes | Q5: SAMPLE | R5: =IF(AND($H5<>"",$I5<>"",$H5<=R$4+6,$I5>=R$4),1,"") | S5: =IF(AND($H5<>"",$I5<>"",$H5<=S$4+6,$I5>=S$4),1,"") | T5: =IF(AND($H5<>"",$I5<>"",$H5<=T$4+6,$I5>=T$4),1,"") | U5: =IF(AND($H5<>"",$I5<>"",$H5<=U$4+6,$I5>=U$4),1,"") | V5: =IF(AND($H5<>"",$I5<>"",$H5<=V$4+6,$I5>=V$4),1,"") | W5: =IF(AND($H5<>"",$I5<>"",$H5<=W$4+6,$I5>=W$4),1,"") | X5: =IF(AND($H5<>"",$I5<>"",$H5<=X$4+6,$I5>=X$4),1,"") | Y5: =IF(AND($H5<>"",$I5<>"",$H5<=Y$4+6,$I5>=Y$4),1,"") | ... AO5: =IF(AND($H5<>"",$I5<>"",$H5<=AO$4+6,$I5>=AO$4),1,"")
A6: 2.0 | B6: ERP Implementation | C6: Requirements | D6: Gather business requirements | E6: Requirements specification | F6: Priya Raman | G6: 1.0 | H6: 46216 | I6: 46241 | J6: 46216 | K6: 46241 | L6: =IF(OR(H6="",I6=""),"",I6-H6+1) | M6: 1 | N6: Complete | O6: =IF(OR(I6="",K6=""),"",I6-K6) | P6: Yes | Q6: SAMPLE | R6: =IF(AND($H6<>"",$I6<>"",$H6<=R$4+6,$I6>=R$4),1,"") | S6: =IF(AND($H6<>"",$I6<>"",$H6<=S$4+6,$I6>=S$4),1,"") | T6: =IF(AND($H6<>"",$I6<>"",$H6<=T$4+6,$I6>=T$4),1,"") | U6: =IF(AND($H6<>"",$I6<>"",$H6<=U$4+6,$I6>=U$4),1,"") | V6: =IF(AND($H6<>"",$I6<>"",$H6<=V$4+6,$I6>=V$4),1,"") | W6: =IF(AND($H6<>"",$I6<>"",$H6<=W$4+6,$I6>=W$4),1,"") | X6: =IF(AND($H6<>"",$I6<>"",$H6<=X$4+6,$I6>=X$4),1,"") | Y6: =IF(AND($H6<>"",$I6<>"",$H6<=Y$4+6,$I6>=Y$4),1,"") | ... AO6: =IF(AND($H6<>"",$I6<>"",$H6<=AO$4+6,$I6>=AO$4),1,"")
A7: 3.0 | B7: ERP Implementation | C7: Design | D7: Solution design workshops | E7: Design document | F7: Tom Becker | G7: 2.0 | H7: 46244 | I7: 46262 | J7: 46244 | K7: 46262 | L7: =IF(OR(H7="",I7=""),"",I7-H7+1) | M7: 1 | N7: Complete | O7: =IF(OR(I7="",K7=""),"",I7-K7) | P7: No | Q7: SAMPLE | R7: =IF(AND($H7<>"",$I7<>"",$H7<=R$4+6,$I7>=R$4),1,"") | S7: =IF(AND($H7<>"",$I7<>"",$H7<=S$4+6,$I7>=S$4),1,"") | T7: =IF(AND($H7<>"",$I7<>"",$H7<=T$4+6,$I7>=T$4),1,"") | U7: =IF(AND($H7<>"",$I7<>"",$H7<=U$4+6,$I7>=U$4),1,"") | V7: =IF(AND($H7<>"",$I7<>"",$H7<=V$4+6,$I7>=V$4),1,"") | W7: =IF(AND($H7<>"",$I7<>"",$H7<=W$4+6,$I7>=W$4),1,"") | X7: =IF(AND($H7<>"",$I7<>"",$H7<=X$4+6,$I7>=X$4),1,"") | Y7: =IF(AND($H7<>"",$I7<>"",$H7<=Y$4+6,$I7>=Y$4),1,"") | ... AO7: =IF(AND($H7<>"",$I7<>"",$H7<=AO$4+6,$I7>=AO$4),1,"")
A8: 4.0 | B8: ERP Implementation | C8: Build | D8: Configure core ERP modules | E8: Configured system | F8: Ahmed Khan | G8: 3.0 | H8: 46265 | I8: 46304 | J8: 46265 | K8: 46297 | L8: =IF(OR(H8="",I8=""),"",I8-H8+1) | M8: 0.7 | N8: In Progress | O8: =IF(OR(I8="",K8=""),"",I8-K8) | P8: No | Q8: SAMPLE - running 7 days late | R8: =IF(AND($H8<>"",$I8<>"",$H8<=R$4+6,$I8>=R$4),1,"") | S8: =IF(AND($H8<>"",$I8<>"",$H8<=S$4+6,$I8>=S$4),1,"") | T8: =IF(AND($H8<>"",$I8<>"",$H8<=T$4+6,$I8>=T$4),1,"") | U8: =IF(AND($H8<>"",$I8<>"",$H8<=U$4+6,$I8>=U$4),1,"") | V8: =IF(AND($H8<>"",$I8<>"",$H8<=V$4+6,$I8>=V$4),1,"") | W8: =IF(AND($H8<>"",$I8<>"",$H8<=W$4+6,$I8>=W$4),1,"") | X8: =IF(AND($H8<>"",$I8<>"",$H8<=X$4+6,$I8>=X$4),1,"") | Y8: =IF(AND($H8<>"",$I8<>"",$H8<=Y$4+6,$I8>=Y$4),1,"") | ... AO8: =IF(AND($H8<>"",$I8<>"",$H8<=AO$4+6,$I8>=AO$4),1,"")
A9: 5.0 | B9: ERP Implementation | C9: Build | D9: Data migration scripts | E9: Migration package | F9: David Okoro | G9: 4.0 | H9: 46300 | I9: 46325 | J9: 46293 | K9: 46318 | L9: =IF(OR(H9="",I9=""),"",I9-H9+1) | M9: 0.25 | N9: In Progress | O9: =IF(OR(I9="",K9=""),"",I9-K9) | P9: No | Q9: SAMPLE | R9: =IF(AND($H9<>"",$I9<>"",$H9<=R$4+6,$I9>=R$4),1,"") | S9: =IF(AND($H9<>"",$I9<>"",$H9<=S$4+6,$I9>=S$4),1,"") | T9: =IF(AND($H9<>"",$I9<>"",$H9<=T$4+6,$I9>=T$4),1,"") | U9: =IF(AND($H9<>"",$I9<>"",$H9<=U$4+6,$I9>=U$4),1,"") | V9: =IF(AND($H9<>"",$I9<>"",$H9<=V$4+6,$I9>=V$4),1,"") | W9: =IF(AND($H9<>"",$I9<>"",$H9<=W$4+6,$I9>=W$4),1,"") | X9: =IF(AND($H9<>"",$I9<>"",$H9<=X$4+6,$I9>=X$4),1,"") | Y9: =IF(AND($H9<>"",$I9<>"",$H9<=Y$4+6,$I9>=Y$4),1,"") | ... AO9: =IF(AND($H9<>"",$I9<>"",$H9<=AO$4+6,$I9>=AO$4),1,"")
A10: 6.0 | B10: ERP Implementation | C10: Test | D10: System integration testing | E10: SIT report | F10: Grace Alemu | G10: 5.0 | H10: 46328 | I10: 46346 | J10: 46321 | K10: 46339 | L10: =IF(OR(H10="",I10=""),"",I10-H10+1) | M10: 0 | N10: Not Started | O10: =IF(OR(I10="",K10=""),"",I10-K10) | P10: No | Q10: SAMPLE | R10: =IF(AND($H10<>"",$I10<>"",$H10<=R$4+6,$I10>=R$4),1,"") | S10: =IF(AND($H10<>"",$I10<>"",$H10<=S$4+6,$I10>=S$4),1,"") | T10: =IF(AND($H10<>"",$I10<>"",$H10<=T$4+6,$I10>=T$4),1,"") | U10: =IF(AND($H10<>"",$I10<>"",$H10<=U$4+6,$I10>=U$4),1,"") | V10: =IF(AND($H10<>"",$I10<>"",$H10<=V$4+6,$I10>=V$4),1,"") | W10: =IF(AND($H10<>"",$I10<>"",$H10<=W$4+6,$I10>=W$4),1,"") | X10: =IF(AND($H10<>"",$I10<>"",$H10<=X$4+6,$I10>=X$4),1,"") | Y10: =IF(AND($H10<>"",$I10<>"",$H10<=Y$4+6,$I10>=Y$4),1,"") | ... AO10: =IF(AND($H10<>"",$I10<>"",$H10<=AO$4+6,$I10>=AO$4),1,"")
A11: 7.0 | B11: ERP Implementation | C11: Test | D11: User acceptance testing | E11: UAT sign-off | F11: Maria Silva | G11: 6.0 | H11: 46349 | I11: 46360 | J11: 46342 | K11: 46353 | L11: =IF(OR(H11="",I11=""),"",I11-H11+1) | M11: 0 | N11: Not Started | O11: =IF(OR(I11="",K11=""),"",I11-K11) | P11: Yes | Q11: SAMPLE | R11: =IF(AND($H11<>"",$I11<>"",$H11<=R$4+6,$I11>=R$4),1,"") | S11: =IF(AND($H11<>"",$I11<>"",$H11<=S$4+6,$I11>=S$4),1,"") | T11: =IF(AND($H11<>"",$I11<>"",$H11<=T$4+6,$I11>=T$4),1,"") | U11: =IF(AND($H11<>"",$I11<>"",$H11<=U$4+6,$I11>=U$4),1,"") | V11: =IF(AND($H11<>"",$I11<>"",$H11<=V$4+6,$I11>=V$4),1,"") | W11: =IF(AND($H11<>"",$I11<>"",$H11<=W$4+6,$I11>=W$4),1,"") | X11: =IF(AND($H11<>"",$I11<>"",$H11<=X$4+6,$I11>=X$4),1,"") | Y11: =IF(AND($H11<>"",$I11<>"",$H11<=Y$4+6,$I11>=Y$4),1,"") | ... AO11: =IF(AND($H11<>"",$I11<>"",$H11<=AO$4+6,$I11>=AO$4),1,"")
A12: 8.0 | B12: ERP Implementation | C12: Deployment | D12: Go-live preparation | E12: Cutover plan | F12: Tom Becker | G12: 7.0 | H12: 46363 | I12: 46371 | J12: 46356 | K12: 46367 | L12: =IF(OR(H12="",I12=""),"",I12-H12+1) | M12: 0 | N12: Not Started | O12: =IF(OR(I12="",K12=""),"",I12-K12) | P12: No | Q12: SAMPLE | R12: =IF(AND($H12<>"",$I12<>"",$H12<=R$4+6,$I12>=R$4),1,"") | S12: =IF(AND($H12<>"",$I12<>"",$H12<=S$4+6,$I12>=S$4),1,"") | T12: =IF(AND($H12<>"",$I12<>"",$H12<=T$4+6,$I12>=T$4),1,"") | U12: =IF(AND($H12<>"",$I12<>"",$H12<=U$4+6,$I12>=U$4),1,"") | V12: =IF(AND($H12<>"",$I12<>"",$H12<=V$4+6,$I12>=V$4),1,"") | W12: =IF(AND($H12<>"",$I12<>"",$H12<=W$4+6,$I12>=W$4),1,"") | X12: =IF(AND($H12<>"",$I12<>"",$H12<=X$4+6,$I12>=X$4),1,"") | Y12: =IF(AND($H12<>"",$I12<>"",$H12<=Y$4+6,$I12>=Y$4),1,"") | ... AO12: =IF(AND($H12<>"",$I12<>"",$H12<=AO$4+6,$I12>=AO$4),1,"")
A13: 9.0 | B13: ERP Implementation | C13: Deployment | D13: Production go-live | E13: Live system | F13: Ahmed Khan | G13: 8.0 | H13: 46372 | I13: 46374 | J13: 46370 | K13: 46374 | L13: =IF(OR(H13="",I13=""),"",I13-H13+1) | M13: 0 | N13: Not Started | O13: =IF(OR(I13="",K13=""),"",I13-K13) | P13: Yes | Q13: SAMPLE | R13: =IF(AND($H13<>"",$I13<>"",$H13<=R$4+6,$I13>=R$4),1,"") | S13: =IF(AND($H13<>"",$I13<>"",$H13<=S$4+6,$I13>=S$4),1,"") | T13: =IF(AND($H13<>"",$I13<>"",$H13<=T$4+6,$I13>=T$4),1,"") | U13: =IF(AND($H13<>"",$I13<>"",$H13<=U$4+6,$I13>=U$4),1,"") | V13: =IF(AND($H13<>"",$I13<>"",$H13<=V$4+6,$I13>=V$4),1,"") | W13: =IF(AND($H13<>"",$I13<>"",$H13<=W$4+6,$I13>=W$4),1,"") | X13: =IF(AND($H13<>"",$I13<>"",$H13<=X$4+6,$I13>=X$4),1,"") | Y13: =IF(AND($H13<>"",$I13<>"",$H13<=Y$4+6,$I13>=Y$4),1,"") | ... AO13: =IF(AND($H13<>"",$I13<>"",$H13<=AO$4+6,$I13>=AO$4),1,"")
A14: 10.0 | B14: ERP Implementation | C14: Closure | D14: Handover and documentation | E14: O&M manual | F14: Priya Raman | G14: 9.0 | H14: 46377 | I14: 46402 | J14: 46377 | K14: 46402 | L14: =IF(OR(H14="",I14=""),"",I14-H14+1) | M14: 0 | N14: Not Started | O14: =IF(OR(I14="",K14=""),"",I14-K14) | P14: Yes | Q14: SAMPLE | R14: =IF(AND($H14<>"",$I14<>"",$H14<=R$4+6,$I14>=R$4),1,"") | S14: =IF(AND($H14<>"",$I14<>"",$H14<=S$4+6,$I14>=S$4),1,"") | T14: =IF(AND($H14<>"",$I14<>"",$H14<=T$4+6,$I14>=T$4),1,"") | U14: =IF(AND($H14<>"",$I14<>"",$H14<=U$4+6,$I14>=U$4),1,"") | V14: =IF(AND($H14<>"",$I14<>"",$H14<=V$4+6,$I14>=V$4),1,"") | W14: =IF(AND($H14<>"",$I14<>"",$H14<=W$4+6,$I14>=W$4),1,"") | X14: =IF(AND($H14<>"",$I14<>"",$H14<=X$4+6,$I14>=X$4),1,"") | Y14: =IF(AND($H14<>"",$I14<>"",$H14<=Y$4+6,$I14>=Y$4),1,"") | ... AO14: =IF(AND($H14<>"",$I14<>"",$H14<=AO$4+6,$I14>=AO$4),1,"")
A15: 1.0 | B15: Network Infrastructure Upgrade | C15: Initiation | D15: Site survey and design | E15: Survey report | F15: Lisa Chen | H15: 46249 | I15: 46262 | J15: 46249 | K15: 46262 | L15: =IF(OR(H15="",I15=""),"",I15-H15+1) | M15: 1 | N15: Complete | O15: =IF(OR(I15="",K15=""),"",I15-K15) | P15: Yes | Q15: SAMPLE | R15: =IF(AND($H15<>"",$I15<>"",$H15<=R$4+6,$I15>=R$4),1,"") | S15: =IF(AND($H15<>"",$I15<>"",$H15<=S$4+6,$I15>=S$4),1,"") | T15: =IF(AND($H15<>"",$I15<>"",$H15<=T$4+6,$I15>=T$4),1,"") | U15: =IF(AND($H15<>"",$I15<>"",$H15<=U$4+6,$I15>=U$4),1,"") | V15: =IF(AND($H15<>"",$I15<>"",$H15<=V$4+6,$I15>=V$4),1,"") | W15: =IF(AND($H15<>"",$I15<>"",$H15<=W$4+6,$I15>=W$4),1,"") | X15: =IF(AND($H15<>"",$I15<>"",$H15<=X$4+6,$I15>=X$4),1,"") | Y15: =IF(AND($H15<>"",$I15<>"",$H15<=Y$4+6,$I15>=Y$4),1,"") | ... AO15: =IF(AND($H15<>"",$I15<>"",$H15<=AO$4+6,$I15>=AO$4),1,"")
A16: 2.0 | B16: Network Infrastructure Upgrade | C16: Procure | D16: Order switches and cabling | E16: Purchase order | F16: Lisa Chen | G16: 1.0 | H16: 46265 | I16: 46283 | J16: 46265 | K16: 46276 | L16: =IF(OR(H16="",I16=""),"",I16-H16+1) | M16: 1 | N16: Complete | O16: =IF(OR(I16="",K16=""),"",I16-K16) | P16: No | Q16: SAMPLE | R16: =IF(AND($H16<>"",$I16<>"",$H16<=R$4+6,$I16>=R$4),1,"") | S16: =IF(AND($H16<>"",$I16<>"",$H16<=S$4+6,$I16>=S$4),1,"") | T16: =IF(AND($H16<>"",$I16<>"",$H16<=T$4+6,$I16>=T$4),1,"") | U16: =IF(AND($H16<>"",$I16<>"",$H16<=U$4+6,$I16>=U$4),1,"") | V16: =IF(AND($H16<>"",$I16<>"",$H16<=V$4+6,$I16>=V$4),1,"") | W16: =IF(AND($H16<>"",$I16<>"",$H16<=W$4+6,$I16>=W$4),1,"") | X16: =IF(AND($H16<>"",$I16<>"",$H16<=X$4+6,$I16>=X$4),1,"") | Y16: =IF(AND($H16<>"",$I16<>"",$H16<=Y$4+6,$I16>=Y$4),1,"") | ... AO16: =IF(AND($H16<>"",$I16<>"",$H16<=AO$4+6,$I16>=AO$4),1,"")
A17: 3.0 | B17: Network Infrastructure Upgrade | C17: Install | D17: Cabinet and switch installation | E17: Installed links | F17: Tom Becker | G17: 2.0 | H17: 46286 | I17: 46319 | J17: 46286 | K17: 46312 | L17: =IF(OR(H17="",I17=""),"",I17-H17+1) | M17: 0.55 | N17: In Progress | O17: =IF(OR(I17="",K17=""),"",I17-K17) | P17: No | Q17: SAMPLE | R17: =IF(AND($H17<>"",$I17<>"",$H17<=R$4+6,$I17>=R$4),1,"") | S17: =IF(AND($H17<>"",$I17<>"",$H17<=S$4+6,$I17>=S$4),1,"") | T17: =IF(AND($H17<>"",$I17<>"",$H17<=T$4+6,$I17>=T$4),1,"") | U17: =IF(AND($H17<>"",$I17<>"",$H17<=U$4+6,$I17>=U$4),1,"") | V17: =IF(AND($H17<>"",$I17<>"",$H17<=V$4+6,$I17>=V$4),1,"") | W17: =IF(AND($H17<>"",$I17<>"",$H17<=W$4+6,$I17>=W$4),1,"") | X17: =IF(AND($H17<>"",$I17<>"",$H17<=X$4+6,$I17>=X$4),1,"") | Y17: =IF(AND($H17<>"",$I17<>"",$H17<=Y$4+6,$I17>=Y$4),1,"") | ... AO17: =IF(AND($H17<>"",$I17<>"",$H17<=AO$4+6,$I17>=AO$4),1,"")
A18: 4.0 | B18: Network Infrastructure Upgrade | C18: Test | D18: Network acceptance testing | E18: Test report | F18: Grace Alemu | G18: 3.0 | H18: 46321 | I18: 46339 | J18: 46314 | K18: 46332 | L18: =IF(OR(H18="",I18=""),"",I18-H18+1) | M18: 0 | N18: Not Started | O18: =IF(OR(I18="",K18=""),"",I18-K18) | P18: Yes | Q18: SAMPLE | R18: =IF(AND($H18<>"",$I18<>"",$H18<=R$4+6,$I18>=R$4),1,"") | S18: =IF(AND($H18<>"",$I18<>"",$H18<=S$4+6,$I18>=S$4),1,"") | T18: =IF(AND($H18<>"",$I18<>"",$H18<=T$4+6,$I18>=T$4),1,"") | U18: =IF(AND($H18<>"",$I18<>"",$H18<=U$4+6,$I18>=U$4),1,"") | V18: =IF(AND($H18<>"",$I18<>"",$H18<=V$4+6,$I18>=V$4),1,"") | W18: =IF(AND($H18<>"",$I18<>"",$H18<=W$4+6,$I18>=W$4),1,"") | X18: =IF(AND($H18<>"",$I18<>"",$H18<=X$4+6,$I18>=X$4),1,"") | Y18: =IF(AND($H18<>"",$I18<>"",$H18<=Y$4+6,$I18>=Y$4),1,"") | ... AO18: =IF(AND($H18<>"",$I18<>"",$H18<=AO$4+6,$I18>=AO$4),1,"")
A19: 5.0 | B19: Network Infrastructure Upgrade | C19: Deploy | D19: Cutover and handover | E19: Cutover note | F19: Lisa Chen | G19: 4.0 | H19: 46342 | I19: 46351 | J19: 46335 | K19: 46351 | L19: =IF(OR(H19="",I19=""),"",I19-H19+1) | M19: 0 | N19: Not Started | O19: =IF(OR(I19="",K19=""),"",I19-K19) | P19: Yes | Q19: SAMPLE | R19: =IF(AND($H19<>"",$I19<>"",$H19<=R$4+6,$I19>=R$4),1,"") | S19: =IF(AND($H19<>"",$I19<>"",$H19<=S$4+6,$I19>=S$4),1,"") | T19: =IF(AND($H19<>"",$I19<>"",$H19<=T$4+6,$I19>=T$4),1,"") | U19: =IF(AND($H19<>"",$I19<>"",$H19<=U$4+6,$I19>=U$4),1,"") | V19: =IF(AND($H19<>"",$I19<>"",$H19<=V$4+6,$I19>=V$4),1,"") | W19: =IF(AND($H19<>"",$I19<>"",$H19<=W$4+6,$I19>=W$4),1,"") | X19: =IF(AND($H19<>"",$I19<>"",$H19<=X$4+6,$I19>=X$4),1,"") | Y19: =IF(AND($H19<>"",$I19<>"",$H19<=Y$4+6,$I19>=Y$4),1,"") | ... AO19: =IF(AND($H19<>"",$I19<>"",$H19<=AO$4+6,$I19>=AO$4),1,"")
L20: =IF(OR(H20="",I20=""),"",I20-H20+1) | O20: =IF(OR(I20="",K20=""),"",I20-K20) | R20: =IF(AND($H20<>"",$I20<>"",$H20<=R$4+6,$I20>=R$4),1,"") | S20: =IF(AND($H20<>"",$I20<>"",$H20<=S$4+6,$I20>=S$4),1,"") | T20: =IF(AND($H20<>"",$I20<>"",$H20<=T$4+6,$I20>=T$4),1,"") | U20: =IF(AND($H20<>"",$I20<>"",$H20<=U$4+6,$I20>=U$4),1,"") | V20: =IF(AND($H20<>"",$I20<>"",$H20<=V$4+6,$I20>=V$4),1,"") | W20: =IF(AND($H20<>"",$I20<>"",$H20<=W$4+6,$I20>=W$4),1,"") | X20: =IF(AND($H20<>"",$I20<>"",$H20<=X$4+6,$I20>=X$4),1,"") | Y20: =IF(AND($H20<>"",$I20<>"",$H20<=Y$4+6,$I20>=Y$4),1,"") | ... AO20: =IF(AND($H20<>"",$I20<>"",$H20<=AO$4+6,$I20>=AO$4),1,"")
L21: =IF(OR(H21="",I21=""),"",I21-H21+1) | O21: =IF(OR(I21="",K21=""),"",I21-K21) | R21: =IF(AND($H21<>"",$I21<>"",$H21<=R$4+6,$I21>=R$4),1,"") | S21: =IF(AND($H21<>"",$I21<>"",$H21<=S$4+6,$I21>=S$4),1,"") | T21: =IF(AND($H21<>"",$I21<>"",$H21<=T$4+6,$I21>=T$4),1,"") | U21: =IF(AND($H21<>"",$I21<>"",$H21<=U$4+6,$I21>=U$4),1,"") | V21: =IF(AND($H21<>"",$I21<>"",$H21<=V$4+6,$I21>=V$4),1,"") | W21: =IF(AND($H21<>"",$I21<>"",$H21<=W$4+6,$I21>=W$4),1,"") | X21: =IF(AND($H21<>"",$I21<>"",$H21<=X$4+6,$I21>=X$4),1,"") | Y21: =IF(AND($H21<>"",$I21<>"",$H21<=Y$4+6,$I21>=Y$4),1,"") | ... AO21: =IF(AND($H21<>"",$I21<>"",$H21<=AO$4+6,$I21>=AO$4),1,"")
L22: =IF(OR(H22="",I22=""),"",I22-H22+1) | O22: =IF(OR(I22="",K22=""),"",I22-K22) | R22: =IF(AND($H22<>"",$I22<>"",$H22<=R$4+6,$I22>=R$4),1,"") | S22: =IF(AND($H22<>"",$I22<>"",$H22<=S$4+6,$I22>=S$4),1,"") | T22: =IF(AND($H22<>"",$I22<>"",$H22<=T$4+6,$I22>=T$4),1,"") | U22: =IF(AND($H22<>"",$I22<>"",$H22<=U$4+6,$I22>=U$4),1,"") | V22: =IF(AND($H22<>"",$I22<>"",$H22<=V$4+6,$I22>=V$4),1,"") | W22: =IF(AND($H22<>"",$I22<>"",$H22<=W$4+6,$I22>=W$4),1,"") | X22: =IF(AND($H22<>"",$I22<>"",$H22<=X$4+6,$I22>=X$4),1,"") | Y22: =IF(AND($H22<>"",$I22<>"",$H22<=Y$4+6,$I22>=Y$4),1,"") | ... AO22: =IF(AND($H22<>"",$I22<>"",$H22<=AO$4+6,$I22>=AO$4),1,"")
L23: =IF(OR(H23="",I23=""),"",I23-H23+1) | O23: =IF(OR(I23="",K23=""),"",I23-K23) | R23: =IF(AND($H23<>"",$I23<>"",$H23<=R$4+6,$I23>=R$4),1,"") | S23: =IF(AND($H23<>"",$I23<>"",$H23<=S$4+6,$I23>=S$4),1,"") | T23: =IF(AND($H23<>"",$I23<>"",$H23<=T$4+6,$I23>=T$4),1,"") | U23: =IF(AND($H23<>"",$I23<>"",$H23<=U$4+6,$I23>=U$4),1,"") | V23: =IF(AND($H23<>"",$I23<>"",$H23<=V$4+6,$I23>=V$4),1,"") | W23: =IF(AND($H23<>"",$I23<>"",$H23<=W$4+6,$I23>=W$4),1,"") | X23: =IF(AND($H23<>"",$I23<>"",$H23<=X$4+6,$I23>=X$4),1,"") | Y23: =IF(AND($H23<>"",$I23<>"",$H23<=Y$4+6,$I23>=Y$4),1,"") | ... AO23: =IF(AND($H23<>"",$I23<>"",$H23<=AO$4+6,$I23>=AO$4),1,"")
L24: =IF(OR(H24="",I24=""),"",I24-H24+1) | O24: =IF(OR(I24="",K24=""),"",I24-K24) | R24: =IF(AND($H24<>"",$I24<>"",$H24<=R$4+6,$I24>=R$4),1,"") | S24: =IF(AND($H24<>"",$I24<>"",$H24<=S$4+6,$I24>=S$4),1,"") | T24: =IF(AND($H24<>"",$I24<>"",$H24<=T$4+6,$I24>=T$4),1,"") | U24: =IF(AND($H24<>"",$I24<>"",$H24<=U$4+6,$I24>=U$4),1,"") | V24: =IF(AND($H24<>"",$I24<>"",$H24<=V$4+6,$I24>=V$4),1,"") | W24: =IF(AND($H24<>"",$I24<>"",$H24<=W$4+6,$I24>=W$4),1,"") | X24: =IF(AND($H24<>"",$I24<>"",$H24<=X$4+6,$I24>=X$4),1,"") | Y24: =IF(AND($H24<>"",$I24<>"",$H24<=Y$4+6,$I24>=Y$4),1,"") | ... AO24: =IF(AND($H24<>"",$I24<>"",$H24<=AO$4+6,$I24>=AO$4),1,"")
L25: =IF(OR(H25="",I25=""),"",I25-H25+1) | O25: =IF(OR(I25="",K25=""),"",I25-K25) | R25: =IF(AND($H25<>"",$I25<>"",$H25<=R$4+6,$I25>=R$4),1,"") | S25: =IF(AND($H25<>"",$I25<>"",$H25<=S$4+6,$I25>=S$4),1,"") | T25: =IF(AND($H25<>"",$I25<>"",$H25<=T$4+6,$I25>=T$4),1,"") | U25: =IF(AND($H25<>"",$I25<>"",$H25<=U$4+6,$I25>=U$4),1,"") | V25: =IF(AND($H25<>"",$I25<>"",$H25<=V$4+6,$I25>=V$4),1,"") | W25: =IF(AND($H25<>"",$I25<>"",$H25<=W$4+6,$I25>=W$4),1,"") | X25: =IF(AND($H25<>"",$I25<>"",$H25<=X$4+6,$I25>=X$4),1,"") | Y25: =IF(AND($H25<>"",$I25<>"",$H25<=Y$4+6,$I25>=Y$4),1,"") | ... AO25: =IF(AND($H25<>"",$I25<>"",$H25<=AO$4+6,$I25>=AO$4),1,"")
L26: =IF(OR(H26="",I26=""),"",I26-H26+1) | O26: =IF(OR(I26="",K26=""),"",I26-K26) | R26: =IF(AND($H26<>"",$I26<>"",$H26<=R$4+6,$I26>=R$4),1,"") | S26: =IF(AND($H26<>"",$I26<>"",$H26<=S$4+6,$I26>=S$4),1,"") | T26: =IF(AND($H26<>"",$I26<>"",$H26<=T$4+6,$I26>=T$4),1,"") | U26: =IF(AND($H26<>"",$I26<>"",$H26<=U$4+6,$I26>=U$4),1,"") | V26: =IF(AND($H26<>"",$I26<>"",$H26<=V$4+6,$I26>=V$4),1,"") | W26: =IF(AND($H26<>"",$I26<>"",$H26<=W$4+6,$I26>=W$4),1,"") | X26: =IF(AND($H26<>"",$I26<>"",$H26<=X$4+6,$I26>=X$4),1,"") | Y26: =IF(AND($H26<>"",$I26<>"",$H26<=Y$4+6,$I26>=Y$4),1,"") | ... AO26: =IF(AND($H26<>"",$I26<>"",$H26<=AO$4+6,$I26>=AO$4),1,"")
L27: =IF(OR(H27="",I27=""),"",I27-H27+1) | O27: =IF(OR(I27="",K27=""),"",I27-K27) | R27: =IF(AND($H27<>"",$I27<>"",$H27<=R$4+6,$I27>=R$4),1,"") | S27: =IF(AND($H27<>"",$I27<>"",$H27<=S$4+6,$I27>=S$4),1,"") | T27: =IF(AND($H27<>"",$I27<>"",$H27<=T$4+6,$I27>=T$4),1,"") | U27: =IF(AND($H27<>"",$I27<>"",$H27<=U$4+6,$I27>=U$4),1,"") | V27: =IF(AND($H27<>"",$I27<>"",$H27<=V$4+6,$I27>=V$4),1,"") | W27: =IF(AND($H27<>"",$I27<>"",$H27<=W$4+6,$I27>=W$4),1,"") | X27: =IF(AND($H27<>"",$I27<>"",$H27<=X$4+6,$I27>=X$4),1,"") | Y27: =IF(AND($H27<>"",$I27<>"",$H27<=Y$4+6,$I27>=Y$4),1,"") | ... AO27: =IF(AND($H27<>"",$I27<>"",$H27<=AO$4+6,$I27>=AO$4),1,"")
L28: =IF(OR(H28="",I28=""),"",I28-H28+1) | O28: =IF(OR(I28="",K28=""),"",I28-K28) | R28: =IF(AND($H28<>"",$I28<>"",$H28<=R$4+6,$I28>=R$4),1,"") | S28: =IF(AND($H28<>"",$I28<>"",$H28<=S$4+6,$I28>=S$4),1,"") | T28: =IF(AND($H28<>"",$I28<>"",$H28<=T$4+6,$I28>=T$4),1,"") | U28: =IF(AND($H28<>"",$I28<>"",$H28<=U$4+6,$I28>=U$4),1,"") | V28: =IF(AND($H28<>"",$I28<>"",$H28<=V$4+6,$I28>=V$4),1,"") | W28: =IF(AND($H28<>"",$I28<>"",$H28<=W$4+6,$I28>=W$4),1,"") | X28: =IF(AND($H28<>"",$I28<>"",$H28<=X$4+6,$I28>=X$4),1,"") | Y28: =IF(AND($H28<>"",$I28<>"",$H28<=Y$4+6,$I28>=Y$4),1,"") | ... AO28: =IF(AND($H28<>"",$I28<>"",$H28<=AO$4+6,$I28>=AO$4),1,"")
L29: =IF(OR(H29="",I29=""),"",I29-H29+1) | O29: =IF(OR(I29="",K29=""),"",I29-K29) | R29: =IF(AND($H29<>"",$I29<>"",$H29<=R$4+6,$I29>=R$4),1,"") | S29: =IF(AND($H29<>"",$I29<>"",$H29<=S$4+6,$I29>=S$4),1,"") | T29: =IF(AND($H29<>"",$I29<>"",$H29<=T$4+6,$I29>=T$4),1,"") | U29: =IF(AND($H29<>"",$I29<>"",$H29<=U$4+6,$I29>=U$4),1,"") | V29: =IF(AND($H29<>"",$I29<>"",$H29<=V$4+6,$I29>=V$4),1,"") | W29: =IF(AND($H29<>"",$I29<>"",$H29<=W$4+6,$I29>=W$4),1,"") | X29: =IF(AND($H29<>"",$I29<>"",$H29<=X$4+6,$I29>=X$4),1,"") | Y29: =IF(AND($H29<>"",$I29<>"",$H29<=Y$4+6,$I29>=Y$4),1,"") | ... AO29: =IF(AND($H29<>"",$I29<>"",$H29<=AO$4+6,$I29>=AO$4),1,"")
L30: =IF(OR(H30="",I30=""),"",I30-H30+1) | O30: =IF(OR(I30="",K30=""),"",I30-K30) | R30: =IF(AND($H30<>"",$I30<>"",$H30<=R$4+6,$I30>=R$4),1,"") | S30: =IF(AND($H30<>"",$I30<>"",$H30<=S$4+6,$I30>=S$4),1,"") | T30: =IF(AND($H30<>"",$I30<>"",$H30<=T$4+6,$I30>=T$4),1,"") | U30: =IF(AND($H30<>"",$I30<>"",$H30<=U$4+6,$I30>=U$4),1,"") | V30: =IF(AND($H30<>"",$I30<>"",$H30<=V$4+6,$I30>=V$4),1,"") | W30: =IF(AND($H30<>"",$I30<>"",$H30<=W$4+6,$I30>=W$4),1,"") | X30: =IF(AND($H30<>"",$I30<>"",$H30<=X$4+6,$I30>=X$4),1,"") | Y30: =IF(AND($H30<>"",$I30<>"",$H30<=Y$4+6,$I30>=Y$4),1,"") | ... AO30: =IF(AND($H30<>"",$I30<>"",$H30<=AO$4+6,$I30>=AO$4),1,"")
L31: =IF(OR(H31="",I31=""),"",I31-H31+1) | O31: =IF(OR(I31="",K31=""),"",I31-K31) | R31: =IF(AND($H31<>"",$I31<>"",$H31<=R$4+6,$I31>=R$4),1,"") | S31: =IF(AND($H31<>"",$I31<>"",$H31<=S$4+6,$I31>=S$4),1,"") | T31: =IF(AND($H31<>"",$I31<>"",$H31<=T$4+6,$I31>=T$4),1,"") | U31: =IF(AND($H31<>"",$I31<>"",$H31<=U$4+6,$I31>=U$4),1,"") | V31: =IF(AND($H31<>"",$I31<>"",$H31<=V$4+6,$I31>=V$4),1,"") | W31: =IF(AND($H31<>"",$I31<>"",$H31<=W$4+6,$I31>=W$4),1,"") | X31: =IF(AND($H31<>"",$I31<>"",$H31<=X$4+6,$I31>=X$4),1,"") | Y31: =IF(AND($H31<>"",$I31<>"",$H31<=Y$4+6,$I31>=Y$4),1,"") | ... AO31: =IF(AND($H31<>"",$I31<>"",$H31<=AO$4+6,$I31>=AO$4),1,"")
... L34: =IF(OR(H34="",I34=""),"",I34-H34+1) | O34: =IF(OR(I34="",K34=""),"",I34-K34) | R34: =IF(AND($H34<>"",$I34<>"",$H34<=R$4+6,$I34>=R$4),1,"") | S34: =IF(AND($H34<>"",$I34<>"",$H34<=S$4+6,$I34>=S$4),1,"") | T34: =IF(AND($H34<>"",$I34<>"",$H34<=T$4+6,$I34>=T$4),1,"") | U34: =IF(AND($H34<>"",$I34<>"",$H34<=U$4+6,$I34>=U$4),1,"") | V34: =IF(AND($H34<>"",$I34<>"",$H34<=V$4+6,$I34>=V$4),1,"") | W34: =IF(AND($H34<>"",$I34<>"",$H34<=W$4+6,$I34>=W$4),1,"") | X34: =IF(AND($H34<>"",$I34<>"",$H34<=X$4+6,$I34>=X$4),1,"") | Y34: =IF(AND($H34<>"",$I34<>"",$H34<=Y$4+6,$I34>=Y$4),1,"") | ... AO34: =IF(AND($H34<>"",$I34<>"",$H34<=AO$4+6,$I34>=AO$4),1,"")
A36: LEGEND: dark blue = complete | blue = in progress | red = blocked | grey = not started | red date column = the current week

Sheet 05_MILESTONES
A1: MILESTONE TRACKER
A2: Every milestone with baseline, forecast, days remaining and automatic RAG. Feeds the dashboard 'next milestones', 'upcoming milestones' chart and portfolio next-milestone column.
A3: SAMPLE DATA - every sample record is marked SAMPLE in the Notes column. Delete or overwrite them freely: all formulas, KPIs, charts and drop-downs keep working.
A4: Milestone ID | B4: Project | C4: Milestone | D4: Owner | E4: Baseline Date | F4: Forecast Date | G4: Actual Date | H4: Status | I4: Days Remaining | J4: Variance | K4: RAG | L4: Notes | M4: Key | N4: ProjKey
A5: M-001 | B5: ERP Implementation | C5: Charter approved | D5: Ahmed Khan | E5: 46213 | F5: 46213 | G5: 46213 | H5: Complete | I5: =IF(OR(A5="",H5="Complete"),"",IF(F5="","",F5-TODAY())) | J5: =IF(OR(E5="",F5=""),"",F5-E5) | K5: =IF(A5="","",IF(H5="Complete","Green",IF(F5="","",IF(F5<TODAY(),"Red",IF(F5-TODAY()<=7,"Yellow","Green"))))) | L5: SAMPLE | M5: =IF(OR(A5="",F5="",H5="Complete"),"",IF(F5>=TODAY(),F5+ROW()/100000,"")) | N5: =IF(M5="","",B5&"|"&(COUNTIFS(B$5:B$34,B5,M$5:M$34,"<"&M5)+1))
A6: M-002 | B6: ERP Implementation | C6: Requirements sign-off | D6: Priya Raman | E6: 46241 | F6: 46241 | G6: 46241 | H6: Complete | I6: =IF(OR(A6="",H6="Complete"),"",IF(F6="","",F6-TODAY())) | J6: =IF(OR(E6="",F6=""),"",F6-E6) | K6: =IF(A6="","",IF(H6="Complete","Green",IF(F6="","",IF(F6<TODAY(),"Red",IF(F6-TODAY()<=7,"Yellow","Green"))))) | L6: SAMPLE | M6: =IF(OR(A6="",F6="",H6="Complete"),"",IF(F6>=TODAY(),F6+ROW()/100000,"")) | N6: =IF(M6="","",B6&"|"&(COUNTIFS(B$5:B$34,B6,M$5:M$34,"<"&M6)+1))
A7: M-003 | B7: ERP Implementation | C7: Design sign-off | D7: Tom Becker | E7: 46262 | F7: 46262 | G7: 46265 | H7: Complete | I7: =IF(OR(A7="",H7="Complete"),"",IF(F7="","",F7-TODAY())) | J7: =IF(OR(E7="",F7=""),"",F7-E7) | K7: =IF(A7="","",IF(H7="Complete","Green",IF(F7="","",IF(F7<TODAY(),"Red",IF(F7-TODAY()<=7,"Yellow","Green"))))) | L7: SAMPLE | M7: =IF(OR(A7="",F7="",H7="Complete"),"",IF(F7>=TODAY(),F7+ROW()/100000,"")) | N7: =IF(M7="","",B7&"|"&(COUNTIFS(B$5:B$34,B7,M$5:M$34,"<"&M7)+1))
A8: M-004 | B8: ERP Implementation | C8: Core configuration complete | D8: Ahmed Khan | E8: 46297 | F8: 46304 | H8: In Progress | I8: =IF(OR(A8="",H8="Complete"),"",IF(F8="","",F8-TODAY())) | J8: =IF(OR(E8="",F8=""),"",F8-E8) | K8: =IF(A8="","",IF(H8="Complete","Green",IF(F8="","",IF(F8<TODAY(),"Red",IF(F8-TODAY()<=7,"Yellow","Green"))))) | L8: SAMPLE - due in days | M8: =IF(OR(A8="",F8="",H8="Complete"),"",IF(F8>=TODAY(),F8+ROW()/100000,"")) | N8: =IF(M8="","",B8&"|"&(COUNTIFS(B$5:B$34,B8,M$5:M$34,"<"&M8)+1))
A9: M-005 | B9: ERP Implementation | C9: Data migration complete | D9: David Okoro | E9: 46318 | F9: 46325 | H9: In Progress | I9: =IF(OR(A9="",H9="Complete"),"",IF(F9="","",F9-TODAY())) | J9: =IF(OR(E9="",F9=""),"",F9-E9) | K9: =IF(A9="","",IF(H9="Complete","Green",IF(F9="","",IF(F9<TODAY(),"Red",IF(F9-TODAY()<=7,"Yellow","Green"))))) | L9: SAMPLE | M9: =IF(OR(A9="",F9="",H9="Complete"),"",IF(F9>=TODAY(),F9+ROW()/100000,"")) | N9: =IF(M9="","",B9&"|"&(COUNTIFS(B$5:B$34,B9,M$5:M$34,"<"&M9)+1))
A10: M-006 | B10: ERP Implementation | C10: System integration testing complete | D10: Grace Alemu | E10: 46339 | F10: 46346 | H10: Not Started | I10: =IF(OR(A10="",H10="Complete"),"",IF(F10="","",F10-TODAY())) | J10: =IF(OR(E10="",F10=""),"",F10-E10) | K10: =IF(A10="","",IF(H10="Complete","Green",IF(F10="","",IF(F10<TODAY(),"Red",IF(F10-TODAY()<=7,"Yellow","Green"))))) | L10: SAMPLE | M10: =IF(OR(A10="",F10="",H10="Complete"),"",IF(F10>=TODAY(),F10+ROW()/100000,"")) | N10: =IF(M10="","",B10&"|"&(COUNTIFS(B$5:B$34,B10,M$5:M$34,"<"&M10)+1))
A11: M-007 | B11: ERP Implementation | C11: UAT sign-off | D11: Maria Silva | E11: 46353 | F11: 46360 | H11: Not Started | I11: =IF(OR(A11="",H11="Complete"),"",IF(F11="","",F11-TODAY())) | J11: =IF(OR(E11="",F11=""),"",F11-E11) | K11: =IF(A11="","",IF(H11="Complete","Green",IF(F11="","",IF(F11<TODAY(),"Red",IF(F11-TODAY()<=7,"Yellow","Green"))))) | L11: SAMPLE | M11: =IF(OR(A11="",F11="",H11="Complete"),"",IF(F11>=TODAY(),F11+ROW()/100000,"")) | N11: =IF(M11="","",B11&"|"&(COUNTIFS(B$5:B$34,B11,M$5:M$34,"<"&M11)+1))
A12: M-008 | B12: ERP Implementation | C12: Production go-live | D12: Ahmed Khan | E12: 46374 | F12: 46402 | H12: Not Started | I12: =IF(OR(A12="",H12="Complete"),"",IF(F12="","",F12-TODAY())) | J12: =IF(OR(E12="",F12=""),"",F12-E12) | K12: =IF(A12="","",IF(H12="Complete","Green",IF(F12="","",IF(F12<TODAY(),"Red",IF(F12-TODAY()<=7,"Yellow","Green"))))) | L12: SAMPLE | M12: =IF(OR(A12="",F12="",H12="Complete"),"",IF(F12>=TODAY(),F12+ROW()/100000,"")) | N12: =IF(M12="","",B12&"|"&(COUNTIFS(B$5:B$34,B12,M$5:M$34,"<"&M12)+1))
A13: M-009 | B13: Network Infrastructure Upgrade | C13: Switch installation complete | D13: Tom Becker | E13: 46311 | F13: 46311 | H13: In Progress | I13: =IF(OR(A13="",H13="Complete"),"",IF(F13="","",F13-TODAY())) | J13: =IF(OR(E13="",F13=""),"",F13-E13) | K13: =IF(A13="","",IF(H13="Complete","Green",IF(F13="","",IF(F13<TODAY(),"Red",IF(F13-TODAY()<=7,"Yellow","Green"))))) | L13: SAMPLE | M13: =IF(OR(A13="",F13="",H13="Complete"),"",IF(F13>=TODAY(),F13+ROW()/100000,"")) | N13: =IF(M13="","",B13&"|"&(COUNTIFS(B$5:B$34,B13,M$5:M$34,"<"&M13)+1))
A14: M-010 | B14: Network Infrastructure Upgrade | C14: Network go-live | D14: Lisa Chen | E14: 46351 | F14: 46351 | H14: Not Started | I14: =IF(OR(A14="",H14="Complete"),"",IF(F14="","",F14-TODAY())) | J14: =IF(OR(E14="",F14=""),"",F14-E14) | K14: =IF(A14="","",IF(H14="Complete","Green",IF(F14="","",IF(F14<TODAY(),"Red",IF(F14-TODAY()<=7,"Yellow","Green"))))) | L14: SAMPLE | M14: =IF(OR(A14="",F14="",H14="Complete"),"",IF(F14>=TODAY(),F14+ROW()/100000,"")) | N14: =IF(M14="","",B14&"|"&(COUNTIFS(B$5:B$34,B14,M$5:M$34,"<"&M14)+1))
A15: M-011 | B15: Network Infrastructure Upgrade | C15: Cabling inspection sign-off | D15: Lisa Chen | E15: 46307 | F15: 46307 | H15: In Progress | I15: =IF(OR(A15="",H15="Complete"),"",IF(F15="","",F15-TODAY())) | J15: =IF(OR(E15="",F15=""),"",F15-E15) | K15: =IF(A15="","",IF(H15="Complete","Green",IF(F15="","",IF(F15<TODAY(),"Red",IF(F15-TODAY()<=7,"Yellow","Green"))))) | L15: SAMPLE | M15: =IF(OR(A15="",F15="",H15="Complete"),"",IF(F15>=TODAY(),F15+ROW()/100000,"")) | N15: =IF(M15="","",B15&"|"&(COUNTIFS(B$5:B$34,B15,M$5:M$34,"<"&M15)+1))
A16: M-012 | B16: HR Management System | C16: Vendor shortlist agreed | D16: David Okoro | E16: 46300 | F16: 46300 | H16: Delayed | I16: =IF(OR(A16="",H16="Complete"),"",IF(F16="","",F16-TODAY())) | J16: =IF(OR(E16="",F16=""),"",F16-E16) | K16: =IF(A16="","",IF(H16="Complete","Green",IF(F16="","",IF(F16<TODAY(),"Red",IF(F16-TODAY()<=7,"Yellow","Green"))))) | L16: SAMPLE - overdue | M16: =IF(OR(A16="",F16="",H16="Complete"),"",IF(F16>=TODAY(),F16+ROW()/100000,"")) | N16: =IF(M16="","",B16&"|"&(COUNTIFS(B$5:B$34,B16,M$5:M$34,"<"&M16)+1))
A17: M-013 | B17: HR Management System | C17: Contract signed | D17: David Okoro | E17: 46332 | F17: 46346 | H17: Not Started | I17: =IF(OR(A17="",H17="Complete"),"",IF(F17="","",F17-TODAY())) | J17: =IF(OR(E17="",F17=""),"",F17-E17) | K17: =IF(A17="","",IF(H17="Complete","Green",IF(F17="","",IF(F17<TODAY(),"Red",IF(F17-TODAY()<=7,"Yellow","Green"))))) | L17: SAMPLE | M17: =IF(OR(A17="",F17="",H17="Complete"),"",IF(F17>=TODAY(),F17+ROW()/100000,"")) | N17: =IF(M17="","",B17&"|"&(COUNTIFS(B$5:B$34,B17,M$5:M$34,"<"&M17)+1))
A18: M-014 | B18: Website Development | C18: Design approval | D18: Maria Silva | E18: 46309 | F18: 46316 | H18: In Progress | I18: =IF(OR(A18="",H18="Complete"),"",IF(F18="","",F18-TODAY())) | J18: =IF(OR(E18="",F18=""),"",F18-E18) | K18: =IF(A18="","",IF(H18="Complete","Green",IF(F18="","",IF(F18<TODAY(),"Red",IF(F18-TODAY()<=7,"Yellow","Green"))))) | L18: SAMPLE | M18: =IF(OR(A18="",F18="",H18="Complete"),"",IF(F18>=TODAY(),F18+ROW()/100000,"")) | N18: =IF(M18="","",B18&"|"&(COUNTIFS(B$5:B$34,B18,M$5:M$34,"<"&M18)+1))
A19: M-015 | B19: Website Development | C19: Content ready for load | D19: Maria Silva | E19: 46314 | F19: 46314 | H19: In Progress | I19: =IF(OR(A19="",H19="Complete"),"",IF(F19="","",F19-TODAY())) | J19: =IF(OR(E19="",F19=""),"",F19-E19) | K19: =IF(A19="","",IF(H19="Complete","Green",IF(F19="","",IF(F19<TODAY(),"Red",IF(F19-TODAY()<=7,"Yellow","Green"))))) | L19: SAMPLE | M19: =IF(OR(A19="",F19="",H19="Complete"),"",IF(F19>=TODAY(),F19+ROW()/100000,"")) | N19: =IF(M19="","",B19&"|"&(COUNTIFS(B$5:B$34,B19,M$5:M$34,"<"&M19)+1))
A20: M-016 | B20: Office Security Upgrade | C20: Security assessment sign-off | D20: Tom Becker | E20: 46300 | F20: 46309 | H20: In Progress | I20: =IF(OR(A20="",H20="Complete"),"",IF(F20="","",F20-TODAY())) | J20: =IF(OR(E20="",F20=""),"",F20-E20) | K20: =IF(A20="","",IF(H20="Complete","Green",IF(F20="","",IF(F20<TODAY(),"Red",IF(F20-TODAY()<=7,"Yellow","Green"))))) | L20: SAMPLE | M20: =IF(OR(A20="",F20="",H20="Complete"),"",IF(F20>=TODAY(),F20+ROW()/100000,"")) | N20: =IF(M20="","",B20&"|"&(COUNTIFS(B$5:B$34,B20,M$5:M$34,"<"&M20)+1))
A21: M-017 | B21: Payroll Reporting Portal | C21: Project closure approved | D21: Priya Raman | E21: 46295 | F21: 46295 | G21: 46293 | H21: Complete | I21: =IF(OR(A21="",H21="Complete"),"",IF(F21="","",F21-TODAY())) | J21: =IF(OR(E21="",F21=""),"",F21-E21) | K21: =IF(A21="","",IF(H21="Complete","Green",IF(F21="","",IF(F21<TODAY(),"Red",IF(F21-TODAY()<=7,"Yellow","Green"))))) | L21: SAMPLE | M21: =IF(OR(A21="",F21="",H21="Complete"),"",IF(F21>=TODAY(),F21+ROW()/100000,"")) | N21: =IF(M21="","",B21&"|"&(COUNTIFS(B$5:B$34,B21,M$5:M$34,"<"&M21)+1))
A22: M-018 | B22: Network Infrastructure Upgrade | C22: User acceptance complete | D22: Grace Alemu | E22: 46328 | F22: 46328 | H22: Not Started | I22: =IF(OR(A22="",H22="Complete"),"",IF(F22="","",F22-TODAY())) | J22: =IF(OR(E22="",F22=""),"",F22-E22) | K22: =IF(A22="","",IF(H22="Complete","Green",IF(F22="","",IF(F22<TODAY(),"Red",IF(F22-TODAY()<=7,"Yellow","Green"))))) | L22: SAMPLE | M22: =IF(OR(A22="",F22="",H22="Complete"),"",IF(F22>=TODAY(),F22+ROW()/100000,"")) | N22: =IF(M22="","",B22&"|"&(COUNTIFS(B$5:B$34,B22,M$5:M$34,"<"&M22)+1))
I23: =IF(OR(A23="",H23="Complete"),"",IF(F23="","",F23-TODAY())) | J23: =IF(OR(E23="",F23=""),"",F23-E23) | K23: =IF(A23="","",IF(H23="Complete","Green",IF(F23="","",IF(F23<TODAY(),"Red",IF(F23-TODAY()<=7,"Yellow","Green"))))) | M23: =IF(OR(A23="",F23="",H23="Complete"),"",IF(F23>=TODAY(),F23+ROW()/100000,"")) | N23: =IF(M23="","",B23&"|"&(COUNTIFS(B$5:B$34,B23,M$5:M$34,"<"&M23)+1))
I24: =IF(OR(A24="",H24="Complete"),"",IF(F24="","",F24-TODAY())) | J24: =IF(OR(E24="",F24=""),"",F24-E24) | K24: =IF(A24="","",IF(H24="Complete","Green",IF(F24="","",IF(F24<TODAY(),"Red",IF(F24-TODAY()<=7,"Yellow","Green"))))) | M24: =IF(OR(A24="",F24="",H24="Complete"),"",IF(F24>=TODAY(),F24+ROW()/100000,"")) | N24: =IF(M24="","",B24&"|"&(COUNTIFS(B$5:B$34,B24,M$5:M$34,"<"&M24)+1))
I25: =IF(OR(A25="",H25="Complete"),"",IF(F25="","",F25-TODAY())) | J25: =IF(OR(E25="",F25=""),"",F25-E25) | K25: =IF(A25="","",IF(H25="Complete","Green",IF(F25="","",IF(F25<TODAY(),"Red",IF(F25-TODAY()<=7,"Yellow","Green"))))) | M25: =IF(OR(A25="",F25="",H25="Complete"),"",IF(F25>=TODAY(),F25+ROW()/100000,"")) | N25: =IF(M25="","",B25&"|"&(COUNTIFS(B$5:B$34,B25,M$5:M$34,"<"&M25)+1))
I26: =IF(OR(A26="",H26="Complete"),"",IF(F26="","",F26-TODAY())) | J26: =IF(OR(E26="",F26=""),"",F26-E26) | K26: =IF(A26="","",IF(H26="Complete","Green",IF(F26="","",IF(F26<TODAY(),"Red",IF(F26-TODAY()<=7,"Yellow","Green"))))) | M26: =IF(OR(A26="",F26="",H26="Complete"),"",IF(F26>=TODAY(),F26+ROW()/100000,"")) | N26: =IF(M26="","",B26&"|"&(COUNTIFS(B$5:B$34,B26,M$5:M$34,"<"&M26)+1))
I27: =IF(OR(A27="",H27="Complete"),"",IF(F27="","",F27-TODAY())) | J27: =IF(OR(E27="",F27=""),"",F27-E27) | K27: =IF(A27="","",IF(H27="Complete","Green",IF(F27="","",IF(F27<TODAY(),"Red",IF(F27-TODAY()<=7,"Yellow","Green"))))) | M27: =IF(OR(A27="",F27="",H27="Complete"),"",IF(F27>=TODAY(),F27+ROW()/100000,"")) | N27: =IF(M27="","",B27&"|"&(COUNTIFS(B$5:B$34,B27,M$5:M$34,"<"&M27)+1))
I28: =IF(OR(A28="",H28="Complete"),"",IF(F28="","",F28-TODAY())) | J28: =IF(OR(E28="",F28=""),"",F28-E28) | K28: =IF(A28="","",IF(H28="Complete","Green",IF(F28="","",IF(F28<TODAY(),"Red",IF(F28-TODAY()<=7,"Yellow","Green"))))) | M28: =IF(OR(A28="",F28="",H28="Complete"),"",IF(F28>=TODAY(),F28+ROW()/100000,"")) | N28: =IF(M28="","",B28&"|"&(COUNTIFS(B$5:B$34,B28,M$5:M$34,"<"&M28)+1))
I29: =IF(OR(A29="",H29="Complete"),"",IF(F29="","",F29-TODAY())) | J29: =IF(OR(E29="",F29=""),"",F29-E29) | K29: =IF(A29="","",IF(H29="Complete","Green",IF(F29="","",IF(F29<TODAY(),"Red",IF(F29-TODAY()<=7,"Yellow","Green"))))) | M29: =IF(OR(A29="",F29="",H29="Complete"),"",IF(F29>=TODAY(),F29+ROW()/100000,"")) | N29: =IF(M29="","",B29&"|"&(COUNTIFS(B$5:B$34,B29,M$5:M$34,"<"&M29)+1))
I30: =IF(OR(A30="",H30="Complete"),"",IF(F30="","",F30-TODAY())) | J30: =IF(OR(E30="",F30=""),"",F30-E30) | K30: =IF(A30="","",IF(H30="Complete","Green",IF(F30="","",IF(F30<TODAY(),"Red",IF(F30-TODAY()<=7,"Yellow","Green"))))) | M30: =IF(OR(A30="",F30="",H30="Complete"),"",IF(F30>=TODAY(),F30+ROW()/100000,"")) | N30: =IF(M30="","",B30&"|"&(COUNTIFS(B$5:B$34,B30,M$5:M$34,"<"&M30)+1))
I31: =IF(OR(A31="",H31="Complete"),"",IF(F31="","",F31-TODAY())) | J31: =IF(OR(E31="",F31=""),"",F31-E31) | K31: =IF(A31="","",IF(H31="Complete","Green",IF(F31="","",IF(F31<TODAY(),"Red",IF(F31-TODAY()<=7,"Yellow","Green"))))) | M31: =IF(OR(A31="",F31="",H31="Complete"),"",IF(F31>=TODAY(),F31+ROW()/100000,"")) | N31: =IF(M31="","",B31&"|"&(COUNTIFS(B$5:B$34,B31,M$5:M$34,"<"&M31)+1))
I32: =IF(OR(A32="",H32="Complete"),"",IF(F32="","",F32-TODAY())) | J32: =IF(OR(E32="",F32=""),"",F32-E32) | K32: =IF(A32="","",IF(H32="Complete","Green",IF(F32="","",IF(F32<TODAY(),"Red",IF(F32-TODAY()<=7,"Yellow","Green"))))) | M32: =IF(OR(A32="",F32="",H32="Complete"),"",IF(F32>=TODAY(),F32+ROW()/100000,"")) | N32: =IF(M32="","",B32&"|"&(COUNTIFS(B$5:B$34,B32,M$5:M$34,"<"&M32)+1))
I33: =IF(OR(A33="",H33="Complete"),"",IF(F33="","",F33-TODAY())) | J33: =IF(OR(E33="",F33=""),"",F33-E33) | K33: =IF(A33="","",IF(H33="Complete","Green",IF(F33="","",IF(F33<TODAY(),"Red",IF(F33-TODAY()<=7,"Yellow","Green"))))) | M33: =IF(OR(A33="",F33="",H33="Complete"),"",IF(F33>=TODAY(),F33+ROW()/100000,"")) | N33: =IF(M33="","",B33&"|"&(COUNTIFS(B$5:B$34,B33,M$5:M$34,"<"&M33)+1))
I34: =IF(OR(A34="",H34="Complete"),"",IF(F34="","",F34-TODAY())) | J34: =IF(OR(E34="",F34=""),"",F34-E34) | K34: =IF(A34="","",IF(H34="Complete","Green",IF(F34="","",IF(F34<TODAY(),"Red",IF(F34-TODAY()<=7,"Yellow","Green"))))) | M34: =IF(OR(A34="",F34="",H34="Complete"),"",IF(F34>=TODAY(),F34+ROW()/100000,"")) | N34: =IF(M34="","",B34&"|"&(COUNTIFS(B$5:B$34,B34,M$5:M$34,"<"&M34)+1))

Sheet 06_RAID_LOG
A1: RAID LOG - RISKS, ASSUMPTIONS, ISSUES, DEPENDENCIES
A2: One controlled register for risks, assumptions, issues and dependencies. Risk score = probability x impact; dashboard charts and top-risk panels read this table.
A3: SAMPLE DATA - every sample record is marked SAMPLE in the Notes column. Delete or overwrite them freely: all formulas, KPIs, charts and drop-downs keep working.
A4: ID | B4: Project | C4: Type | D4: Description | E4: Category | F4: Probability | G4: Impact | H4: Risk Score | I4: Priority | J4: Owner | K4: Mitigation | L4: Contingency | M4: Due Date | N4: Status | O4: Escalation | P4: Resolution | Q4: Date Raised | R4: Date Closed | S4: Rank | T4: ProjKey
A5: RSK-001 | B5: ERP Implementation | C5: Risk | D5: Key vendor may miss module delivery date | E5: Vendor | F5: High | G5: High | H5: =IF(OR(F5="",G5=""),"",MATCH(F5,L_Prob,0)*MATCH(G5,L_Impact,0)) | I5: =IF(H5="","",IF(H5<=2,"Low",IF(H5<=5,"Medium",IF(H5<=9,"High","Critical")))) | J5: Lisa Chen | K5: Weekly vendor checkpoints and delivery plan review | L5: Re-plan schedule with second supplier | M5: 46325 | N5: Open | O5: Yes | Q5: 46280 | S5: =IF(OR(C5<>"Risk",N5="Closed",A5="",H5=""),"",COUNTIFS(C$5:C$34,"Risk",N$5:N$34,"<>Closed",H$5:H$34,">"&H5)+COUNTIFS(C$5:C5,"Risk",N$5:N5,"<>Closed",H$5:H5,H5)) | T5: =IF(OR(A5="",H5=""),"",C5&"|"&B5&"|"&(COUNTIFS(C$5:C$34,C5,B$5:B$34,B5,H$5:H$34,">"&H5)+1))
A6: RSK-002 | B6: ERP Implementation | C6: Risk | D6: Data migration quality may fail UAT | E6: Technical | F6: Critical | G6: High | H6: =IF(OR(F6="",G6=""),"",MATCH(F6,L_Prob,0)*MATCH(G6,L_Impact,0)) | I6: =IF(H6="","",IF(H6<=2,"Low",IF(H6<=5,"Medium",IF(H6<=9,"High","Critical")))) | J6: David Okoro | K6: Data cleansing sprints and mock migration | L6: Manual clean-up buffer before UAT | M6: 46319 | N6: Open | O6: Yes | Q6: 46283 | S6: =IF(OR(C6<>"Risk",N6="Closed",A6="",H6=""),"",COUNTIFS(C$5:C$34,"Risk",N$5:N$34,"<>Closed",H$5:H$34,">"&H6)+COUNTIFS(C$5:C6,"Risk",N$5:N6,"<>Closed",H$5:H6,H6)) | T6: =IF(OR(A6="",H6=""),"",C6&"|"&B6&"|"&(COUNTIFS(C$5:C$34,C6,B$5:B$34,B6,H$5:H$34,">"&H6)+1))
A7: RSK-003 | B7: HR Management System | C7: Risk | D7: Business users unavailable during peak season | E7: Resource | F7: Medium | G7: High | H7: =IF(OR(F7="",G7=""),"",MATCH(F7,L_Prob,0)*MATCH(G7,L_Impact,0)) | I7: =IF(H7="","",IF(H7<=2,"Low",IF(H7<=5,"Medium",IF(H7<=9,"High","Critical")))) | J7: David Okoro | K7: Agree UAT window with HR early | L7: Shift UAT to next quarter | M7: 46336 | N7: Open | O7: No | Q7: 46287 | S7: =IF(OR(C7<>"Risk",N7="Closed",A7="",H7=""),"",COUNTIFS(C$5:C$34,"Risk",N$5:N$34,"<>Closed",H$5:H$34,">"&H7)+COUNTIFS(C$5:C7,"Risk",N$5:N7,"<>Closed",H$5:H7,H7)) | T7: =IF(OR(A7="",H7=""),"",C7&"|"&B7&"|"&(COUNTIFS(C$5:C$34,C7,B$5:B$34,B7,H$5:H$34,">"&H7)+1))
A8: RSK-004 | B8: Network Infrastructure Upgrade | C8: Risk | D8: Cable supply lead time exceeds plan | E8: Vendor | F8: Medium | G8: Medium | H8: =IF(OR(F8="",G8=""),"",MATCH(F8,L_Prob,0)*MATCH(G8,L_Impact,0)) | I8: =IF(H8="","",IF(H8<=2,"Low",IF(H8<=5,"Medium",IF(H8<=9,"High","Critical")))) | J8: Lisa Chen | K8: Order cable in advance of install window | L8: Use alternative local supplier | M8: 46315 | N8: In Progress | O8: No | Q8: 46275 | S8: =IF(OR(C8<>"Risk",N8="Closed",A8="",H8=""),"",COUNTIFS(C$5:C$34,"Risk",N$5:N$34,"<>Closed",H$5:H$34,">"&H8)+COUNTIFS(C$5:C8,"Risk",N$5:N8,"<>Closed",H$5:H8,H8)) | T8: =IF(OR(A8="",H8=""),"",C8&"|"&B8&"|"&(COUNTIFS(C$5:C$34,C8,B$5:B$34,B8,H$5:H$34,">"&H8)+1))
A9: RSK-005 | B9: Website Development | C9: Risk | D9: Scope creep from marketing change requests | E9: Scope | F9: High | G9: Medium | H9: =IF(OR(F9="",G9=""),"",MATCH(F9,L_Prob,0)*MATCH(G9,L_Impact,0)) | I9: =IF(H9="","",IF(H9<=2,"Low",IF(H9<=5,"Medium",IF(H9<=9,"High","Critical")))) | J9: Maria Silva | K9: Freeze scope and route changes to change control | L9: Reduce page count in phase 1 | M9: 46323 | N9: Open | O9: No | Q9: 46290 | S9: =IF(OR(C9<>"Risk",N9="Closed",A9="",H9=""),"",COUNTIFS(C$5:C$34,"Risk",N$5:N$34,"<>Closed",H$5:H$34,">"&H9)+COUNTIFS(C$5:C9,"Risk",N$5:N9,"<>Closed",H$5:H9,H9)) | T9: =IF(OR(A9="",H9=""),"",C9&"|"&B9&"|"&(COUNTIFS(C$5:C$34,C9,B$5:B$34,B9,H$5:H$34,">"&H9)+1))
A10: RSK-006 | B10: Office Security Upgrade | C10: Risk | D10: Power interruption during installation | E10: Technical | F10: Low | G10: Medium | H10: =IF(OR(F10="",G10=""),"",MATCH(F10,L_Prob,0)*MATCH(G10,L_Impact,0)) | I10: =IF(H10="","",IF(H10<=2,"Low",IF(H10<=5,"Medium",IF(H10<=9,"High","Critical")))) | J10: Tom Becker | K10: Schedule works outside office hours | L10: Reschedule installation weekend | M10: 46331 | N10: Open | O10: No | Q10: 46296 | S10: =IF(OR(C10<>"Risk",N10="Closed",A10="",H10=""),"",COUNTIFS(C$5:C$34,"Risk",N$5:N$34,"<>Closed",H$5:H$34,">"&H10)+COUNTIFS(C$5:C10,"Risk",N$5:N10,"<>Closed",H$5:H10,H10)) | T10: =IF(OR(A10="",H10=""),"",C10&"|"&B10&"|"&(COUNTIFS(C$5:C$34,C10,B$5:B$34,B10,H$5:H$34,">"&H10)+1))
A11: RSK-007 | B11: Network Infrastructure Upgrade | C11: Risk | D11: Switch firmware defect found in test | E11: Technical | F11: High | G11: High | H11: =IF(OR(F11="",G11=""),"",MATCH(F11,L_Prob,0)*MATCH(G11,L_Impact,0)) | I11: =IF(H11="","",IF(H11<=2,"Low",IF(H11<=5,"Medium",IF(H11<=9,"High","Critical")))) | J11: Tom Becker | K11: Upgrade firmware before rollout | L11: Rollback to previous firmware | M11: 46295 | N11: Closed | O11: No | P11: Firmware 7.2.1 applied and verified | Q11: 46277 | R11: 46294 | S11: =IF(OR(C11<>"Risk",N11="Closed",A11="",H11=""),"",COUNTIFS(C$5:C$34,"Risk",N$5:N$34,"<>Closed",H$5:H$34,">"&H11)+COUNTIFS(C$5:C11,"Risk",N$5:N11,"<>Closed",H$5:H11,H11)) | T11: =IF(OR(A11="",H11=""),"",C11&"|"&B11&"|"&(COUNTIFS(C$5:C$34,C11,B$5:B$34,B11,H$5:H$34,">"&H11)+1))
A12: ASM-001 | B12: ERP Implementation | C12: Assumption | D12: Approved amount of 850,000 covers all phases | E12: Budget | F12: Medium | G12: High | H12: =IF(OR(F12="",G12=""),"",MATCH(F12,L_Prob,0)*MATCH(G12,L_Impact,0)) | I12: =IF(H12="","",IF(H12<=2,"Low",IF(H12<=5,"Medium",IF(H12<=9,"High","Critical")))) | J12: Priya Raman | K12: Confirm contingency drawdown rules with Finance | L12: Raise change request if gap | M12: 46326 | N12: Open | O12: No | Q12: 46208 | S12: =IF(OR(C12<>"Risk",N12="Closed",A12="",H12=""),"",COUNTIFS(C$5:C$34,"Risk",N$5:N$34,"<>Closed",H$5:H$34,">"&H12)+COUNTIFS(C$5:C12,"Risk",N$5:N12,"<>Closed",H$5:H12,H12)) | T12: =IF(OR(A12="",H12=""),"",C12&"|"&B12&"|"&(COUNTIFS(C$5:C$34,C12,B$5:B$34,B12,H$5:H$34,">"&H12)+1))
A13: ASM-002 | B13: HR Management System | C13: Assumption | D13: Legacy HR data can be migrated in one run | E13: Technical | F13: Medium | G13: Medium | H13: =IF(OR(F13="",G13=""),"",MATCH(F13,L_Prob,0)*MATCH(G13,L_Impact,0)) | I13: =IF(H13="","",IF(H13<=2,"Low",IF(H13<=5,"Medium",IF(H13<=9,"High","Critical")))) | J13: David Okoro | K13: Validate data quality sample | L13: Split migration into two batches | M13: 46341 | N13: Open | O13: No | Q13: 46273 | S13: =IF(OR(C13<>"Risk",N13="Closed",A13="",H13=""),"",COUNTIFS(C$5:C$34,"Risk",N$5:N$34,"<>Closed",H$5:H$34,">"&H13)+COUNTIFS(C$5:C13,"Risk",N$5:N13,"<>Closed",H$5:H13,H13)) | T13: =IF(OR(A13="",H13=""),"",C13&"|"&B13&"|"&(COUNTIFS(C$5:C$34,C13,B$5:B$34,B13,H$5:H$34,">"&H13)+1))
A14: ISS-001 | B14: ERP Implementation | C14: Issue | D14: UAT test environment not available | E14: Technical | F14: High | G14: High | H14: =IF(OR(F14="",G14=""),"",MATCH(F14,L_Prob,0)*MATCH(G14,L_Impact,0)) | I14: =IF(H14="","",IF(H14<=2,"Low",IF(H14<=5,"Medium",IF(H14<=9,"High","Critical")))) | J14: Tom Becker | K14: Provision environment by 12 Oct | L14: Book shared test server | M14: 46307 | N14: Open | O14: Yes | Q14: 46301 | S14: =IF(OR(C14<>"Risk",N14="Closed",A14="",H14=""),"",COUNTIFS(C$5:C$34,"Risk",N$5:N$34,"<>Closed",H$5:H$34,">"&H14)+COUNTIFS(C$5:C14,"Risk",N$5:N14,"<>Closed",H$5:H14,H14)) | T14: =IF(OR(A14="",H14=""),"",C14&"|"&B14&"|"&(COUNTIFS(C$5:C$34,C14,B$5:B$34,B14,H$5:H$34,">"&H14)+1))
A15: ISS-002 | B15: HR Management System | C15: Issue | D15: Incomplete employee data for migration | E15: Resource | F15: High | G15: Medium | H15: =IF(OR(F15="",G15=""),"",MATCH(F15,L_Prob,0)*MATCH(G15,L_Impact,0)) | I15: =IF(H15="","",IF(H15<=2,"Low",IF(H15<=5,"Medium",IF(H15<=9,"High","Critical")))) | J15: David Okoro | K15: HR to complete missing fields | L15: Manual completion during migration | M15: 46310 | N15: In Progress | O15: No | Q15: 46297 | S15: =IF(OR(C15<>"Risk",N15="Closed",A15="",H15=""),"",COUNTIFS(C$5:C$34,"Risk",N$5:N$34,"<>Closed",H$5:H$34,">"&H15)+COUNTIFS(C$5:C15,"Risk",N$5:N15,"<>Closed",H$5:H15,H15)) | T15: =IF(OR(A15="",H15=""),"",C15&"|"&B15&"|"&(COUNTIFS(C$5:C$34,C15,B$5:B$34,B15,H$5:H$34,">"&H15)+1))
A16: ISS-003 | B16: Network Infrastructure Upgrade | C16: Issue | D16: Site access delayed by facilities | E16: Resource | F16: Medium | G16: Medium | H16: =IF(OR(F16="",G16=""),"",MATCH(F16,L_Prob,0)*MATCH(G16,L_Impact,0)) | I16: =IF(H16="","",IF(H16<=2,"Low",IF(H16<=5,"Medium",IF(H16<=9,"High","Critical")))) | J16: Tom Becker | K16: Confirm access window with facilities | L16: Reschedule installation | M16: 46309 | N16: In Progress | O16: No | Q16: 46298 | S16: =IF(OR(C16<>"Risk",N16="Closed",A16="",H16=""),"",COUNTIFS(C$5:C$34,"Risk",N$5:N$34,"<>Closed",H$5:H$34,">"&H16)+COUNTIFS(C$5:C16,"Risk",N$5:N16,"<>Closed",H$5:H16,H16)) | T16: =IF(OR(A16="",H16=""),"",C16&"|"&B16&"|"&(COUNTIFS(C$5:C$34,C16,B$5:B$34,B16,H$5:H$34,">"&H16)+1))
A17: ISS-004 | B17: ERP Implementation | C17: Issue | D17: Finance analyst not yet assigned to project | E17: Resource | F17: Low | G17: Medium | H17: =IF(OR(F17="",G17=""),"",MATCH(F17,L_Prob,0)*MATCH(G17,L_Impact,0)) | I17: =IF(H17="","",IF(H17<=2,"Low",IF(H17<=5,"Medium",IF(H17<=9,"High","Critical")))) | J17: Ahmed Khan | K17: Sponsor to nominate analyst | L17: PMO provides interim support | M17: 46315 | N17: Open | O17: No | Q17: 46300 | S17: =IF(OR(C17<>"Risk",N17="Closed",A17="",H17=""),"",COUNTIFS(C$5:C$34,"Risk",N$5:N$34,"<>Closed",H$5:H$34,">"&H17)+COUNTIFS(C$5:C17,"Risk",N$5:N17,"<>Closed",H$5:H17,H17)) | T17: =IF(OR(A17="",H17=""),"",C17&"|"&B17&"|"&(COUNTIFS(C$5:C$34,C17,B$5:B$34,B17,H$5:H$34,">"&H17)+1))
A18: ISS-005 | B18: Website Development | C18: Issue | D18: Hosting certificate expired | E18: Technical | F18: Medium | G18: High | H18: =IF(OR(F18="",G18=""),"",MATCH(F18,L_Prob,0)*MATCH(G18,L_Impact,0)) | I18: =IF(H18="","",IF(H18<=2,"Low",IF(H18<=5,"Medium",IF(H18<=9,"High","Critical")))) | J18: Tom Becker | K18: Renew certificate | L18: Temporary certificate issued | M18: 46285 | N18: Closed | O18: No | P18: Certificate renewed for 12 months | Q18: 46283 | R18: 46284 | S18: =IF(OR(C18<>"Risk",N18="Closed",A18="",H18=""),"",COUNTIFS(C$5:C$34,"Risk",N$5:N$34,"<>Closed",H$5:H$34,">"&H18)+COUNTIFS(C$5:C18,"Risk",N$5:N18,"<>Closed",H$5:H18,H18)) | T18: =IF(OR(A18="",H18=""),"",C18&"|"&B18&"|"&(COUNTIFS(C$5:C$34,C18,B$5:B$34,B18,H$5:H$34,">"&H18)+1))
A19: DEP-001 | B19: ERP Implementation | C19: Dependency | D19: Payment gateway provider approval pending | E19: Vendor | F19: High | G19: Medium | H19: =IF(OR(F19="",G19=""),"",MATCH(F19,L_Prob,0)*MATCH(G19,L_Impact,0)) | I19: =IF(H19="","",IF(H19<=2,"Low",IF(H19<=5,"Medium",IF(H19<=9,"High","Critical")))) | J19: Priya Raman | K19: Weekly follow-up with provider | L19: Use manual payment interface initially | M19: 46313 | N19: Open | O19: Yes | Q19: 46285 | S19: =IF(OR(C19<>"Risk",N19="Closed",A19="",H19=""),"",COUNTIFS(C$5:C$34,"Risk",N$5:N$34,"<>Closed",H$5:H$34,">"&H19)+COUNTIFS(C$5:C19,"Risk",N$5:N19,"<>Closed",H$5:H19,H19)) | T19: =IF(OR(A19="",H19=""),"",C19&"|"&B19&"|"&(COUNTIFS(C$5:C$34,C19,B$5:B$34,B19,H$5:H$34,">"&H19)+1))
A20: DEP-002 | B20: HR Management System | C20: Dependency | D20: Legal contract review required before signature | E20: Legal | F20: Medium | G20: High | H20: =IF(OR(F20="",G20=""),"",MATCH(F20,L_Prob,0)*MATCH(G20,L_Impact,0)) | I20: =IF(H20="","",IF(H20<=2,"Low",IF(H20<=5,"Medium",IF(H20<=9,"High","Critical")))) | J20: Grace Alemu | K20: Book legal review slot | L20: Conditional approval from legal | M20: 46327 | N20: Open | O20: No | Q20: 46293 | S20: =IF(OR(C20<>"Risk",N20="Closed",A20="",H20=""),"",COUNTIFS(C$5:C$34,"Risk",N$5:N$34,"<>Closed",H$5:H$34,">"&H20)+COUNTIFS(C$5:C20,"Risk",N$5:N20,"<>Closed",H$5:H20,H20)) | T20: =IF(OR(A20="",H20=""),"",C20&"|"&B20&"|"&(COUNTIFS(C$5:C$34,C20,B$5:B$34,B20,H$5:H$34,">"&H20)+1))
H21: =IF(OR(F21="",G21=""),"",MATCH(F21,L_Prob,0)*MATCH(G21,L_Impact,0)) | I21: =IF(H21="","",IF(H21<=2,"Low",IF(H21<=5,"Medium",IF(H21<=9,"High","Critical")))) | S21: =IF(OR(C21<>"Risk",N21="Closed",A21="",H21=""),"",COUNTIFS(C$5:C$34,"Risk",N$5:N$34,"<>Closed",H$5:H$34,">"&H21)+COUNTIFS(C$5:C21,"Risk",N$5:N21,"<>Closed",H$5:H21,H21)) | T21: =IF(OR(A21="",H21=""),"",C21&"|"&B21&"|"&(COUNTIFS(C$5:C$34,C21,B$5:B$34,B21,H$5:H$34,">"&H21)+1))
H22: =IF(OR(F22="",G22=""),"",MATCH(F22,L_Prob,0)*MATCH(G22,L_Impact,0)) | I22: =IF(H22="","",IF(H22<=2,"Low",IF(H22<=5,"Medium",IF(H22<=9,"High","Critical")))) | S22: =IF(OR(C22<>"Risk",N22="Closed",A22="",H22=""),"",COUNTIFS(C$5:C$34,"Risk",N$5:N$34,"<>Closed",H$5:H$34,">"&H22)+COUNTIFS(C$5:C22,"Risk",N$5:N22,"<>Closed",H$5:H22,H22)) | T22: =IF(OR(A22="",H22=""),"",C22&"|"&B22&"|"&(COUNTIFS(C$5:C$34,C22,B$5:B$34,B22,H$5:H$34,">"&H22)+1))
H23: =IF(OR(F23="",G23=""),"",MATCH(F23,L_Prob,0)*MATCH(G23,L_Impact,0)) | I23: =IF(H23="","",IF(H23<=2,"Low",IF(H23<=5,"Medium",IF(H23<=9,"High","Critical")))) | S23: =IF(OR(C23<>"Risk",N23="Closed",A23="",H23=""),"",COUNTIFS(C$5:C$34,"Risk",N$5:N$34,"<>Closed",H$5:H$34,">"&H23)+COUNTIFS(C$5:C23,"Risk",N$5:N23,"<>Closed",H$5:H23,H23)) | T23: =IF(OR(A23="",H23=""),"",C23&"|"&B23&"|"&(COUNTIFS(C$5:C$34,C23,B$5:B$34,B23,H$5:H$34,">"&H23)+1))
H24: =IF(OR(F24="",G24=""),"",MATCH(F24,L_Prob,0)*MATCH(G24,L_Impact,0)) | I24: =IF(H24="","",IF(H24<=2,"Low",IF(H24<=5,"Medium",IF(H24<=9,"High","Critical")))) | S24: =IF(OR(C24<>"Risk",N24="Closed",A24="",H24=""),"",COUNTIFS(C$5:C$34,"Risk",N$5:N$34,"<>Closed",H$5:H$34,">"&H24)+COUNTIFS(C$5:C24,"Risk",N$5:N24,"<>Closed",H$5:H24,H24)) | T24: =IF(OR(A24="",H24=""),"",C24&"|"&B24&"|"&(COUNTIFS(C$5:C$34,C24,B$5:B$34,B24,H$5:H$34,">"&H24)+1))
H25: =IF(OR(F25="",G25=""),"",MATCH(F25,L_Prob,0)*MATCH(G25,L_Impact,0)) | I25: =IF(H25="","",IF(H25<=2,"Low",IF(H25<=5,"Medium",IF(H25<=9,"High","Critical")))) | S25: =IF(OR(C25<>"Risk",N25="Closed",A25="",H25=""),"",COUNTIFS(C$5:C$34,"Risk",N$5:N$34,"<>Closed",H$5:H$34,">"&H25)+COUNTIFS(C$5:C25,"Risk",N$5:N25,"<>Closed",H$5:H25,H25)) | T25: =IF(OR(A25="",H25=""),"",C25&"|"&B25&"|"&(COUNTIFS(C$5:C$34,C25,B$5:B$34,B25,H$5:H$34,">"&H25)+1))
H26: =IF(OR(F26="",G26=""),"",MATCH(F26,L_Prob,0)*MATCH(G26,L_Impact,0)) | I26: =IF(H26="","",IF(H26<=2,"Low",IF(H26<=5,"Medium",IF(H26<=9,"High","Critical")))) | S26: =IF(OR(C26<>"Risk",N26="Closed",A26="",H26=""),"",COUNTIFS(C$5:C$34,"Risk",N$5:N$34,"<>Closed",H$5:H$34,">"&H26)+COUNTIFS(C$5:C26,"Risk",N$5:N26,"<>Closed",H$5:H26,H26)) | T26: =IF(OR(A26="",H26=""),"",C26&"|"&B26&"|"&(COUNTIFS(C$5:C$34,C26,B$5:B$34,B26,H$5:H$34,">"&H26)+1))
H27: =IF(OR(F27="",G27=""),"",MATCH(F27,L_Prob,0)*MATCH(G27,L_Impact,0)) | I27: =IF(H27="","",IF(H27<=2,"Low",IF(H27<=5,"Medium",IF(H27<=9,"High","Critical")))) | S27: =IF(OR(C27<>"Risk",N27="Closed",A27="",H27=""),"",COUNTIFS(C$5:C$34,"Risk",N$5:N$34,"<>Closed",H$5:H$34,">"&H27)+COUNTIFS(C$5:C27,"Risk",N$5:N27,"<>Closed",H$5:H27,H27)) | T27: =IF(OR(A27="",H27=""),"",C27&"|"&B27&"|"&(COUNTIFS(C$5:C$34,C27,B$5:B$34,B27,H$5:H$34,">"&H27)+1))
H28: =IF(OR(F28="",G28=""),"",MATCH(F28,L_Prob,0)*MATCH(G28,L_Impact,0)) | I28: =IF(H28="","",IF(H28<=2,"Low",IF(H28<=5,"Medium",IF(H28<=9,"High","Critical")))) | S28: =IF(OR(C28<>"Risk",N28="Closed",A28="",H28=""),"",COUNTIFS(C$5:C$34,"Risk",N$5:N$34,"<>Closed",H$5:H$34,">"&H28)+COUNTIFS(C$5:C28,"Risk",N$5:N28,"<>Closed",H$5:H28,H28)) | T28: =IF(OR(A28="",H28=""),"",C28&"|"&B28&"|"&(COUNTIFS(C$5:C$34,C28,B$5:B$34,B28,H$5:H$34,">"&H28)+1))
H29: =IF(OR(F29="",G29=""),"",MATCH(F29,L_Prob,0)*MATCH(G29,L_Impact,0)) | I29: =IF(H29="","",IF(H29<=2,"Low",IF(H29<=5,"Medium",IF(H29<=9,"High","Critical")))) | S29: =IF(OR(C29<>"Risk",N29="Closed",A29="",H29=""),"",COUNTIFS(C$5:C$34,"Risk",N$5:N$34,"<>Closed",H$5:H$34,">"&H29)+COUNTIFS(C$5:C29,"Risk",N$5:N29,"<>Closed",H$5:H29,H29)) | T29: =IF(OR(A29="",H29=""),"",C29&"|"&B29&"|"&(COUNTIFS(C$5:C$34,C29,B$5:B$34,B29,H$5:H$34,">"&H29)+1))
H30: =IF(OR(F30="",G30=""),"",MATCH(F30,L_Prob,0)*MATCH(G30,L_Impact,0)) | I30: =IF(H30="","",IF(H30<=2,"Low",IF(H30<=5,"Medium",IF(H30<=9,"High","Critical")))) | S30: =IF(OR(C30<>"Risk",N30="Closed",A30="",H30=""),"",COUNTIFS(C$5:C$34,"Risk",N$5:N$34,"<>Closed",H$5:H$34,">"&H30)+COUNTIFS(C$5:C30,"Risk",N$5:N30,"<>Closed",H$5:H30,H30)) | T30: =IF(OR(A30="",H30=""),"",C30&"|"&B30&"|"&(COUNTIFS(C$5:C$34,C30,B$5:B$34,B30,H$5:H$34,">"&H30)+1))
H31: =IF(OR(F31="",G31=""),"",MATCH(F31,L_Prob,0)*MATCH(G31,L_Impact,0)) | I31: =IF(H31="","",IF(H31<=2,"Low",IF(H31<=5,"Medium",IF(H31<=9,"High","Critical")))) | S31: =IF(OR(C31<>"Risk",N31="Closed",A31="",H31=""),"",COUNTIFS(C$5:C$34,"Risk",N$5:N$34,"<>Closed",H$5:H$34,">"&H31)+COUNTIFS(C$5:C31,"Risk",N$5:N31,"<>Closed",H$5:H31,H31)) | T31: =IF(OR(A31="",H31=""),"",C31&"|"&B31&"|"&(COUNTIFS(C$5:C$34,C31,B$5:B$34,B31,H$5:H$34,">"&H31)+1))
H32: =IF(OR(F32="",G32=""),"",MATCH(F32,L_Prob,0)*MATCH(G32,L_Impact,0)) | I32: =IF(H32="","",IF(H32<=2,"Low",IF(H32<=5,"Medium",IF(H32<=9,"High","Critical")))) | S32: =IF(OR(C32<>"Risk",N32="Closed",A32="",H32=""),"",COUNTIFS(C$5:C$34,"Risk",N$5:N$34,"<>Closed",H$5:H$34,">"&H32)+COUNTIFS(C$5:C32,"Risk",N$5:N32,"<>Closed",H$5:H32,H32)) | T32: =IF(OR(A32="",H32=""),"",C32&"|"&B32&"|"&(COUNTIFS(C$5:C$34,C32,B$5:B$34,B32,H$5:H$34,">"&H32)+1))
... H34: =IF(OR(F34="",G34=""),"",MATCH(F34,L_Prob,0)*MATCH(G34,L_Impact,0)) | I34: =IF(H34="","",IF(H34<=2,"Low",IF(H34<=5,"Medium",IF(H34<=9,"High","Critical")))) | S34: =IF(OR(C34<>"Risk",N34="Closed",A34="",H34=""),"",COUNTIFS(C$5:C$34,"Risk",N$5:N$34,"<>Closed",H$5:H$34,">"&H34)+COUNTIFS(C$5:C34,"Risk",N$5:N34,"<>Closed",H$5:H34,H34)) | T34: =IF(OR(A34="",H34=""),"",C34&"|"&B34&"|"&(COUNTIFS(C$5:C$34,C34,B$5:B$34,B34,H$5:H$34,">"&H34)+1))

Sheet 07_ACTION_TRACKER
A1: ACTION TRACKER
A2: Every action from every meeting with one owner and one due date. Overdue = red, due within 3 days = amber, complete = green. Feeds the dashboard overdue KPI and charts.
A3: SAMPLE DATA - every sample record is marked SAMPLE in the Notes column. Delete or overwrite them freely: all formulas, KPIs, charts and drop-downs keep working.
A4: Action ID | B4: Project | C4: Meeting / Source | D4: Action | E4: Owner | F4: Priority | G4: Date Opened | H4: Due Date | I4: Status | J4: Days Remaining | K4: Days Overdue | L4: Escalation | M4: Completion Date | N4: Notes | O4: OverdueRank | P4: ProjKey
A5: ACT-001 | B5: ERP Implementation | C5: Steering Committee 06-Oct | D5: Confirm UAT user list with business | E5: Maria Silva | F5: High | G5: 46301 | H5: 46301 | I5: Open | J5: =IF(OR(A5="",I5="Complete",H5=""),"",H5-TODAY()) | K5: =IF(OR(A5="",H5="",I5="Complete"),0,MAX(0,TODAY()-H5)) | L5: Yes | N5: SAMPLE | O5: =IF(OR(A5="",I5="Complete",K5<=0),"",COUNTIFS(I$5:I$34,"<>Complete",K$5:K$34,">"&K5)+COUNTIFS(I$5:I5,"<>Complete",K$5:K5,K5)) | P5: =IF(OR(A5="",I5="Complete"),"",B5&"|"&(COUNTIFS(B$5:B$34,B5,I$5:I$34,"<>Complete",K$5:K$34,">"&K5)+COUNTIFS(B$5:B5,B5,I$5:I5,"<>Complete",K$5:K5,K5)))
A6: ACT-002 | B6: ERP Implementation | C6: PMO Review 01-Oct | D6: Chase vendor on module delivery dates | E6: Lisa Chen | F6: Critical | G6: 46296 | H6: 46300 | I6: Open | J6: =IF(OR(A6="",I6="Complete",H6=""),"",H6-TODAY()) | K6: =IF(OR(A6="",H6="",I6="Complete"),0,MAX(0,TODAY()-H6)) | L6: Yes | N6: SAMPLE | O6: =IF(OR(A6="",I6="Complete",K6<=0),"",COUNTIFS(I$5:I$34,"<>Complete",K$5:K$34,">"&K6)+COUNTIFS(I$5:I6,"<>Complete",K$5:K6,K6)) | P6: =IF(OR(A6="",I6="Complete"),"",B6&"|"&(COUNTIFS(B$5:B$34,B6,I$5:I$34,"<>Complete",K$5:K$34,">"&K6)+COUNTIFS(B$5:B6,B6,I$5:I6,"<>Complete",K$5:K6,K6)))
A7: ACT-003 | B7: Network Infrastructure Upgrade | C7: Project Team 07-Oct | D7: Confirm site access schedule with facilities | E7: Tom Becker | F7: High | G7: 46302 | H7: 46304 | I7: In Progress | J7: =IF(OR(A7="",I7="Complete",H7=""),"",H7-TODAY()) | K7: =IF(OR(A7="",H7="",I7="Complete"),0,MAX(0,TODAY()-H7)) | L7: No | N7: SAMPLE | O7: =IF(OR(A7="",I7="Complete",K7<=0),"",COUNTIFS(I$5:I$34,"<>Complete",K$5:K$34,">"&K7)+COUNTIFS(I$5:I7,"<>Complete",K$5:K7,K7)) | P7: =IF(OR(A7="",I7="Complete"),"",B7&"|"&(COUNTIFS(B$5:B$34,B7,I$5:I$34,"<>Complete",K$5:K$34,">"&K7)+COUNTIFS(B$5:B7,B7,I$5:I7,"<>Complete",K$5:K7,K7)))
A8: ACT-004 | B8: HR Management System | C8: Steering Committee 08-Oct | D8: Sign off vendor shortlist | E8: David Okoro | F8: High | G8: 46303 | H8: 46305 | I8: Open | J8: =IF(OR(A8="",I8="Complete",H8=""),"",H8-TODAY()) | K8: =IF(OR(A8="",H8="",I8="Complete"),0,MAX(0,TODAY()-H8)) | L8: No | N8: SAMPLE | O8: =IF(OR(A8="",I8="Complete",K8<=0),"",COUNTIFS(I$5:I$34,"<>Complete",K$5:K$34,">"&K8)+COUNTIFS(I$5:I8,"<>Complete",K$5:K8,K8)) | P8: =IF(OR(A8="",I8="Complete"),"",B8&"|"&(COUNTIFS(B$5:B$34,B8,I$5:I$34,"<>Complete",K$5:K$34,">"&K8)+COUNTIFS(B$5:B8,B8,I$5:I8,"<>Complete",K$5:K8,K8)))
A9: ACT-005 | B9: ERP Implementation | C9: Sponsor Review 02-Oct | D9: Approve change request CR-001 | E9: Ahmed Khan | F9: Critical | G9: 46297 | H9: 46302 | I9: Open | J9: =IF(OR(A9="",I9="Complete",H9=""),"",H9-TODAY()) | K9: =IF(OR(A9="",H9="",I9="Complete"),0,MAX(0,TODAY()-H9)) | L9: Yes | N9: SAMPLE | O9: =IF(OR(A9="",I9="Complete",K9<=0),"",COUNTIFS(I$5:I$34,"<>Complete",K$5:K$34,">"&K9)+COUNTIFS(I$5:I9,"<>Complete",K$5:K9,K9)) | P9: =IF(OR(A9="",I9="Complete"),"",B9&"|"&(COUNTIFS(B$5:B$34,B9,I$5:I$34,"<>Complete",K$5:K$34,">"&K9)+COUNTIFS(B$5:B9,B9,I$5:I9,"<>Complete",K$5:K9,K9)))
A10: ACT-006 | B10: Website Development | C10: Project Team 05-Oct | D10: Restart kick-off once scope is frozen | E10: Maria Silva | F10: Medium | G10: 46300 | H10: 46312 | I10: Open | J10: =IF(OR(A10="",I10="Complete",H10=""),"",H10-TODAY()) | K10: =IF(OR(A10="",H10="",I10="Complete"),0,MAX(0,TODAY()-H10)) | L10: No | N10: SAMPLE | O10: =IF(OR(A10="",I10="Complete",K10<=0),"",COUNTIFS(I$5:I$34,"<>Complete",K$5:K$34,">"&K10)+COUNTIFS(I$5:I10,"<>Complete",K$5:K10,K10)) | P10: =IF(OR(A10="",I10="Complete"),"",B10&"|"&(COUNTIFS(B$5:B$34,B10,I$5:I$34,"<>Complete",K$5:K$34,">"&K10)+COUNTIFS(B$5:B10,B10,I$5:I10,"<>Complete",K$5:K10,K10)))
A11: ACT-007 | B11: ERP Implementation | C11: PMO Review 06-Oct | D11: Update RAID with migration quality risk | E11: David Okoro | F11: Medium | G11: 46301 | H11: 46308 | I11: In Progress | J11: =IF(OR(A11="",I11="Complete",H11=""),"",H11-TODAY()) | K11: =IF(OR(A11="",H11="",I11="Complete"),0,MAX(0,TODAY()-H11)) | L11: No | N11: SAMPLE | O11: =IF(OR(A11="",I11="Complete",K11<=0),"",COUNTIFS(I$5:I$34,"<>Complete",K$5:K$34,">"&K11)+COUNTIFS(I$5:I11,"<>Complete",K$5:K11,K11)) | P11: =IF(OR(A11="",I11="Complete"),"",B11&"|"&(COUNTIFS(B$5:B$34,B11,I$5:I$34,"<>Complete",K$5:K$34,">"&K11)+COUNTIFS(B$5:B11,B11,I$5:I11,"<>Complete",K$5:K11,K11)))
A12: ACT-008 | B12: ERP Implementation | C12: Weekly Team 30-Sep | D12: Publish September cost report | E12: Priya Raman | F12: Medium | G12: 46295 | H12: 46298 | I12: Open | J12: =IF(OR(A12="",I12="Complete",H12=""),"",H12-TODAY()) | K12: =IF(OR(A12="",H12="",I12="Complete"),0,MAX(0,TODAY()-H12)) | L12: Yes | N12: SAMPLE | O12: =IF(OR(A12="",I12="Complete",K12<=0),"",COUNTIFS(I$5:I$34,"<>Complete",K$5:K$34,">"&K12)+COUNTIFS(I$5:I12,"<>Complete",K$5:K12,K12)) | P12: =IF(OR(A12="",I12="Complete"),"",B12&"|"&(COUNTIFS(B$5:B$34,B12,I$5:I$34,"<>Complete",K$5:K$34,">"&K12)+COUNTIFS(B$5:B12,B12,I$5:I12,"<>Complete",K$5:K12,K12)))
A13: ACT-009 | B13: ERP Implementation | C13: Project Team 08-Oct | D13: Book UAT training room and invites | E13: Maria Silva | F13: Low | G13: 46303 | H13: 46315 | I13: Open | J13: =IF(OR(A13="",I13="Complete",H13=""),"",H13-TODAY()) | K13: =IF(OR(A13="",H13="",I13="Complete"),0,MAX(0,TODAY()-H13)) | L13: No | N13: SAMPLE | O13: =IF(OR(A13="",I13="Complete",K13<=0),"",COUNTIFS(I$5:I$34,"<>Complete",K$5:K$34,">"&K13)+COUNTIFS(I$5:I13,"<>Complete",K$5:K13,K13)) | P13: =IF(OR(A13="",I13="Complete"),"",B13&"|"&(COUNTIFS(B$5:B$34,B13,I$5:I$34,"<>Complete",K$5:K$34,">"&K13)+COUNTIFS(B$5:B13,B13,I$5:I13,"<>Complete",K$5:K13,K13)))
A14: ACT-010 | B14: Network Infrastructure Upgrade | C14: Project Team 28-Sep | D14: Deliver cabling quotation | E14: Lisa Chen | F14: High | G14: 46293 | H14: 46297 | I14: Complete | J14: =IF(OR(A14="",I14="Complete",H14=""),"",H14-TODAY()) | K14: =IF(OR(A14="",H14="",I14="Complete"),0,MAX(0,TODAY()-H14)) | L14: No | M14: 46296 | N14: SAMPLE | O14: =IF(OR(A14="",I14="Complete",K14<=0),"",COUNTIFS(I$5:I$34,"<>Complete",K$5:K$34,">"&K14)+COUNTIFS(I$5:I14,"<>Complete",K$5:K14,K14)) | P14: =IF(OR(A14="",I14="Complete"),"",B14&"|"&(COUNTIFS(B$5:B$34,B14,I$5:I$34,"<>Complete",K$5:K$34,">"&K14)+COUNTIFS(B$5:B14,B14,I$5:I14,"<>Complete",K$5:K14,K14)))
A15: ACT-011 | B15: HR Management System | C15: Sponsor Review 01-Oct | D15: Confirm approved amount with Finance | E15: David Okoro | F15: Critical | G15: 46296 | H15: 46310 | I15: Open | J15: =IF(OR(A15="",I15="Complete",H15=""),"",H15-TODAY()) | K15: =IF(OR(A15="",H15="",I15="Complete"),0,MAX(0,TODAY()-H15)) | L15: No | N15: SAMPLE | O15: =IF(OR(A15="",I15="Complete",K15<=0),"",COUNTIFS(I$5:I$34,"<>Complete",K$5:K$34,">"&K15)+COUNTIFS(I$5:I15,"<>Complete",K$5:K15,K15)) | P15: =IF(OR(A15="",I15="Complete"),"",B15&"|"&(COUNTIFS(B$5:B$34,B15,I$5:I$34,"<>Complete",K$5:K$34,">"&K15)+COUNTIFS(B$5:B15,B15,I$5:I15,"<>Complete",K$5:K15,K15)))
A16: ACT-012 | B16: Office Security Upgrade | C16: Project Team 04-Oct | D16: Finalise vendor selection | E16: Lisa Chen | F16: High | G16: 46299 | H16: 46301 | I16: Open | J16: =IF(OR(A16="",I16="Complete",H16=""),"",H16-TODAY()) | K16: =IF(OR(A16="",H16="",I16="Complete"),0,MAX(0,TODAY()-H16)) | L16: No | N16: SAMPLE | O16: =IF(OR(A16="",I16="Complete",K16<=0),"",COUNTIFS(I$5:I$34,"<>Complete",K$5:K$34,">"&K16)+COUNTIFS(I$5:I16,"<>Complete",K$5:K16,K16)) | P16: =IF(OR(A16="",I16="Complete"),"",B16&"|"&(COUNTIFS(B$5:B$34,B16,I$5:I$34,"<>Complete",K$5:K$34,">"&K16)+COUNTIFS(B$5:B16,B16,I$5:I16,"<>Complete",K$5:K16,K16)))
A17: ACT-013 | B17: ERP Implementation | C17: Project Team 25-Sep | D17: Archive approved design documents | E17: Priya Raman | F17: Low | G17: 46290 | H17: 46295 | I17: Complete | J17: =IF(OR(A17="",I17="Complete",H17=""),"",H17-TODAY()) | K17: =IF(OR(A17="",H17="",I17="Complete"),0,MAX(0,TODAY()-H17)) | L17: No | M17: 46295 | N17: SAMPLE | O17: =IF(OR(A17="",I17="Complete",K17<=0),"",COUNTIFS(I$5:I$34,"<>Complete",K$5:K$34,">"&K17)+COUNTIFS(I$5:I17,"<>Complete",K$5:K17,K17)) | P17: =IF(OR(A17="",I17="Complete"),"",B17&"|"&(COUNTIFS(B$5:B$34,B17,I$5:I$34,"<>Complete",K$5:K$34,">"&K17)+COUNTIFS(B$5:B17,B17,I$5:I17,"<>Complete",K$5:K17,K17)))
A18: ACT-014 | B18: Payroll Reporting Portal | C18: Closure Review 01-Oct | D18: Collect lessons learned from project team | E18: Priya Raman | F18: Medium | G18: 46296 | H18: 46304 | I18: Open | J18: =IF(OR(A18="",I18="Complete",H18=""),"",H18-TODAY()) | K18: =IF(OR(A18="",H18="",I18="Complete"),0,MAX(0,TODAY()-H18)) | L18: No | N18: SAMPLE | O18: =IF(OR(A18="",I18="Complete",K18<=0),"",COUNTIFS(I$5:I$34,"<>Complete",K$5:K$34,">"&K18)+COUNTIFS(I$5:I18,"<>Complete",K$5:K18,K18)) | P18: =IF(OR(A18="",I18="Complete"),"",B18&"|"&(COUNTIFS(B$5:B$34,B18,I$5:I$34,"<>Complete",K$5:K$34,">"&K18)+COUNTIFS(B$5:B18,B18,I$5:I18,"<>Complete",K$5:K18,K18)))
J19: =IF(OR(A19="",I19="Complete",H19=""),"",H19-TODAY()) | K19: =IF(OR(A19="",H19="",I19="Complete"),0,MAX(0,TODAY()-H19)) | O19: =IF(OR(A19="",I19="Complete",K19<=0),"",COUNTIFS(I$5:I$34,"<>Complete",K$5:K$34,">"&K19)+COUNTIFS(I$5:I19,"<>Complete",K$5:K19,K19)) | P19: =IF(OR(A19="",I19="Complete"),"",B19&"|"&(COUNTIFS(B$5:B$34,B19,I$5:I$34,"<>Complete",K$5:K$34,">"&K19)+COUNTIFS(B$5:B19,B19,I$5:I19,"<>Complete",K$5:K19,K19)))
J20: =IF(OR(A20="",I20="Complete",H20=""),"",H20-TODAY()) | K20: =IF(OR(A20="",H20="",I20="Complete"),0,MAX(0,TODAY()-H20)) | O20: =IF(OR(A20="",I20="Complete",K20<=0),"",COUNTIFS(I$5:I$34,"<>Complete",K$5:K$34,">"&K20)+COUNTIFS(I$5:I20,"<>Complete",K$5:K20,K20)) | P20: =IF(OR(A20="",I20="Complete"),"",B20&"|"&(COUNTIFS(B$5:B$34,B20,I$5:I$34,"<>Complete",K$5:K$34,">"&K20)+COUNTIFS(B$5:B20,B20,I$5:I20,"<>Complete",K$5:K20,K20)))
J21: =IF(OR(A21="",I21="Complete",H21=""),"",H21-TODAY()) | K21: =IF(OR(A21="",H21="",I21="Complete"),0,MAX(0,TODAY()-H21)) | O21: =IF(OR(A21="",I21="Complete",K21<=0),"",COUNTIFS(I$5:I$34,"<>Complete",K$5:K$34,">"&K21)+COUNTIFS(I$5:I21,"<>Complete",K$5:K21,K21)) | P21: =IF(OR(A21="",I21="Complete"),"",B21&"|"&(COUNTIFS(B$5:B$34,B21,I$5:I$34,"<>Complete",K$5:K$34,">"&K21)+COUNTIFS(B$5:B21,B21,I$5:I21,"<>Complete",K$5:K21,K21)))
J22: =IF(OR(A22="",I22="Complete",H22=""),"",H22-TODAY()) | K22: =IF(OR(A22="",H22="",I22="Complete"),0,MAX(0,TODAY()-H22)) | O22: =IF(OR(A22="",I22="Complete",K22<=0),"",COUNTIFS(I$5:I$34,"<>Complete",K$5:K$34,">"&K22)+COUNTIFS(I$5:I22,"<>Complete",K$5:K22,K22)) | P22: =IF(OR(A22="",I22="Complete"),"",B22&"|"&(COUNTIFS(B$5:B$34,B22,I$5:I$34,"<>Complete",K$5:K$34,">"&K22)+COUNTIFS(B$5:B22,B22,I$5:I22,"<>Complete",K$5:K22,K22)))
J23: =IF(OR(A23="",I23="Complete",H23=""),"",H23-TODAY()) | K23: =IF(OR(A23="",H23="",I23="Complete"),0,MAX(0,TODAY()-H23)) | O23: =IF(OR(A23="",I23="Complete",K23<=0),"",COUNTIFS(I$5:I$34,"<>Complete",K$5:K$34,">"&K23)+COUNTIFS(I$5:I23,"<>Complete",K$5:K23,K23)) | P23: =IF(OR(A23="",I23="Complete"),"",B23&"|"&(COUNTIFS(B$5:B$34,B23,I$5:I$34,"<>Complete",K$5:K$34,">"&K23)+COUNTIFS(B$5:B23,B23,I$5:I23,"<>Complete",K$5:K23,K23)))
J24: =IF(OR(A24="",I24="Complete",H24=""),"",H24-TODAY()) | K24: =IF(OR(A24="",H24="",I24="Complete"),0,MAX(0,TODAY()-H24)) | O24: =IF(OR(A24="",I24="Complete",K24<=0),"",COUNTIFS(I$5:I$34,"<>Complete",K$5:K$34,">"&K24)+COUNTIFS(I$5:I24,"<>Complete",K$5:K24,K24)) | P24: =IF(OR(A24="",I24="Complete"),"",B24&"|"&(COUNTIFS(B$5:B$34,B24,I$5:I$34,"<>Complete",K$5:K$34,">"&K24)+COUNTIFS(B$5:B24,B24,I$5:I24,"<>Complete",K$5:K24,K24)))
J25: =IF(OR(A25="",I25="Complete",H25=""),"",H25-TODAY()) | K25: =IF(OR(A25="",H25="",I25="Complete"),0,MAX(0,TODAY()-H25)) | O25: =IF(OR(A25="",I25="Complete",K25<=0),"",COUNTIFS(I$5:I$34,"<>Complete",K$5:K$34,">"&K25)+COUNTIFS(I$5:I25,"<>Complete",K$5:K25,K25)) | P25: =IF(OR(A25="",I25="Complete"),"",B25&"|"&(COUNTIFS(B$5:B$34,B25,I$5:I$34,"<>Complete",K$5:K$34,">"&K25)+COUNTIFS(B$5:B25,B25,I$5:I25,"<>Complete",K$5:K25,K25)))
J26: =IF(OR(A26="",I26="Complete",H26=""),"",H26-TODAY()) | K26: =IF(OR(A26="",H26="",I26="Complete"),0,MAX(0,TODAY()-H26)) | O26: =IF(OR(A26="",I26="Complete",K26<=0),"",COUNTIFS(I$5:I$34,"<>Complete",K$5:K$34,">"&K26)+COUNTIFS(I$5:I26,"<>Complete",K$5:K26,K26)) | P26: =IF(OR(A26="",I26="Complete"),"",B26&"|"&(COUNTIFS(B$5:B$34,B26,I$5:I$34,"<>Complete",K$5:K$34,">"&K26)+COUNTIFS(B$5:B26,B26,I$5:I26,"<>Complete",K$5:K26,K26)))
J27: =IF(OR(A27="",I27="Complete",H27=""),"",H27-TODAY()) | K27: =IF(OR(A27="",H27="",I27="Complete"),0,MAX(0,TODAY()-H27)) | O27: =IF(OR(A27="",I27="Complete",K27<=0),"",COUNTIFS(I$5:I$34,"<>Complete",K$5:K$34,">"&K27)+COUNTIFS(I$5:I27,"<>Complete",K$5:K27,K27)) | P27: =IF(OR(A27="",I27="Complete"),"",B27&"|"&(COUNTIFS(B$5:B$34,B27,I$5:I$34,"<>Complete",K$5:K$34,">"&K27)+COUNTIFS(B$5:B27,B27,I$5:I27,"<>Complete",K$5:K27,K27)))
J28: =IF(OR(A28="",I28="Complete",H28=""),"",H28-TODAY()) | K28: =IF(OR(A28="",H28="",I28="Complete"),0,MAX(0,TODAY()-H28)) | O28: =IF(OR(A28="",I28="Complete",K28<=0),"",COUNTIFS(I$5:I$34,"<>Complete",K$5:K$34,">"&K28)+COUNTIFS(I$5:I28,"<>Complete",K$5:K28,K28)) | P28: =IF(OR(A28="",I28="Complete"),"",B28&"|"&(COUNTIFS(B$5:B$34,B28,I$5:I$34,"<>Complete",K$5:K$34,">"&K28)+COUNTIFS(B$5:B28,B28,I$5:I28,"<>Complete",K$5:K28,K28)))
J29: =IF(OR(A29="",I29="Complete",H29=""),"",H29-TODAY()) | K29: =IF(OR(A29="",H29="",I29="Complete"),0,MAX(0,TODAY()-H29)) | O29: =IF(OR(A29="",I29="Complete",K29<=0),"",COUNTIFS(I$5:I$34,"<>Complete",K$5:K$34,">"&K29)+COUNTIFS(I$5:I29,"<>Complete",K$5:K29,K29)) | P29: =IF(OR(A29="",I29="Complete"),"",B29&"|"&(COUNTIFS(B$5:B$34,B29,I$5:I$34,"<>Complete",K$5:K$34,">"&K29)+COUNTIFS(B$5:B29,B29,I$5:I29,"<>Complete",K$5:K29,K29)))
J30: =IF(OR(A30="",I30="Complete",H30=""),"",H30-TODAY()) | K30: =IF(OR(A30="",H30="",I30="Complete"),0,MAX(0,TODAY()-H30)) | O30: =IF(OR(A30="",I30="Complete",K30<=0),"",COUNTIFS(I$5:I$34,"<>Complete",K$5:K$34,">"&K30)+COUNTIFS(I$5:I30,"<>Complete",K$5:K30,K30)) | P30: =IF(OR(A30="",I30="Complete"),"",B30&"|"&(COUNTIFS(B$5:B$34,B30,I$5:I$34,"<>Complete",K$5:K$34,">"&K30)+COUNTIFS(B$5:B30,B30,I$5:I30,"<>Complete",K$5:K30,K30)))
... J34: =IF(OR(A34="",I34="Complete",H34=""),"",H34-TODAY()) | K34: =IF(OR(A34="",H34="",I34="Complete"),0,MAX(0,TODAY()-H34)) | O34: =IF(OR(A34="",I34="Complete",K34<=0),"",COUNTIFS(I$5:I$34,"<>Complete",K$5:K$34,">"&K34)+COUNTIFS(I$5:I34,"<>Complete",K$5:K34,K34)) | P34: =IF(OR(A34="",I34="Complete"),"",B34&"|"&(COUNTIFS(B$5:B$34,B34,I$5:I$34,"<>Complete",K$5:K$34,">"&K34)+COUNTIFS(B$5:B34,B34,I$5:I34,"<>Complete",K$5:K34,K34)))

Sheet 08_RACI_MATRIX
A1: RACI MATRIX
A2: Who is Responsible, Accountable, Consulted and Informed for each activity. Exactly one Accountable per row - the validation column flags any row that breaks the rule.
A3: SAMPLE DATA - every sample record is marked SAMPLE in the Notes column. Delete or overwrite them freely: all formulas, KPIs, charts and drop-downs keep working.
A4: Activity / Deliverable | B4: Sponsor | C4: PMO | D4: Project Manager | E4: Business Owner | F4: IT Lead | G4: Developer | H4: Finance | I4: Procurement | J4: QA | K4: End Users | L4: A Count | M4: Validation | N4: Notes
A5: Project charter approval | B5: A | C5: R | D5: C | E5: C | F5: I | G5: I | H5: C | I5: I | J5: I | K5: I | L5: =IF(A5="","",COUNTIF($A5:K5,"A")) | M5: =IF(A5="","",IF(L5=1,"OK",IF(L5=0,"ERROR - NO ACCOUNTABLE","ERROR - MULTIPLE ACCOUNTABLE"))) | N5: SAMPLE
A6: Requirements sign-off | B6: I | C6: C | D6: R | E6: A | F6: C | G6: I | H6: C | I6: I | J6: C | K6: C | L6: =IF(A6="","",COUNTIF($A6:K6,"A")) | M6: =IF(A6="","",IF(L6=1,"OK",IF(L6=0,"ERROR - NO ACCOUNTABLE","ERROR - MULTIPLE ACCOUNTABLE"))) | N6: SAMPLE
A7: Solution design | B7: I | C7: I | D7: A | E7: C | F7: R | G7: R | H7: I | I7: I | J7: C | K7: I | L7: =IF(A7="","",COUNTIF($A7:K7,"A")) | M7: =IF(A7="","",IF(L7=1,"OK",IF(L7=0,"ERROR - NO ACCOUNTABLE","ERROR - MULTIPLE ACCOUNTABLE"))) | N7: SAMPLE
A8: Development / configuration | B8: I | C8: I | D8: A | E8: I | F8: C | G8: R | H8: I | I8: I | J8: C | K8: I | L8: =IF(A8="","",COUNTIF($A8:K8,"A")) | M8: =IF(A8="","",IF(L8=1,"OK",IF(L8=0,"ERROR - NO ACCOUNTABLE","ERROR - MULTIPLE ACCOUNTABLE"))) | N8: SAMPLE
A9: Data migration | B9: I | C9: I | D9: A | E9: C | F9: R | G9: R | H9: C | I9: I | J9: C | K9: I | L9: =IF(A9="","",COUNTIF($A9:K9,"A")) | M9: =IF(A9="","",IF(L9=1,"OK",IF(L9=0,"ERROR - NO ACCOUNTABLE","ERROR - MULTIPLE ACCOUNTABLE"))) | N9: SAMPLE
A10: Testing and UAT | B10: I | C10: I | D10: C | E10: R | F10: C | G10: R | H10: I | I10: I | J10: A | K10: R | L10: =IF(A10="","",COUNTIF($A10:K10,"A")) | M10: =IF(A10="","",IF(L10=1,"OK",IF(L10=0,"ERROR - NO ACCOUNTABLE","ERROR - MULTIPLE ACCOUNTABLE"))) | N10: SAMPLE
A11: Go-live approval | B11: A | C11: I | D11: R | E11: C | F11: C | G11: I | H11: C | I11: I | J11: C | K11: I | L11: =IF(A11="","",COUNTIF($A11:K11,"A")) | M11: =IF(A11="","",IF(L11=1,"OK",IF(L11=0,"ERROR - NO ACCOUNTABLE","ERROR - MULTIPLE ACCOUNTABLE"))) | N11: SAMPLE
A12: Budget approval | B12: C | C12: I | D12: R | E12: I | F12: I | G12: I | H12: A | I12: I | J12: I | K12: I | L12: =IF(A12="","",COUNTIF($A12:K12,"A")) | M12: =IF(A12="","",IF(L12=1,"OK",IF(L12=0,"ERROR - NO ACCOUNTABLE","ERROR - MULTIPLE ACCOUNTABLE"))) | N12: SAMPLE
A13: Vendor selection | B13: I | C13: I | D13: R | E13: I | F13: C | G13: I | H13: C | I13: A | J13: C | K13: I | L13: =IF(A13="","",COUNTIF($A13:K13,"A")) | M13: =IF(A13="","",IF(L13=1,"OK",IF(L13=0,"ERROR - NO ACCOUNTABLE","ERROR - MULTIPLE ACCOUNTABLE"))) | N13: SAMPLE
A14: Lessons learned | B14: I | C14: A | D14: R | E14: C | F14: C | G14: I | H14: I | I14: I | J14: C | K14: C | L14: =IF(A14="","",COUNTIF($A14:K14,"A")) | M14: =IF(A14="","",IF(L14=1,"OK",IF(L14=0,"ERROR - NO ACCOUNTABLE","ERROR - MULTIPLE ACCOUNTABLE"))) | N14: SAMPLE
L15: =IF(A15="","",COUNTIF($A15:K15,"A")) | M15: =IF(A15="","",IF(L15=1,"OK",IF(L15=0,"ERROR - NO ACCOUNTABLE","ERROR - MULTIPLE ACCOUNTABLE")))
L16: =IF(A16="","",COUNTIF($A16:K16,"A")) | M16: =IF(A16="","",IF(L16=1,"OK",IF(L16=0,"ERROR - NO ACCOUNTABLE","ERROR - MULTIPLE ACCOUNTABLE")))
L17: =IF(A17="","",COUNTIF($A17:K17,"A")) | M17: =IF(A17="","",IF(L17=1,"OK",IF(L17=0,"ERROR - NO ACCOUNTABLE","ERROR - MULTIPLE ACCOUNTABLE")))
L18: =IF(A18="","",COUNTIF($A18:K18,"A")) | M18: =IF(A18="","",IF(L18=1,"OK",IF(L18=0,"ERROR - NO ACCOUNTABLE","ERROR - MULTIPLE ACCOUNTABLE")))
L19: =IF(A19="","",COUNTIF($A19:K19,"A")) | M19: =IF(A19="","",IF(L19=1,"OK",IF(L19=0,"ERROR - NO ACCOUNTABLE","ERROR - MULTIPLE ACCOUNTABLE")))
L20: =IF(A20="","",COUNTIF($A20:K20,"A")) | M20: =IF(A20="","",IF(L20=1,"OK",IF(L20=0,"ERROR - NO ACCOUNTABLE","ERROR - MULTIPLE ACCOUNTABLE")))
L21: =IF(A21="","",COUNTIF($A21:K21,"A")) | M21: =IF(A21="","",IF(L21=1,"OK",IF(L21=0,"ERROR - NO ACCOUNTABLE","ERROR - MULTIPLE ACCOUNTABLE")))
L22: =IF(A22="","",COUNTIF($A22:K22,"A")) | M22: =IF(A22="","",IF(L22=1,"OK",IF(L22=0,"ERROR - NO ACCOUNTABLE","ERROR - MULTIPLE ACCOUNTABLE")))
L23: =IF(A23="","",COUNTIF($A23:K23,"A")) | M23: =IF(A23="","",IF(L23=1,"OK",IF(L23=0,"ERROR - NO ACCOUNTABLE","ERROR - MULTIPLE ACCOUNTABLE")))
L24: =IF(A24="","",COUNTIF($A24:K24,"A")) | M24: =IF(A24="","",IF(L24=1,"OK",IF(L24=0,"ERROR - NO ACCOUNTABLE","ERROR - MULTIPLE ACCOUNTABLE")))
L25: =IF(A25="","",COUNTIF($A25:K25,"A")) | M25: =IF(A25="","",IF(L25=1,"OK",IF(L25=0,"ERROR - NO ACCOUNTABLE","ERROR - MULTIPLE ACCOUNTABLE")))
L26: =IF(A26="","",COUNTIF($A26:K26,"A")) | M26: =IF(A26="","",IF(L26=1,"OK",IF(L26=0,"ERROR - NO ACCOUNTABLE","ERROR - MULTIPLE ACCOUNTABLE")))
... L34: =IF(A34="","",COUNTIF($A34:K34,"A")) | M34: =IF(A34="","",IF(L34=1,"OK",IF(L34=0,"ERROR - NO ACCOUNTABLE","ERROR - MULTIPLE ACCOUNTABLE")))

Sheet 09_STAKEHOLDERS
A1: STAKEHOLDER REGISTER
A2: People who can help or block the portfolio, with influence/interest classification (automatic) and the engagement approach for each one.
A3: SAMPLE DATA - every sample record is marked SAMPLE in the Notes column. Delete or overwrite them freely: all formulas, KPIs, charts and drop-downs keep working.
A4: Stakeholder | B4: Role | C4: Department | D4: Influence | E4: Interest | F4: Engagement Level | G4: Power/Interest Class | H4: Information Needed | I4: Frequency | J4: Channel | K4: Owner | L4: Strategy | M4: Notes
A5: Sarah Mitchell (CEO) | B5: Executive Sponsor | C5: Operations | D5: High | E5: High | F5: Supportive | G5: =IF(A5="","",IF(AND(D5="High",E5="High"),"Manage Closely",IF(D5="High","Keep Satisfied",IF(E5="High","Keep Informed","Monitor")))) | H5: Portfolio RAG, top risks, decisions required | I5: Weekly | J5: Executive dashboard | K5: Priya Raman | L5: SAMPLE - manage closely, decision-ready pack every Friday | M5: SAMPLE
A6: Ahmed Khan | B6: Project Manager | C6: IT | D6: High | E6: High | F6: Leading | G6: =IF(A6="","",IF(AND(D6="High",E6="High"),"Manage Closely",IF(D6="High","Keep Satisfied",IF(E6="High","Keep Informed","Monitor")))) | H6: Schedule, RAID, actions | I6: Daily | J6: Teams | K6: Priya Raman | L6: SAMPLE - daily stand-up and action follow-up | M6: SAMPLE
A7: Finance Director | B7: Budget Owner | C7: Finance | D7: High | E7: Medium | F7: Neutral | G7: =IF(A7="","",IF(AND(D7="High",E7="High"),"Manage Closely",IF(D7="High","Keep Satisfied",IF(E7="High","Keep Informed","Monitor")))) | H7: Actual vs approved cost, forecast | I7: Monthly | J7: Cost report | K7: Priya Raman | L7: SAMPLE - keep satisfied with cost accuracy | M7: SAMPLE
A8: HR Director | B8: Business Owner | C8: HR | D8: High | E8: High | F8: Supportive | G8: =IF(A8="","",IF(AND(D8="High",E8="High"),"Manage Closely",IF(D8="High","Keep Satisfied",IF(E8="High","Keep Informed","Monitor")))) | H8: HR system progress, UAT readiness | I8: Weekly | J8: Meeting | K8: David Okoro | L8: SAMPLE - manage closely | M8: SAMPLE
A9: IT Operations Lead | B9: Technical Lead | C9: IT | D9: Medium | E9: High | F9: Leading | G9: =IF(A9="","",IF(AND(D9="High",E9="High"),"Manage Closely",IF(D9="High","Keep Satisfied",IF(E9="High","Keep Informed","Monitor")))) | H9: Infrastructure tasks, cut-over plan | I9: Weekly | J9: Teams | K9: Tom Becker | L9: SAMPLE - keep engaged | M9: SAMPLE
A10: Procurement Manager | B10: Supplier Manager | C10: Procurement | D10: Medium | E10: Medium | F10: Neutral | G10: =IF(A10="","",IF(AND(D10="High",E10="High"),"Manage Closely",IF(D10="High","Keep Satisfied",IF(E10="High","Keep Informed","Monitor")))) | H10: Purchase requests, quotations | I10: Bi-Weekly | J10: Email | K10: Lisa Chen | L10: SAMPLE - keep informed | M10: SAMPLE
A11: End User Community | B11: System Users | C11: Operations | D11: Low | E11: High | F11: Resistant | G11: =IF(A11="","",IF(AND(D11="High",E11="High"),"Manage Closely",IF(D11="High","Keep Satisfied",IF(E11="High","Keep Informed","Monitor")))) | H11: Training, go-live dates, changes | I11: Weekly | J11: Newsletter | K11: Maria Silva | L11: SAMPLE - keep informed, early training | M11: SAMPLE
A12: Internal Audit | B12: Assurance | C12: Finance | D12: Medium | E12: Low | F12: Unaware | G12: =IF(A12="","",IF(AND(D12="High",E12="High"),"Manage Closely",IF(D12="High","Keep Satisfied",IF(E12="High","Keep Informed","Monitor")))) | H12: Control evidence, approvals | I12: Quarterly | J12: Report | K12: Grace Alemu | L12: SAMPLE - monitor | M12: SAMPLE
G13: =IF(A13="","",IF(AND(D13="High",E13="High"),"Manage Closely",IF(D13="High","Keep Satisfied",IF(E13="High","Keep Informed","Monitor"))))
G14: =IF(A14="","",IF(AND(D14="High",E14="High"),"Manage Closely",IF(D14="High","Keep Satisfied",IF(E14="High","Keep Informed","Monitor"))))
G15: =IF(A15="","",IF(AND(D15="High",E15="High"),"Manage Closely",IF(D15="High","Keep Satisfied",IF(E15="High","Keep Informed","Monitor"))))
G16: =IF(A16="","",IF(AND(D16="High",E16="High"),"Manage Closely",IF(D16="High","Keep Satisfied",IF(E16="High","Keep Informed","Monitor"))))
G17: =IF(A17="","",IF(AND(D17="High",E17="High"),"Manage Closely",IF(D17="High","Keep Satisfied",IF(E17="High","Keep Informed","Monitor"))))
G18: =IF(A18="","",IF(AND(D18="High",E18="High"),"Manage Closely",IF(D18="High","Keep Satisfied",IF(E18="High","Keep Informed","Monitor"))))
G19: =IF(A19="","",IF(AND(D19="High",E19="High"),"Manage Closely",IF(D19="High","Keep Satisfied",IF(E19="High","Keep Informed","Monitor"))))
G20: =IF(A20="","",IF(AND(D20="High",E20="High"),"Manage Closely",IF(D20="High","Keep Satisfied",IF(E20="High","Keep Informed","Monitor"))))
G21: =IF(A21="","",IF(AND(D21="High",E21="High"),"Manage Closely",IF(D21="High","Keep Satisfied",IF(E21="High","Keep Informed","Monitor"))))
G22: =IF(A22="","",IF(AND(D22="High",E22="High"),"Manage Closely",IF(D22="High","Keep Satisfied",IF(E22="High","Keep Informed","Monitor"))))
G23: =IF(A23="","",IF(AND(D23="High",E23="High"),"Manage Closely",IF(D23="High","Keep Satisfied",IF(E23="High","Keep Informed","Monitor"))))
G24: =IF(A24="","",IF(AND(D24="High",E24="High"),"Manage Closely",IF(D24="High","Keep Satisfied",IF(E24="High","Keep Informed","Monitor"))))
... G34: =IF(A34="","",IF(AND(D34="High",E34="High"),"Manage Closely",IF(D34="High","Keep Satisfied",IF(E34="High","Keep Informed","Monitor"))))
A36: POWER / INTEREST MATRIX - AUTOMATIC COUNTS
A37: INFLUENCE \ INTEREST | C37: LOW | G37: MEDIUM | K37: HIGH
A38: HIGH POWER | C38: =COUNTIFS($D$5:$D$34,"High",$E$5:$E$34,"Low") | G38: =COUNTIFS($D$5:$D$34,"High",$E$5:$E$34,"Medium") | K38: =COUNTIFS($D$5:$D$34,"High",$E$5:$E$34,"High")
A39: MEDIUM POWER | C39: =COUNTIFS($D$5:$D$34,"Medium",$E$5:$E$34,"Low") | G39: =COUNTIFS($D$5:$D$34,"Medium",$E$5:$E$34,"Medium") | K39: =COUNTIFS($D$5:$D$34,"Medium",$E$5:$E$34,"High")
A40: LOW POWER | C40: =COUNTIFS($D$5:$D$34,"Low",$E$5:$E$34,"Low") | G40: =COUNTIFS($D$5:$D$34,"Low",$E$5:$E$34,"Medium") | K40: =COUNTIFS($D$5:$D$34,"Low",$E$5:$E$34,"High")
A42: MANAGE CLOSELY | D42: KEEP SATISFIED | G42: KEEP INFORMED | J42: MONITOR
A43: =COUNTIF($G$5:$G$34,"Manage Closely") | D43: =COUNTIF($G$5:$G$34,"Keep Satisfied") | G43: =COUNTIF($G$5:$G$34,"Keep Informed") | J43: =COUNTIF($G$5:$G$34,"Monitor")
A44: Counts come from the Influence and Interest drop-downs above; the Power/Interest Class column (and this matrix) updates the moment either changes.

Sheet 10_CHANGE_CONTROL
A1: CHANGE CONTROL
A2: Formal change requests with impact assessment and approval. No change may be implemented unless the approval status is Approved - the compliance column flags breaches.
A3: SAMPLE DATA - every sample record is marked SAMPLE in the Notes column. Delete or overwrite them freely: all formulas, KPIs, charts and drop-downs keep working.
A4: Change ID | B4: Project | C4: Requested By | D4: Request Date | E4: Change Description | F4: Reason | G4: Scope Impact | H4: Schedule Impact (days) | I4: Cost Impact | J4: Risk Impact | K4: Priority | L4: Impact Assessment | M4: Recommendation | N4: Approval Status | O4: Approved By | P4: Approval Date | Q4: Implementation Status | R4: Compliance Check | S4: Notes | T4: PendingRank
A5: CR-001 | B5: ERP Implementation | C5: Business Owner | D5: 46297 | E5: Add payroll variance report to scope | F5: New finance reporting requirement | G5: Medium | H5: 12 | I5: 28000 | J5: Medium | K5: High | L5: Adds 12 days and 28,000; no impact on go-live if built in sprint 4 | M5: Approve - funded from contingency | N5: Pending | Q5: Not Started | R5: =IF(A5="","",IF(AND(N5<>"Approved",OR(Q5="In Progress",Q5="Complete")),"INVALID - NOT APPROVED",IF(N5="Pending","Awaiting Approval","OK"))) | S5: SAMPLE - awaiting steering approval | T5: =IF(OR(A5="",N5<>"Pending"),"",COUNTIF(N$5:N$34,"Pending")-COUNTIF(N$5:N5,"Pending")+1)
A6: CR-002 | B6: Network Infrastructure Upgrade | C6: IT Operations Lead | D6: 46285 | E6: Upgrade switch count from 8 to 10 | F6: Two extra floors in scope | G6: Medium | H6: 5 | I6: 15000 | J6: Low | K6: Medium | L6: 5 extra days, 15,000 cost | M6: Approve | N6: Approved | O6: Priya Raman | P6: 46290 | Q6: Complete | R6: =IF(A6="","",IF(AND(N6<>"Approved",OR(Q6="In Progress",Q6="Complete")),"INVALID - NOT APPROVED",IF(N6="Pending","Awaiting Approval","OK"))) | S6: SAMPLE - ordered additional switches | T6: =IF(OR(A6="",N6<>"Pending"),"",COUNTIF(N$5:N$34,"Pending")-COUNTIF(N$5:N6,"Pending")+1)
A7: CR-003 | B7: HR Management System | C7: HR Director | D7: 46301 | E7: Include mobile self-service module | F7: Executive request | G7: High | H7: 45 | I7: 95000 | J7: High | K7: High | L7: 45 days and 95,000 - breaches approved amount | M7: Reject for phase 1, re-plan for phase 2 | N7: Pending | Q7: Not Started | R7: =IF(A7="","",IF(AND(N7<>"Approved",OR(Q7="In Progress",Q7="Complete")),"INVALID - NOT APPROVED",IF(N7="Pending","Awaiting Approval","OK"))) | S7: SAMPLE - needs sponsor decision | T7: =IF(OR(A7="",N7<>"Pending"),"",COUNTIF(N$5:N$34,"Pending")-COUNTIF(N$5:N7,"Pending")+1)
A8: CR-004 | B8: Website Development | C8: Marketing Manager | D8: 46293 | E8: Add e-commerce checkout | F8: Nice-to-have | G8: High | H8: 60 | I8: 70000 | J8: High | K8: Low | L8: Doubles remaining scope | M8: Reject - out of phase 1 | N8: Rejected | P8: 46296 | Q8: Not Started | R8: =IF(A8="","",IF(AND(N8<>"Approved",OR(Q8="In Progress",Q8="Complete")),"INVALID - NOT APPROVED",IF(N8="Pending","Awaiting Approval","OK"))) | S8: SAMPLE | T8: =IF(OR(A8="",N8<>"Pending"),"",COUNTIF(N$5:N$34,"Pending")-COUNTIF(N$5:N8,"Pending")+1)
A9: CR-005 | B9: Office Security Upgrade | C9: Facilities Manager | D9: 46280 | E9: Add two extra camera locations | F9: Blind spots identified | G9: Low | H9: 2 | I9: 4500 | J9: Low | K9: Medium | L9: 2 days, 4,500 cost - within contingency | M9: Approve | N9: Approved | O9: Priya Raman | P9: 46283 | Q9: In Progress | R9: =IF(A9="","",IF(AND(N9<>"Approved",OR(Q9="In Progress",Q9="Complete")),"INVALID - NOT APPROVED",IF(N9="Pending","Awaiting Approval","OK"))) | S9: SAMPLE | T9: =IF(OR(A9="",N9<>"Pending"),"",COUNTIF(N$5:N$34,"Pending")-COUNTIF(N$5:N9,"Pending")+1)
R10: =IF(A10="","",IF(AND(N10<>"Approved",OR(Q10="In Progress",Q10="Complete")),"INVALID - NOT APPROVED",IF(N10="Pending","Awaiting Approval","OK"))) | T10: =IF(OR(A10="",N10<>"Pending"),"",COUNTIF(N$5:N$34,"Pending")-COUNTIF(N$5:N10,"Pending")+1)
R11: =IF(A11="","",IF(AND(N11<>"Approved",OR(Q11="In Progress",Q11="Complete")),"INVALID - NOT APPROVED",IF(N11="Pending","Awaiting Approval","OK"))) | T11: =IF(OR(A11="",N11<>"Pending"),"",COUNTIF(N$5:N$34,"Pending")-COUNTIF(N$5:N11,"Pending")+1)
R12: =IF(A12="","",IF(AND(N12<>"Approved",OR(Q12="In Progress",Q12="Complete")),"INVALID - NOT APPROVED",IF(N12="Pending","Awaiting Approval","OK"))) | T12: =IF(OR(A12="",N12<>"Pending"),"",COUNTIF(N$5:N$34,"Pending")-COUNTIF(N$5:N12,"Pending")+1)
R13: =IF(A13="","",IF(AND(N13<>"Approved",OR(Q13="In Progress",Q13="Complete")),"INVALID - NOT APPROVED",IF(N13="Pending","Awaiting Approval","OK"))) | T13: =IF(OR(A13="",N13<>"Pending"),"",COUNTIF(N$5:N$34,"Pending")-COUNTIF(N$5:N13,"Pending")+1)
R14: =IF(A14="","",IF(AND(N14<>"Approved",OR(Q14="In Progress",Q14="Complete")),"INVALID - NOT APPROVED",IF(N14="Pending","Awaiting Approval","OK"))) | T14: =IF(OR(A14="",N14<>"Pending"),"",COUNTIF(N$5:N$34,"Pending")-COUNTIF(N$5:N14,"Pending")+1)
R15: =IF(A15="","",IF(AND(N15<>"Approved",OR(Q15="In Progress",Q15="Complete")),"INVALID - NOT APPROVED",IF(N15="Pending","Awaiting Approval","OK"))) | T15: =IF(OR(A15="",N15<>"Pending"),"",COUNTIF(N$5:N$34,"Pending")-COUNTIF(N$5:N15,"Pending")+1)
R16: =IF(A16="","",IF(AND(N16<>"Approved",OR(Q16="In Progress",Q16="Complete")),"INVALID - NOT APPROVED",IF(N16="Pending","Awaiting Approval","OK"))) | T16: =IF(OR(A16="",N16<>"Pending"),"",COUNTIF(N$5:N$34,"Pending")-COUNTIF(N$5:N16,"Pending")+1)
R17: =IF(A17="","",IF(AND(N17<>"Approved",OR(Q17="In Progress",Q17="Complete")),"INVALID - NOT APPROVED",IF(N17="Pending","Awaiting Approval","OK"))) | T17: =IF(OR(A17="",N17<>"Pending"),"",COUNTIF(N$5:N$34,"Pending")-COUNTIF(N$5:N17,"Pending")+1)
R18: =IF(A18="","",IF(AND(N18<>"Approved",OR(Q18="In Progress",Q18="Complete")),"INVALID - NOT APPROVED",IF(N18="Pending","Awaiting Approval","OK"))) | T18: =IF(OR(A18="",N18<>"Pending"),"",COUNTIF(N$5:N$34,"Pending")-COUNTIF(N$5:N18,"Pending")+1)
R19: =IF(A19="","",IF(AND(N19<>"Approved",OR(Q19="In Progress",Q19="Complete")),"INVALID - NOT APPROVED",IF(N19="Pending","Awaiting Approval","OK"))) | T19: =IF(OR(A19="",N19<>"Pending"),"",COUNTIF(N$5:N$34,"Pending")-COUNTIF(N$5:N19,"Pending")+1)
R20: =IF(A20="","",IF(AND(N20<>"Approved",OR(Q20="In Progress",Q20="Complete")),"INVALID - NOT APPROVED",IF(N20="Pending","Awaiting Approval","OK"))) | T20: =IF(OR(A20="",N20<>"Pending"),"",COUNTIF(N$5:N$34,"Pending")-COUNTIF(N$5:N20,"Pending")+1)
R21: =IF(A21="","",IF(AND(N21<>"Approved",OR(Q21="In Progress",Q21="Complete")),"INVALID - NOT APPROVED",IF(N21="Pending","Awaiting Approval","OK"))) | T21: =IF(OR(A21="",N21<>"Pending"),"",COUNTIF(N$5:N$34,"Pending")-COUNTIF(N$5:N21,"Pending")+1)
... R34: =IF(A34="","",IF(AND(N34<>"Approved",OR(Q34="In Progress",Q34="Complete")),"INVALID - NOT APPROVED",IF(N34="Pending","Awaiting Approval","OK"))) | T34: =IF(OR(A34="",N34<>"Pending"),"",COUNTIF(N$5:N$34,"Pending")-COUNTIF(N$5:N34,"Pending")+1)

Sheet 11_COST_MANAGEMENT
A1: COST MANAGEMENT
A2: Approved amount vs committed, actual and forecast cost by category. Variance, utilisation and the category summary are calculated automatically.
A3: SAMPLE DATA - every sample record is marked SAMPLE in the Notes column. Delete or overwrite them freely: all formulas, KPIs, charts and drop-downs keep working.
A4: Cost ID | B4: Project | C4: Cost Category | D4: Owner | E4: Total Approved Amount | F4: Committed Cost | G4: Actual Cost | H4: Forecast Cost | I4: Budget Variance | J4: Forecast Variance | K4: Cost Utilisation % | L4: Cost Status | M4: Notes
